[{"title":"Tesco British Salted Block Butter 250G ++","unit_price":"1.99","currency":"£","price_per_quantity":"7.96","quantity":"1","url":"https://www.tesco.com/groceries/en-GB/products/290920510","image":"https://digitalcontent.api.tesco.com/v2/media/ghs/ded8f8d0-a1df-46b7-8c5e-f849a950e7e0/720c431a-68c2-45c3-b86e-7dd101d89de4.jpeg?h=540&w=540","rating":"4.3","category":"Fresh Food / Milk, Butter & Eggs / Butter, Spreads & Margarine","number_of_reviews":"64","short_desc":"","nutrition":[{"Energy":"306kJ, 74kcal","nutr_percent":"4%"},{"Fat":"8.2g","nutr_percent":"12%"},{"Saturates":"5.2g","nutr_percent":"26%"},{"Sugars":"<0.1g","nutr_percent":"<1%"},{"Salt":"0.15g","nutr_percent":"3%"}],"ingredients":"Butter (. ), Salt (1.5%).","description":"Suitable for vegetarians 2 teaspoons Energy 306kJ 74kcal 4% of the reference intake Fat 8.2g high 12% of the reference intake Saturates 5.2g high 26% of the reference intake Sugars <0.1g low <1% of the reference intake Salt 0.15g medium 3% of the reference intake of the reference intake * Typical values per 100g: Energy 3062kJ / 745kcal Product Description Salted butter. Minimum 80% milk fat. 100% British Milk Expertly churned for a smooth creamy taste Pack size: 250G Information Ingredients INGREDIENTS: Butter ( Milk ), Salt (1.5%). Storage Suitable for home freezing. Ideally freeze as soon as possible after purchase but always by 'use by' date shown. nDefrost thoroughly for a minimum of 12 hours in the fridge. Once defrosted, do not refreeze. nnKeep refrigerated. Produce of Produced in the U.K., using milk from the U.K. Number of uses 25 Servings Recycling info Wrap. Don't Recycle Return to Tesco Stores Ltd., Welwyn Garden City AL7 1GA, U.K Net Contents 250g e Nutrition Typical Values Per 100g 2 teaspoons (10g) Energy 3062kJ / 745kcal 306kJ / 74kcal Fat 82.2g 8.2g Saturates 52.1g 5.2g Carbohydrate 0.6g <0.1g Sugars 0.6g <0.1g Fibre 0g 0g Protein 0.6g <0.1g Salt 1.50g 0.15g * Reference intake of an average adult (8400 kJ / 2000 kcal) - - As sold - -","cooking_instructions":"","storage":"Suitable for home freezing. Ideally freeze as soon as possible after purchase but always by 'use by' date shown. nDefrost thoroughly for a minimum of 12 hours in the fridge. Once defrosted, do not refreeze. nnKeep refrigerated.","allergy_info":"","produce_of":"Produced in the U.K., using milk from the U.K.","number_of_uses":"25 Servings","recycling_info":"Wrap. Don't Recycle","return_to":"Tesco Stores Ltd.,. Welwyn Garden City AL7 1GA,. U.K","net_content":"250g e","nutrition_per_unit":[{"Typical Values":"Fat","Per 100g":"82.2g","2 teaspoons (10g)":"8.2g"},{"Typical Values":"Saturates","Per 100g":"52.1g","2 teaspoons (10g)":"5.2g"},{"Typical Values":"Carbohydrate","Per 100g":"0.6g","2 teaspoons (10g)":"<0.1g"},{"Typical Values":"Sugars","Per 100g":"0.6g","2 teaspoons (10g)":"<0.1g"},{"Typical Values":"Fibre","Per 100g":"0g","2 teaspoons (10g)":"0g"},{"Typical Values":"Protein","Per 100g":"0.6g","2 teaspoons (10g)":"<0.1g"},{"Typical Values":"Salt","Per 100g":"1.50g","2 teaspoons (10g)":"0.15g"},{"Typical Values":"* Reference intake of an average adult (8400 kJ / 2000 kcal)","Per 100g":"-","2 teaspoons (10g)":"-"},{"Typical Values":"As sold","Per 100g":"-","2 teaspoons (10g)":"-"}],"gtin13":"05054775188239","sku":"290920510","timestamp":"2023-01-31T12:05:58Z"},{"title":"Tesco Tomato and Basil Pasta 200g","unit_price":"1.00","currency":"£","price_per_quantity":"NaN","quantity":"1","url":"https://www.tesco.com/groceries/en-GB/products/312713682","image":"https://digitalcontent.api.tesco.com/v2/media/ghs-mktg/b0b04216-fa73-466d-a9d7-c9fcfa1ce9b3/no-image.jpeg?h=540&w=540","rating":"No ratings yet","category":"Fresh Food / Fresh Salad, Coleslaw & Sandwich Fillers / Salad Pots & Pasta Salad","number_of_reviews":"","short_desc":"","nutrition":[],"ingredients":"","description":"Product Description Tesco Tomato & Basil Pasta 200g Pack size: 200G Information","cooking_instructions":"","storage":"","allergy_info":"","produce_of":"","number_of_uses":"","recycling_info":"","return_to":"","net_content":"","nutrition_per_unit":[],"gtin13":"05059697758690","sku":"312713682","timestamp":"2023-01-31T12:06:11Z"},{"title":"Tesco Flat Peach Minimum 4 Pack","unit_price":"1.50","currency":"£","price_per_quantity":"0.38","quantity":"1","url":"https://www.tesco.com/groceries/en-GB/products/268663138","image":"https://digitalcontent.api.tesco.com/v2/media/ghs/e1489a1c-7c92-49ef-ace0-f973dff8d619/0f6d6781-3712-4935-b1d8-6866647e79fb.jpeg?h=540&w=540","rating":"2","category":"Fresh Food / Fresh Fruit / Peaches, Nectarines, Plums & Apricots","number_of_reviews":"118","short_desc":"","nutrition":[{"Energy":"138kJ, 33kcal","nutr_percent":"2%"},{"Fat":"0.1g","nutr_percent":"0%"},{"Saturates":"<0.1g","nutr_percent":"0%"},{"Sugars":"6.5g","nutr_percent":"7%"},{"Salt":"<0.01g","nutr_percent":"0%"}],"ingredients":"Peach","description":"One typical peach Energy 138kJ 33kcal 2% of the reference intake Fat 0.1g low 0% of the reference intake Saturates <0.1g low 0% of the reference intake Sugars 6.5g medium 7% of the reference intake Salt <0.01g low 0% of the reference intake of the reference intake * Typical values per 100g: Energy 162kJ / 38kcal Product Description Peaches. Hand picked Leave to ripen for 2   3 days for a sweet, fragrant flavour Hand picked Leave to ripen for 2   3 days for a sweet, fragrant flavour Information Ingredients Peach Storage Ripen firm fruit at room temperature. Refrigerate ripe fruit. Bring to room temperature before eating. Produce of Produce of Spain, South Africa, Chile Preparation and Usage Wash before use. Number of uses 5 Servings Return to Tesco Stores Ltd., Welwyn Garden City AL7 1GA, U.K Net Contents 4A/5B/6C Nutrition Typical Values Per 100g One typical peach (85g) Energy 162kJ / 38kcal 138kJ / 33kcal Fat 0.1g 0.1g Saturates <0.1g <0.1g Carbohydrate 7.6g 6.5g Sugars 7.6g 6.5g Fibre 1.5g 1.3g Protein 1.0g 0.9g Salt <0.01g <0.01g * Reference intake of an average adult (8400 kJ / 2000 kcal) - - As sold - -","cooking_instructions":"Wash before use.","storage":"Ripen firm fruit at room temperature. Refrigerate ripe fruit. Bring to room temperature before eating.","allergy_info":"","produce_of":"Produce of Spain, South Africa, Chile","number_of_uses":"5 Servings","recycling_info":"","return_to":"Tesco Stores Ltd.,. Welwyn Garden City AL7 1GA,. U.K","net_content":"4A/5B/6C","nutrition_per_unit":[{"Typical Values":"Fat","Per 100g":"0.1g","One typical peach (85g)":"0.1g"},{"Typical Values":"Saturates","Per 100g":"<0.1g","One typical peach (85g)":"<0.1g"},{"Typical Values":"Carbohydrate","Per 100g":"7.6g","One typical peach (85g)":"6.5g"},{"Typical Values":"Sugars","Per 100g":"7.6g","One typical peach (85g)":"6.5g"},{"Typical Values":"Fibre","Per 100g":"1.5g","One typical peach (85g)":"1.3g"},{"Typical Values":"Protein","Per 100g":"1.0g","One typical peach (85g)":"0.9g"},{"Typical Values":"Salt","Per 100g":"<0.01g","One typical peach (85g)":"<0.01g"},{"Typical Values":"* Reference intake of an average adult (8400 kJ / 2000 kcal)","Per 100g":"-","One typical peach (85g)":"-"},{"Typical Values":"As sold","Per 100g":"-","One typical peach (85g)":"-"}],"gtin13":"00000010112762","sku":"268663138","timestamp":"2023-01-31T12:06:15Z"},{"title":"Crackd The No-Egg Egg Replacer 346G","unit_price":"3.00","currency":"£","price_per_quantity":"8.67","quantity":"1","url":"https://www.tesco.com/groceries/en-GB/products/311935187","image":"https://digitalcontent.api.tesco.com/v2/media/ghs/7ec75bfa-d07a-4224-bebb-8b1ec698ccc5/9bcd5aff-dc3f-443b-85c0-5b4f96750951_870124359.jpeg?h=540&w=540","rating":"2.3","category":"Fresh Food / Chilled Vegetarian & Vegan / Egg Alternative","number_of_reviews":"3","short_desc":"","nutrition":[],"ingredients":"Water, Pea Protein (3%), Corn Oil, Thickener (Methyl Cellulose), Pea Starch, Gelling Agent (Gellan Gum), Flavourings, Firming Agent (Calcium Lactate), Dried Inactive Yeast, Acid (Lactic Acid), Black Salt, Acidity Regulator (Potassium Bitartrate), Colour (Beta Carotene), Stabilisers (Calcium Carbonate, Guar Gum, Cellulose Gum), Vitamins (D & B12), Dextrose","description":"Suitable for vegans Product Description Liquid Plant Based High Pressure Processed Egg Replacer. Recipes? Check 'em out online at CRACKD.COM Yeah, you read that right! Made, not laid. There's no egg in this bottle, and that may just change your life. Well... at least in the kitchen. Treated with HPP (High Pressure Process). to maintain flavour, freshness and nutrition. Plant - Based Low Fat Pea Protein Amazing Scrambled Great Pancakes Golden Yorkshires Rich in Protein, Vitamin B12 & D No artificial colours or flavourings Suitable for vegans Pack size: 346G Low Fat Rich in Protein, Vitamin B12 & D Information Ingredients Water, Pea Protein (3%), Corn Oil, Thickener (Methyl Cellulose), Pea Starch, Gelling Agent (Gellan Gum), Flavourings, Firming Agent (Calcium Lactate), Dried Inactive Yeast, Acid (Lactic Acid), Black Salt, Acidity Regulator (Potassium Bitartrate), Colour (Beta Carotene), Stabilisers (Calcium Carbonate, Guar Gum, Cellulose Gum), Vitamins (D & B12), Dextrose Storage Keep me chilledKeep refrigerated.nOnce opened, use within 7 days.nDo not exceed use by date. Cooking Instructions Microwave Instructions: You can also now scramble Crackd in your microwave (750w). For one portion of scrambled (120g): full power 1 min. Stir and cook for another 1 min. Remove from microwave, stir again, and let rest for a further minute before serving. Oven cook Instructions: You can still bake with Crackd. We recommend reducing the temperature of your usual recipe by 10C and cooking for an extra 15 minutes. Be sure to keep an eye on it as everyone's ovens are different! Shallow Fry Instructions: For one portion of scrambled (120g): heat a little oil in a non-stick pan on a medium heat, add in Crackd and stir immediately. Continue stirring for 3-5 minutes until firm. Preparation and Usage Always shake well before use Number of uses Equivalent to 6 eggs! 1 egg = 58g for baking Additives Free From Artificial Colours Free From Artificial Flavours Name and address Crackd Plant Heads, Beeches Farm, Icknield Way, Tring, Herts, Return to Crackd Plant Heads, Beeches Farm, Icknield Way, Tring, Herts, HP23 4LA. howcanwehelp@plantheads.co.uk Net Contents 346g ℮ Nutrition Typical Values Per 100g Energy Values 190 - 45 Fat 2.0 (Of which Saturates) < 0.2 Carbohydrate 4.2 (Of which Sugars) 0.2 Fibre < 0.5 Protein 2.7 Salt 0.3 Vitamin D 2.40 (48% RI*) Vitamin B12 1.43 (59% RI*) Vitamins - *Reference Intake of an average adult (8400kJ/2000kcal) -","cooking_instructions":"Microwave. Instructions: You can also now scramble Crackd in your microwave (750w). For one portion of scrambled (120g): full power 1 min. Stir and cook for another 1 min. Remove from microwave, stir again, and let rest for a further minute before serving.. Oven cook. Instructions: You can still bake with Crackd. We recommend reducing the temperature of your usual recipe by 10C and cooking for an extra 15 minutes. Be sure to keep an eye on it as everyone's ovens are different!. Shallow Fry. Instructions: For one portion of scrambled (120g): heat a little oil in a non-stick pan on a medium heat, add in Crackd and stir immediately. Continue stirring for 3-5 minutes until firm.","storage":"Keep me chilledKeep refrigerated.nOnce opened, use within 7 days.nDo not exceed use by date.","allergy_info":"","produce_of":"","number_of_uses":"Equivalent to 6 eggs! 1 egg = 58g for baking","recycling_info":"","return_to":"Crackd. Plant Heads,. Beeches Farm,. Icknield Way,. Tring,. Herts,. HP23 4LA.. howcanwehelp@plantheads.co.uk","net_content":"346g ℮","nutrition_per_unit":[{"Typical Values":"-","Per 100g":"45"},{"Typical Values":"Fat","Per 100g":"2.0"},{"Typical Values":"(Of which Saturates)","Per 100g":"< 0.2"},{"Typical Values":"Carbohydrate","Per 100g":"4.2"},{"Typical Values":"(Of which Sugars)","Per 100g":"0.2"},{"Typical Values":"Fibre","Per 100g":"< 0.5"},{"Typical Values":"Protein","Per 100g":"2.7"},{"Typical Values":"Salt","Per 100g":"0.3"},{"Typical Values":"Vitamin D","Per 100g":"2.40 (48% RI*)"},{"Typical Values":"Vitamin B12","Per 100g":"1.43 (59% RI*)"},{"Typical Values":"Vitamins","Per 100g":"-"},{"Typical Values":"*Reference Intake of an average adult (8400kJ/2000kcal)","Per 100g":"-"}],"gtin13":"05000326011969","sku":"311935187","timestamp":"2023-01-31T12:06:18Z"},{"title":"Takul Halal Meatball Marinara Pizza 360G","unit_price":"4.00","currency":"£","price_per_quantity":"1.11","quantity":"1","url":"https://www.tesco.com/groceries/en-GB/products/312722020","image":"https://digitalcontent.api.tesco.com/v2/media/ghs/46dddd25-f9fa-4454-851b-19e79c6f6ddb/6b3eac1e-2904-43b4-b459-bccf4802c8bd.jpeg?h=540&w=540","rating":"No ratings yet","category":"Fresh Food / World Foods / Halal Food","number_of_reviews":"","short_desc":"","nutrition":[],"ingredients":"Pizza Base (56%) (. Flour, Water,. , Extra Virgin Olive Oil, Salt, Flour Enhancer (. Starch, Flour Treatment Agent: Ascorbic Acid, L-Cystein), Yeast, Dried. Extract), Tomato Sauce (15%) (Tomato Pulp, Salt, Oregano), Mozzarella. (19%), Spicy Meatball (15%) (Beef (70%), Beef Fat, Breadcrumbs (. Flour, Salt, Yeast), Potato Starch, Onion, Salt, Paprika, Dextrose, Spices, Herbs, Colour (Ammonia Caramel), Flavour), Cheddar. (2%)","description":"Product Description Takul Halal Meatball Marinara Pizza 360G Takul Meatball Marinara Pizza Our stonebaked pizzas are made from dough which is slow proved for 24 hours, hand stretched & generously topped top with a rich tomato sauce, beef meatballs & mozzarella cheese. Takul is about making life easier & tastier, with the peace of mind that everything we create is 100% Halal. From our Halal Kitchen to yours Topped with a rich tomato sauce, beef meatballs & mozzarella cheese Halal Pack size: 360G Information Ingredients Pizza Base (56%) ( Wheat Flour, Water, Durum Semolina , Extra Virgin Olive Oil, Salt, Flour Enhancer ( Wheat Starch, Flour Treatment Agent: Ascorbic Acid, L-Cystein), Yeast, Dried Barley Malt Extract), Tomato Sauce (15%) (Tomato Pulp, Salt, Oregano), Mozzarella Cheese (19%), Spicy Meatball (15%) (Beef (70%), Beef Fat, Breadcrumbs ( Wheat Flour, Salt, Yeast), Potato Starch, Onion, Salt, Paprika, Dextrose, Spices, Herbs, Colour (Ammonia Caramel), Flavour), Cheddar Cheese (2%) Allergy Information May also contain Soy, Nuts and Fish. For allergens including Cereals containing Gluten and Milk, see ingredients in bold. Storage Keep refrigerated between 0°C and 5°C and consume by the 'use by' date - see side of pack. Not suitable for home freezing. Cooking Instructions Oven cook Instructions: Remove all outer packaging, place product directly onto the middle shelf in a preheated oven 200°C / Fan 180°C / Gas Mark 6. 6-8 minutes. All appliances vary, these instructions are given as a guide only. Ensure product is piping hot before serving. Do not reheat. Produce of Produced and packed in the EU using EU Beef Number of uses This pack contains 2 servings Warnings WARNING: Although every care has been taken to remove bones, some may still remain. Recycling info Carton. Recyclable Name and address Produced and packed for: Stonehouse Foods Ltd, PO Box 13059, Dunmow, CM6 9DS. Return to Stonehouse Foods Ltd, PO Box 13059, Dunmow, CM6 9DS. takul.co.uk Net Contents 360g Nutrition Typical Values Per 100g Per 180g serving Energy 862kJ 1552kJ - 205kcal 369kcal Fat 6.7g 12.1g of which Saturates 3.3g 5.9g Carbohydrate 27.0g 48.6g of which sugars 1.7g 3.1g Protein 9.3g 16.7g Salt 1.48g 2.66g This pack contains 2 servings - - Safety information View more safety information WARNING: Although every care has been taken to remove bones, some may still remain.","cooking_instructions":"Oven cook. Instructions: Remove all outer packaging, place product directly onto the middle shelf in a preheated oven 200°C / Fan 180°C / Gas Mark 6.. 6-8 minutes.. All appliances vary, these instructions are given as a guide only.. Ensure product is piping hot before serving.. Do not reheat.","storage":"Keep refrigerated between 0°C and 5°C and consume by the 'use by' date - see side of pack. Not suitable for home freezing.","allergy_info":"May also contain Soy, Nuts and Fish. For allergens including Cereals containing Gluten and Milk, see ingredients in bold.","produce_of":"Produced and packed in the EU using EU Beef","number_of_uses":"This pack contains 2 servings","recycling_info":"Carton. Recyclable","return_to":"Stonehouse Foods Ltd,. PO Box 13059,. Dunmow,. CM6 9DS.. takul.co.uk","net_content":"360g","nutrition_per_unit":[{"Typical Values":"-","Per 100g":"205kcal","Per 180g serving":"369kcal"},{"Typical Values":"Fat","Per 100g":"6.7g","Per 180g serving":"12.1g"},{"Typical Values":"of which Saturates","Per 100g":"3.3g","Per 180g serving":"5.9g"},{"Typical Values":"Carbohydrate","Per 100g":"27.0g","Per 180g serving":"48.6g"},{"Typical Values":"of which sugars","Per 100g":"1.7g","Per 180g serving":"3.1g"},{"Typical Values":"Protein","Per 100g":"9.3g","Per 180g serving":"16.7g"},{"Typical Values":"Salt","Per 100g":"1.48g","Per 180g serving":"2.66g"},{"Typical Values":"This pack contains 2 servings","Per 100g":"-","Per 180g serving":"-"}],"gtin13":"05060902800301","sku":"312722020","timestamp":"2023-01-31T12:06:22Z"},{"title":"Wicked Kitchen Wicked Wellington 485G","unit_price":"5.00","currency":"£","price_per_quantity":"10.31","quantity":"1","url":"https://www.tesco.com/groceries/en-GB/products/309788274","image":"https://digitalcontent.api.tesco.com/v2/media/ghs/77e3ef8b-d2ce-48bf-b272-40a55238d04b/385accc9-630d-4d1c-9d57-915100dd3555.jpeg?h=540&w=540","rating":"2.3","category":"Fresh Food / Chilled Vegetarian & Vegan / Roasts","number_of_reviews":"3","short_desc":"","nutrition":[{"Energy":"1355kJ, 325kcal","nutr_percent":"16%"},{"Fat":"19.6g","nutr_percent":"28%"},{"Saturates":"7.3g","nutr_percent":"37%"},{"Sugars":"4.2g","nutr_percent":"5%"},{"Salt":"0.66g","nutr_percent":"11%"}],"ingredients":"Water, Wheat Flour [. Flour, Calcium Carbonate, Iron, Niacin, Thiamin], Palm Oil, Mushroom, Rapeseed Oil,. Protein Concentrate, Onion, White Onion, Rice Flour, Stabilisers (Methyl Cellulose, Tetrasodium Diphosphate, Disodium Diphosphate), Maize Flour, Salt, Colour (Beetroot Red), Dextrose, Ascorbic Acid, Caramelised Sugar Powder, Garlic Purée, Potato Starch, Sunflower Oil, Tapioca Starch, Parsley, Red Pepper Flakes, Porcini Mushroom Powder, Maize Starch, Sugar, Black Pepper, White Pepper, Thyme, Mace, Sage, Yeast, Psyllium Husk Fibre.","description":"Suitable for vegans 1/4 of a pack (114g**) Energy 1355kJ 325kcal 16% of the reference intake Fat 19.6g - 28% of the reference intake Saturates 7.3g - 37% of the reference intake Sugars 4.2g - 5% of the reference intake Salt 0.66g - 11% of the reference intake of the reference intake * Typical values per 100g: Energy 1189kJ / 285kcal Product Description Mushroom, soya protein, onion and seasoning wrapped in puff pastry. SOYA PROTEIN Give your celebration some welly  Seasoned soya in golden lattice flaky puff pastry with roasted garlic & herb mushroom duxelles This product is part of the Tesco Festive Food to Order range. In order for us to get it to you in time for delivery or Click+Collect slot, please checkout by 11.45pm on 14th December. Beyond this point Festive Food to Order products cannot be changed, but non Festive Food to order products can still be amended. Pack size: 485G Information Ingredients INGREDIENTS: Water, Wheat Flour [ Wheat Flour, Calcium Carbonate, Iron, Niacin, Thiamin], Palm Oil, Mushroom, Rapeseed Oil, Soya Protein Concentrate, Onion, White Onion, Rice Flour, Stabilisers (Methyl Cellulose, Tetrasodium Diphosphate, Disodium Diphosphate), Maize Flour, Salt, Colour (Beetroot Red), Dextrose, Ascorbic Acid, Caramelised Sugar Powder, Garlic Purée, Potato Starch, Sunflower Oil, Tapioca Starch, Parsley, Red Pepper Flakes, Porcini Mushroom Powder, Maize Starch, Sugar, Black Pepper, White Pepper, Thyme, Mace, Sage, Yeast, Psyllium Husk Fibre. Allergy Information For allergens, including cereals containing gluten, see ingredients in bold. Storage Suitable for home freezing. Ideally freeze as soon as possible after purchase but always by 'use by' date shown. nKeep refrigerated. Cooking Instructions Oven Instructions: 200°C/Fan 180°C/Gas 6 55 - 65 mins Place onto a non-stick baking tray, in the centre of a pre-heated oven Stand for 1 minute. Oven from frozen Instructions: 200°C/Fan 180°C/Gas 6 60 - 70 mins Place onto a non-stick baking tray, in the centre of a pre-heated oven Stand for 1 minute. Number of uses 4 Servings Recycling info Film. Recycle at large supermarketnSleeve. RecyclenTray. Recycle Return to Tesco Stores Ltd., Welwyn Garden City AL7 1GA, U.K Net Contents 485g e Nutrition Typical Values Per 100g 1/4 of a pack (114g**) Energy 1189kJ / 285kcal 1355kJ / 325kcal Fat 17.2g 19.6g Saturates 6.4g 7.3g Carbohydrate 24.5g 28.0g Sugars 3.7g 4.2g Fibre 2.5g 2.9g Protein 6.8g 7.7g Salt 0.58g 0.66g * Reference intake of an average adult (8400 kJ / 2000 kcal) - - ** When cooked according to instructions 485g typically weighs 455g. - - When cooked according to instructions. - -","cooking_instructions":"Oven. Instructions: 200°C/Fan 180°C/Gas 6 55 - 65 mins Place onto a non-stick baking tray, in the centre of a pre-heated oven Stand for 1 minute.. Oven from frozen. Instructions: 200°C/Fan 180°C/Gas 6 60 - 70 mins Place onto a non-stick baking tray, in the centre of a pre-heated oven Stand for 1 minute.","storage":"Suitable for home freezing. Ideally freeze as soon as possible after purchase but always by 'use by' date shown. nKeep refrigerated.","allergy_info":"For allergens, including cereals containing gluten, see ingredients in bold.","produce_of":"","number_of_uses":"4 Servings","recycling_info":"Film. Recycle at large supermarketnSleeve. RecyclenTray. Recycle","return_to":"Tesco Stores Ltd.,. Welwyn Garden City AL7 1GA,. U.K","net_content":"485g e","nutrition_per_unit":[{"Typical Values":"Fat","Per 100g":"17.2g","1/4 of a pack (114g**)":"19.6g"},{"Typical Values":"Saturates","Per 100g":"6.4g","1/4 of a pack (114g**)":"7.3g"},{"Typical Values":"Carbohydrate","Per 100g":"24.5g","1/4 of a pack (114g**)":"28.0g"},{"Typical Values":"Sugars","Per 100g":"3.7g","1/4 of a pack (114g**)":"4.2g"},{"Typical Values":"Fibre","Per 100g":"2.5g","1/4 of a pack (114g**)":"2.9g"},{"Typical Values":"Protein","Per 100g":"6.8g","1/4 of a pack (114g**)":"7.7g"},{"Typical Values":"Salt","Per 100g":"0.58g","1/4 of a pack (114g**)":"0.66g"},{"Typical Values":"* Reference intake of an average adult (8400 kJ / 2000 kcal)","Per 100g":"-","1/4 of a pack (114g**)":"-"},{"Typical Values":"** When cooked according to instructions 485g typically weighs 455g.","Per 100g":"-","1/4 of a pack (114g**)":"-"},{"Typical Values":"When cooked according to instructions.","Per 100g":"-","1/4 of a pack (114g**)":"-"}],"gtin13":"05059697404122","sku":"309788274","timestamp":"2023-01-31T12:06:26Z"},{"title":"Tesco Mexican Style Rice & Beans 300G","unit_price":"2.00","currency":"£","price_per_quantity":"6.67","quantity":"1","url":"https://www.tesco.com/groceries/en-GB/products/312352987","image":"https://digitalcontent.api.tesco.com/v2/media/ghs/3c5823e9-7364-4fc0-94d8-a28066e88827/69b43028-92e5-4872-9e26-974d92e1ee58.jpeg?h=540&w=540","rating":"No ratings yet","category":"Fresh Food / Fresh Salad, Coleslaw & Sandwich Fillers / Salad Pots & Pasta Salad","number_of_reviews":"","short_desc":"Any 3 for 2 Clubcard Price - Cheapest Product Free - Selected Vegetables 80g - 800g Offer valid for delivery from 07/12/2022 until 26/09/2023","nutrition":[{"Energy":"667kJ, 158kcal","nutr_percent":"8%"},{"Fat":"3.3g","nutr_percent":"5%"},{"Saturates":"0.5g","nutr_percent":"3%"},{"Sugars":"2.0g","nutr_percent":"2%"},{"Salt":"0.42g","nutr_percent":"7%"}],"ingredients":"Cooked Rice (54%) [Water, Long Grain Rice], Sweetcorn, Black Turtle Beans (9%), Red Pepper, Onion, Coriander, Spinach, Lime Juice, Rapeseed Oil, Concentrated Lime Juice, Smoked Paprika, Garlic Purée, Cumin Seed, Chipotle Chilli Powder, Salt, Coriander Powder, Black Pepper, White Wine Vinegar.","description":"Suitable for vegetarians ½ of a pack Energy 667kJ 158kcal 8% of the reference intake Fat 3.3g low 5% of the reference intake Saturates 0.5g low 3% of the reference intake Sugars 2.0g low 2% of the reference intake Salt 0.42g low 7% of the reference intake of the reference intake * Typical values per 100g: Energy 445kJ / 106kcal Product Description Cooked rice, sweetcorn and black turtle beans with red pepper, onion, spinach, lime juice and spices. A mix of rice and black beans with sweetcorn, pepper & spinach, in a smoky chipotle dressing. with a smoky chipotle dressing Pack size: 300G Information Ingredients INGREDIENTS: Cooked Rice (54%) [Water, Long Grain Rice], Sweetcorn, Black Turtle Beans (9%), Red Pepper, Onion, Coriander, Spinach, Lime Juice, Rapeseed Oil, Concentrated Lime Juice, Smoked Paprika, Garlic Purée, Cumin Seed, Chipotle Chilli Powder, Salt, Coriander Powder, Black Pepper, White Wine Vinegar. Storage Not suitable for freezing. Keep refrigerated. Cooking Instructions Microwave Instructions: Remove label. 800W & 900W 2 mins Pierce film lid several times. Heat on full power. Leave to stand for 2 minutes after heating. Stir before serving. Number of uses 2 Servings Recycling info Pot. RecyclenFilm. Recycle at large supermarket Return to Tesco Stores Ltd., Welwyn Garden City AL7 1GA, U.K Net Contents 300g e Nutrition Typical Values Per 100g ½ of a pack (150g) Energy 445kJ / 106kcal 667kJ / 158kcal Fat 2.2g 3.3g Saturates 0.3g 0.5g Carbohydrate 17.5g 26.3g Sugars 1.3g 2.0g Fibre 2.5g 3.8g Protein 2.7g 4.1g Salt 0.28g 0.42g * Reference intake of an average adult (8400 kJ / 2000 kcal) - - When heated according to instructions. - -","cooking_instructions":"Microwave. Instructions: Remove label.. 800W & 900W 2 mins. Pierce film lid several times. Heat on full power. Leave to stand for 2 minutes after heating.. Stir before serving.","storage":"Not suitable for freezing. Keep refrigerated.","allergy_info":"","produce_of":"","number_of_uses":"2 Servings","recycling_info":"Pot. RecyclenFilm. Recycle at large supermarket","return_to":"Tesco Stores Ltd.,. Welwyn Garden City AL7 1GA,. U.K","net_content":"300g e","nutrition_per_unit":[{"Typical Values":"Fat","Per 100g":"2.2g","½ of a pack (150g)":"3.3g"},{"Typical Values":"Saturates","Per 100g":"0.3g","½ of a pack (150g)":"0.5g"},{"Typical Values":"Carbohydrate","Per 100g":"17.5g","½ of a pack (150g)":"26.3g"},{"Typical Values":"Sugars","Per 100g":"1.3g","½ of a pack (150g)":"2.0g"},{"Typical Values":"Fibre","Per 100g":"2.5g","½ of a pack (150g)":"3.8g"},{"Typical Values":"Protein","Per 100g":"2.7g","½ of a pack (150g)":"4.1g"},{"Typical Values":"Salt","Per 100g":"0.28g","½ of a pack (150g)":"0.42g"},{"Typical Values":"* Reference intake of an average adult (8400 kJ / 2000 kcal)","Per 100g":"-","½ of a pack (150g)":"-"},{"Typical Values":"When heated according to instructions.","Per 100g":"-","½ of a pack (150g)":"-"}],"gtin13":"05059697770647","sku":"312352987","timestamp":"2023-01-31T12:06:30Z"},{"title":"Tesco Deli Liver Sausage 100G","unit_price":"0.85","currency":"£","price_per_quantity":"0.85","quantity":"1","url":"https://www.tesco.com/groceries/en-GB/products/312715947","image":"https://digitalcontent.api.tesco.com/v2/media/ghs/82d4ebc4-9f98-43ea-943e-92d6f852d107/f0d82516-6623-4c43-b3c6-2f5bf710ff8a.jpeg?h=540&w=540","rating":"1","category":"Fresh Food / Cooked Meats, Antipasti & Dips / Deli Counter","number_of_reviews":"1","short_desc":"","nutrition":[{"Energy":"104kJ, 25kcal","nutr_percent":"1%"},{"Fat":"1.8g","nutr_percent":"3%"},{"Saturates":"0.7g","nutr_percent":"4%"},{"Sugars":"0.4g","nutr_percent":"<1%"},{"Salt":"0.17g","nutr_percent":"3%"}],"ingredients":"Pork (25%), Pork Rind, Pork Liver (22%), Water, Potato Starch, Wheat Flour [. Flour, Calcium Carbonate, Iron, Niacin, Thiamin], Pea Fibre, Salt, Sugar, Spices, Stabilisers (Disodium Diphosphate, Tetrasodium Diphosphate), Onion Powder,. Flour, Onion,. Sugar, Lemon Peel, Antioxidant (Sodium Ascorbate), Preservative (Sodium Nitrite), Rapeseed Oil.","description":"One slice Energy 104kJ 25kcal 1% of the reference intake Fat 1.8g medium 3% of the reference intake Saturates 0.7g high 4% of the reference intake Sugars 0.4g low <1% of the reference intake Salt 0.17g medium 3% of the reference intake of the reference intake * Typical values per 100g: Energy 803kJ / 193kcal Product Description Chopped and shaped pork liver sausage slices with added water. British pork liver sausage delicately seasoned with a herb and spice blend. Pack size: 100G Information Ingredients INGREDIENTS: Pork (25%), Pork Rind, Pork Liver (22%), Water, Potato Starch, Wheat Flour [ Wheat Flour, Calcium Carbonate, Iron, Niacin, Thiamin], Pea Fibre, Salt, Sugar, Spices, Stabilisers (Disodium Diphosphate, Tetrasodium Diphosphate), Onion Powder, Mustard Flour, Onion, Milk Sugar, Lemon Peel, Antioxidant (Sodium Ascorbate), Preservative (Sodium Nitrite), Rapeseed Oil. Allergy Information For allergens, including cereals containing gluten, see ingredients in bold. Legal information Packaged in a protective atmosphere Storage Not suitable for freezing. Keep refrigerated. Once opened, consume within 2 days and by 'use by' date shown. Produce of Made using British pork. Number of uses 8 Servings Recycling info Tray. RecyclenFilm. Recycle at large supermarket Return to Tesco Stores Ltd., Welwyn Garden City AL7 1GA, U.K Net Contents 100g e Nutrition Typical Values Per 100g One slice (13g) Energy 803kJ / 193kcal 104kJ / 25kcal Fat 14.0g 1.8g Saturates 5.1g 0.7g Carbohydrate 2.8g 0.4g Sugars 2.8g 0.4g Fibre 1.2g 0.2g Protein 13.4g 1.7g Salt 1.30g 0.17g * Reference intake of an average adult (8400 kJ / 2000 kcal) - - As sold - -","cooking_instructions":"","storage":"Not suitable for freezing. Keep refrigerated. Once opened, consume within 2 days and by 'use by' date shown.","allergy_info":"For allergens, including cereals containing gluten, see ingredients in bold.","produce_of":"Made using British pork.","number_of_uses":"8 Servings","recycling_info":"Tray. RecyclenFilm. Recycle at large supermarket","return_to":"Tesco Stores Ltd.,. Welwyn Garden City AL7 1GA,. U.K","net_content":"100g e","nutrition_per_unit":[{"Typical Values":"Fat","Per 100g":"14.0g","One slice (13g)":"1.8g"},{"Typical Values":"Saturates","Per 100g":"5.1g","One slice (13g)":"0.7g"},{"Typical Values":"Carbohydrate","Per 100g":"2.8g","One slice (13g)":"0.4g"},{"Typical Values":"Sugars","Per 100g":"2.8g","One slice (13g)":"0.4g"},{"Typical Values":"Fibre","Per 100g":"1.2g","One slice (13g)":"0.2g"},{"Typical Values":"Protein","Per 100g":"13.4g","One slice (13g)":"1.7g"},{"Typical Values":"Salt","Per 100g":"1.30g","One slice (13g)":"0.17g"},{"Typical Values":"* Reference intake of an average adult (8400 kJ / 2000 kcal)","Per 100g":"-","One slice (13g)":"-"},{"Typical Values":"As sold","Per 100g":"-","One slice (13g)":"-"}],"gtin13":"05059697706745","sku":"312715947","timestamp":"2023-01-31T12:06:35Z"},{"title":"Tesco 4 British Turkey Burgers 454G","unit_price":"3.20","currency":"£","price_per_quantity":"7.05","quantity":"1","url":"https://www.tesco.com/groceries/en-GB/products/312361256","image":"https://digitalcontent.api.tesco.com/v2/media/ghs/5ef3b9c7-81b9-4d51-9b99-55a002a38093/5159182b-8b25-4a6e-8de2-79b1754fb1f0.jpeg?h=540&w=540","rating":"3","category":"Fresh Food / Fresh Meat & Poultry / Fresh Turkey","number_of_reviews":"4","short_desc":"","nutrition":[{"Energy":"698kJ, 166kcal","nutr_percent":"8%"},{"Fat":"7.3g","nutr_percent":"10%"},{"Saturates":"2.1g","nutr_percent":"11%"},{"Sugars":"0.2g","nutr_percent":"<1%"},{"Salt":"0.65g","nutr_percent":"11%"}],"ingredients":"Turkey (84%), Water, Rice Flour, Gram Flour, Pea Fibre, Spices, Onion Powder, Garlic Powder, Salt, Maize Starch, Emulsifier (Trisodium Diphosphate), Herbs, Yeast Extract, Preservative (Sodium. ), Antioxidant (Citric Acid), Dextrose.","description":"One burger Energy 698kJ 166kcal 8% of the reference intake Fat 7.3g medium 10% of the reference intake Saturates 2.1g medium 11% of the reference intake Sugars 0.2g low <1% of the reference intake Salt 0.65g medium 11% of the reference intake of the reference intake * Typical values per 100g: Energy 751kJ / 179kcal Product Description 4 Seasoned turkey burgers. BRITISH TURKEY lightly seasoned for extra flavour Pack size: 454G Information Ingredients INGREDIENTS: Turkey (84%), Water, Rice Flour, Gram Flour, Pea Fibre, Spices, Onion Powder, Garlic Powder, Salt, Maize Starch, Emulsifier (Trisodium Diphosphate), Herbs, Yeast Extract, Preservative (Sodium Metabisulphite ), Antioxidant (Citric Acid), Dextrose. Allergy Information For allergens, see ingredients in bold. Legal information Packaged in a protective atmosphere Storage Suitable for home freezing. Ideally freeze as soon as possible after purchase but always by 'use by' date shown. nNot suitable for cooking from frozen. nFollow the preparation guidelines above. nOnce defrosted use within 24 hours and do not refreeze. nDefrost thoroughly for a minimum of 24 hours in the fridge.nnKeep refrigerated. nOnce opened, use immediately. Cooking Instructions Microwave Instructions: Not suitable for microwave cooking. Grill Instructions: Time: 14-16 mins Temperature: Medium Place under a pre-heated grill for 14-16 minutes. Turn occasionally. Produce of Made using British turkey. Number of uses 4 Servings Warnings Caution: Although every care has been taken to remove bones, some may remain.Caution: Always wash hands, surfaces and utensils after contact with raw meat..Caution: This product contains raw meat.. Recycling info Tray. RecyclenFilm. Don't Recycle Return to Tesco Stores Ltd., Welwyn Garden City AL7 1GA, U.K Net Contents 454g e Nutrition Typical Values Per 100g One burger (92g**) Energy 751kJ / 179kcal 698kJ / 166kcal Fat 7.8g 7.3g Saturates 2.3g 2.1g Carbohydrate 4.7g 4.4g Sugars 0.2g 0.2g Fibre 1.0g 0.9g Protein 22.0g 20.5g Salt 0.70g 0.65g * Reference intake of an average adult (8400 kJ / 2000 kcal) - - When cooked according to instructions. - - ** When cooked according to instructions 454g typically weighs 372g. - - Safety information View more safety information Caution: Although every care has been taken to remove bones, some may remain.Caution: Always wash hands, surfaces and utensils after contact with raw meat..Caution: This product contains raw meat..","cooking_instructions":"Microwave. Instructions: Not suitable for microwave cooking.. Grill. Instructions: Time: 14-16 mins Temperature: Medium Place under a pre-heated grill for 14-16 minutes. Turn occasionally.","storage":"Suitable for home freezing. Ideally freeze as soon as possible after purchase but always by 'use by' date shown. nNot suitable for cooking from frozen. nFollow the preparation guidelines above. nOnce defrosted use within 24 hours and do not refreeze. nDefrost thoroughly for a minimum of 24 hours in the fridge.nnKeep refrigerated. nOnce opened, use immediately.","allergy_info":"For allergens, see ingredients in bold.","produce_of":"Made using British turkey.","number_of_uses":"4 Servings","recycling_info":"Tray. RecyclenFilm. Don't Recycle","return_to":"Tesco Stores Ltd.,. Welwyn Garden City AL7 1GA,. U.K","net_content":"454g e","nutrition_per_unit":[{"Typical Values":"Fat","Per 100g":"7.8g","One burger (92g**)":"7.3g"},{"Typical Values":"Saturates","Per 100g":"2.3g","One burger (92g**)":"2.1g"},{"Typical Values":"Carbohydrate","Per 100g":"4.7g","One burger (92g**)":"4.4g"},{"Typical Values":"Sugars","Per 100g":"0.2g","One burger (92g**)":"0.2g"},{"Typical Values":"Fibre","Per 100g":"1.0g","One burger (92g**)":"0.9g"},{"Typical Values":"Protein","Per 100g":"22.0g","One burger (92g**)":"20.5g"},{"Typical Values":"Salt","Per 100g":"0.70g","One burger (92g**)":"0.65g"},{"Typical Values":"* Reference intake of an average adult (8400 kJ / 2000 kcal)","Per 100g":"-","One burger (92g**)":"-"},{"Typical Values":"When cooked according to instructions.","Per 100g":"-","One burger (92g**)":"-"},{"Typical Values":"** When cooked according to instructions 454g typically weighs 372g.","Per 100g":"-","One burger (92g**)":"-"}],"gtin13":"05059697736957","sku":"312361256","timestamp":"2023-01-31T12:06:39Z"},{"title":"Tesco Deli Pork Haslet 120G 120G","unit_price":"1.25","currency":"£","price_per_quantity":"1.04","quantity":"1","url":"https://www.tesco.com/groceries/en-GB/products/312578357","image":"https://digitalcontent.api.tesco.com/v2/media/ghs/2903e8aa-47d7-4f9f-b76a-97842ed53fd3/a299bbc4-aa56-4aca-9a4d-c5d22904e017.jpeg?h=540&w=540","rating":"5","category":"Fresh Food / Cooked Meats, Antipasti & Dips / Deli Counter","number_of_reviews":"1","short_desc":"","nutrition":[{"Energy":"325kJ, 79kcal","nutr_percent":"4%"},{"Fat":"6.7g","nutr_percent":"10%"},{"Saturates":"2.4g","nutr_percent":"12%"},{"Sugars":"0.2g","nutr_percent":"<1%"},{"Salt":"0.39g","nutr_percent":"7%"}],"ingredients":"Pork (74%), Pork Fat, Wheat Flour [. Flour, Calcium Carbonate, Iron, Niacin, Thiamin], Kibbled Onion, Salt, Stabiliser (Tetrapotassium Diphosphate), Dried Onion, Sage, Parsley, Parsley Extract, Yeast, Sage Extract, White Pepper, Flavouring, Antioxidant (Sodium Ascorbate), Ginger, Pepper Extract, Pepper,. Flour, Onion, Sugar,. Sugar, Cardamom, Pimento, Lemon Peel Powder, Preservative (Sodium Nitrite), Chilli, Mace, Coriander, Nutmeg.","description":"One slice Energy 325kJ 79kcal 4% of the reference intake Fat 6.7g high 10% of the reference intake Saturates 2.4g high 12% of the reference intake Sugars 0.2g low <1% of the reference intake Salt 0.39g medium 7% of the reference intake of the reference intake * Typical values per 100g: Energy 1084kJ / 262kcal Product Description Seasoned, stuffed pork loaf made from chopped and shaped pork cuts. Sliced British pork meat loaf delicately seasoned with fragrant herbs. Pack size: 120G Information Ingredients INGREDIENTS: Pork (74%), Pork Fat, Wheat Flour [ Wheat Flour, Calcium Carbonate, Iron, Niacin, Thiamin], Kibbled Onion, Salt, Stabiliser (Tetrapotassium Diphosphate), Dried Onion, Sage, Parsley, Parsley Extract, Yeast, Sage Extract, White Pepper, Flavouring, Antioxidant (Sodium Ascorbate), Ginger, Pepper Extract, Pepper, Mustard Flour, Onion, Sugar, Milk Sugar, Cardamom, Pimento, Lemon Peel Powder, Preservative (Sodium Nitrite), Chilli, Mace, Coriander, Nutmeg. Allergy Information For allergens, including cereals containing gluten, see ingredients in bold. Legal information Packaged in a protective atmosphere Storage Not suitable for freezing. Keep refrigerated. Once opened, consume within 2 days and by 'use by' date shown. Produce of Made using British pork. Number of uses 4 Servings Recycling info Tray. RecyclenFilm. Recycle at large supermarket Return to Tesco Stores Ltd., Welwyn Garden City AL7 1GA, U.K Net Contents 120g e Nutrition Typical Values Per 100g One slice (30g) Energy 1084kJ / 262kcal 325kJ / 79kcal Fat 22.2g 6.7g Saturates 8.0g 2.4g Carbohydrate 0.8g 0.2g Sugars 0.8g 0.2g Fibre 3.2g 1.0g Protein 13.2g 4.0g Salt 1.30g 0.39g * Reference intake of an average adult (8400 kJ / 2000 kcal) - - As sold - -","cooking_instructions":"","storage":"Not suitable for freezing. Keep refrigerated. Once opened, consume within 2 days and by 'use by' date shown.","allergy_info":"For allergens, including cereals containing gluten, see ingredients in bold.","produce_of":"Made using British pork.","number_of_uses":"4 Servings","recycling_info":"Tray. RecyclenFilm. Recycle at large supermarket","return_to":"Tesco Stores Ltd.,. Welwyn Garden City AL7 1GA,. U.K","net_content":"120g e","nutrition_per_unit":[{"Typical Values":"Fat","Per 100g":"22.2g","One slice (30g)":"6.7g"},{"Typical Values":"Saturates","Per 100g":"8.0g","One slice (30g)":"2.4g"},{"Typical Values":"Carbohydrate","Per 100g":"0.8g","One slice (30g)":"0.2g"},{"Typical Values":"Sugars","Per 100g":"0.8g","One slice (30g)":"0.2g"},{"Typical Values":"Fibre","Per 100g":"3.2g","One slice (30g)":"1.0g"},{"Typical Values":"Protein","Per 100g":"13.2g","One slice (30g)":"4.0g"},{"Typical Values":"Salt","Per 100g":"1.30g","One slice (30g)":"0.39g"},{"Typical Values":"* Reference intake of an average adult (8400 kJ / 2000 kcal)","Per 100g":"-","One slice (30g)":"-"},{"Typical Values":"As sold","Per 100g":"-","One slice (30g)":"-"}],"gtin13":"05059512735592","sku":"312578357","timestamp":"2023-01-31T12:06:42Z"},{"title":"Tesco Deli Ox Tongue 100G","unit_price":"3.00","currency":"£","price_per_quantity":"3.00","quantity":"1","url":"https://www.tesco.com/groceries/en-GB/products/312208094","image":"https://digitalcontent.api.tesco.com/v2/media/ghs/f4d49cb1-63aa-4e28-b0b3-1d08e916a37c/c4da01e5-4832-4781-ae52-fed77d5f58c9.jpeg?h=540&w=540","rating":"No ratings yet","category":"Fresh Food / Cooked Meats, Antipasti & Dips / Deli Counter","number_of_reviews":"","short_desc":"","nutrition":[{"Energy":"208kJ, 50kcal","nutr_percent":"3%"},{"Fat":"3.2g","nutr_percent":"5%"},{"Saturates":"1.3g","nutr_percent":"7%"},{"Sugars":"0.2g","nutr_percent":"<1%"},{"Salt":"0.57g","nutr_percent":"10%"}],"ingredients":"Ox Tongue (92%), Salt, Sugar, Stabilisers (Pentasodium Triphosphate, Sodium Polyphosphate, Disodium Diphosphate), Beef Gelatine, Antioxidant (Sodium Ascorbate), Preservative (Sodium Nitrite).","description":"One slice Energy 208kJ 50kcal 3% of the reference intake Fat 3.2g medium 5% of the reference intake Saturates 1.3g high 7% of the reference intake Sugars 0.2g low <1% of the reference intake Salt 0.57g high 10% of the reference intake of the reference intake * Typical values per 100g: Energy 834kJ / 200kcal Product Description Cured and cooked ox tongue slices. Traditionally made and cured for an intense flavour 4 Slices Pack size: 100G Information Ingredients INGREDIENTS: Ox Tongue (92%), Salt, Sugar, Stabilisers (Pentasodium Triphosphate, Sodium Polyphosphate, Disodium Diphosphate), Beef Gelatine, Antioxidant (Sodium Ascorbate), Preservative (Sodium Nitrite). Legal information Packaged in a protective atmosphere Storage Not suitable for freezing. Keep refrigerated. Once opened, consume within 2 days and by 'use by' date shown. Produce of Made using British beef. Number of uses 4 Servings Recycling info Film. Recycle at large supermarketnTray. Recycle Return to Tesco Stores Ltd., Welwyn Garden City AL7 1GA, U.K Net Contents 100g e Nutrition Typical Values Per 100g One slice (25g) Energy 834kJ / 200kcal 208kJ / 50kcal Fat 13.0g 3.2g Saturates 5.1g 1.3g Carbohydrate 2.5g 0.6g Sugars 0.9g 0.2g Fibre 0.5g 0.1g Protein 18.1g 4.5g Salt 2.27g 0.57g * Reference intake of an average adult (8400 kJ / 2000 kcal) - - As sold - -","cooking_instructions":"","storage":"Not suitable for freezing. Keep refrigerated. Once opened, consume within 2 days and by 'use by' date shown.","allergy_info":"","produce_of":"Made using British beef.","number_of_uses":"4 Servings","recycling_info":"Film. Recycle at large supermarketnTray. Recycle","return_to":"Tesco Stores Ltd.,. Welwyn Garden City AL7 1GA,. U.K","net_content":"100g e","nutrition_per_unit":[{"Typical Values":"Fat","Per 100g":"13.0g","One slice (25g)":"3.2g"},{"Typical Values":"Saturates","Per 100g":"5.1g","One slice (25g)":"1.3g"},{"Typical Values":"Carbohydrate","Per 100g":"2.5g","One slice (25g)":"0.6g"},{"Typical Values":"Sugars","Per 100g":"0.9g","One slice (25g)":"0.2g"},{"Typical Values":"Fibre","Per 100g":"0.5g","One slice (25g)":"0.1g"},{"Typical Values":"Protein","Per 100g":"18.1g","One slice (25g)":"4.5g"},{"Typical Values":"Salt","Per 100g":"2.27g","One slice (25g)":"0.57g"},{"Typical Values":"* Reference intake of an average adult (8400 kJ / 2000 kcal)","Per 100g":"-","One slice (25g)":"-"},{"Typical Values":"As sold","Per 100g":"-","One slice (25g)":"-"}],"gtin13":"05059697727979","sku":"312208094","timestamp":"2023-01-31T12:06:46Z"},{"title":"This Isn't Beef Plant Based Burgers 226G","unit_price":"3.00","currency":"£","price_per_quantity":"13.27","quantity":"1","url":"https://www.tesco.com/groceries/en-GB/products/312350367","image":"https://digitalcontent.api.tesco.com/v2/media/ghs/87e09c9d-a865-4d1c-98aa-9b2d7a59b006/fd8e4ac9-1297-48b5-9989-1ed200cd86fd.jpeg?h=540&w=540","rating":"3","category":"Fresh Food / Chilled Vegetarian & Vegan / Burgers","number_of_reviews":"6","short_desc":"","nutrition":[{"Energy":"1083kJ, 266kcal","nutr_percent":"13%"},{"Fat":"19.0g","nutr_percent":"27%"},{"Saturates":"4.8g","nutr_percent":"24%"},{"Sugars":"2.1g","nutr_percent":"2%"},{"Salt":"0.95g","nutr_percent":"16%"}],"ingredients":"Rehydrated Textured Pea Protein (51%), Water, Shea Oil, Olive Oil, Natural Flavourings, Thickeners (Methylcellulose, Konjac, Xanthan Gum), Potato Starch, Fava Bean Protein Isolate, Caramelised Sugar, Colour (Beetroot Red), Salt, Pea Fibre, Dextrin, Acidity Regulator (Calcium Hydroxide), Iron, Vitamin B12","description":"Suitable for vegans Suitable for vegetarians Of an adult's Reference Intake, one burger (113g) contains: Energy 1083kJ 266kcal 13% of the reference intake Fat 19.0g medium 27% of the reference intake Saturates 4.8g medium 24% of the reference intake Sugars 2.1g low 2% of the reference intake Salt 0.95g medium 16% of the reference intake of the reference intake * Typical values per 100g: Energy per 100g Product Description Plant-based beef flavoured burgers made from pea protein. Featuring Fat 2.0™ Fat makes animal-based meat taste lush. So - we invented Fat 2.0™ from olive oil and put it in these burgers. It crisps up, adds succulence and we patented it so you can't copy us. All it took was several million £, 6 food scientists and some olives. 40% Less Saturated Fat* *40% less saturated fat compared with a standard beef burger of the same weight. 100% Plant-Based High in Protein Source of Fibre Suitable For Vegetarians & Vegans Pack size: 226G High in Protein Source of Fibre Information Ingredients Rehydrated Textured Pea Protein (51%), Water, Shea Oil, Olive Oil, Natural Flavourings, Thickeners (Methylcellulose, Konjac, Xanthan Gum), Potato Starch, Fava Bean Protein Isolate, Caramelised Sugar, Colour (Beetroot Red), Salt, Pea Fibre, Dextrin, Acidity Regulator (Calcium Hydroxide), Iron, Vitamin B12 Allergy Information May contain Soya and Cereals containing Gluten. Storage Keep refrigerated. Once opened, consume within 24 hours. Do not exceed the use by date.Not suitable for home freezing. Cooking Instructions Cooking Instructions Instructions: Not suitable for microwave cooking. Grill Instructions: Grill burgers on medium heat for 5-6 mins on each side. Shallow Fry Instructions: For best results, heat 1 tbsp of oil in a frying pan on a medium heat. Cook for 8-10 mins, turning frequently. Produce of Produced in the UK Number of uses One pack contains 2 portions Recycling info Card. RecyclenFilm. Don't RecyclenTray. Recycle Name and address This™, The Aircraft Factory, 100 Cambridge Grove, London, W6 0LE. Return to Contact This™ Email us: shout@this.co or write to us: This™, The Aircraft Factory, 100 Cambridge Grove, London, W6 0LE. this.co Net Contents 2 x 113g ℮ Nutrition Typical Values per 100g Energy kJ 987 Energy kcal 236 Fat 16.9g (of which Saturates) 4.3g Carbohydrate 5.9g (of which Sugars) 1.9g Fibre 3.5g Protein 13.6g Salt 0.84g Iron 4.9mg (35%)** Vitamin B12 1.0µg (40%)** **RI% = Reference intake of an average adult (8400kJ/ 2000kcal) -","cooking_instructions":"Cooking Instructions. Instructions: Not suitable for microwave cooking.. Grill. Instructions: Grill burgers on medium heat for 5-6 mins on each side.. Shallow Fry. Instructions: For best results, heat 1 tbsp of oil in a frying pan on a medium heat. Cook for 8-10 mins, turning frequently.","storage":"Keep refrigerated. Once opened, consume within 24 hours. Do not exceed the use by date.Not suitable for home freezing.","allergy_info":"May contain Soya and Cereals containing Gluten.","produce_of":"Produced in the UK","number_of_uses":"One pack contains 2 portions","recycling_info":"Card. RecyclenFilm. Don't RecyclenTray. Recycle","return_to":"Contact This™. Email us: shout@this.co or write to us:. This™,. The Aircraft Factory,. 100 Cambridge Grove,. London,. W6 0LE.. this.co","net_content":"2 x 113g ℮","nutrition_per_unit":[{"Typical Values":"Energy kcal","per 100g":"236"},{"Typical Values":"Fat","per 100g":"16.9g"},{"Typical Values":"(of which Saturates)","per 100g":"4.3g"},{"Typical Values":"Carbohydrate","per 100g":"5.9g"},{"Typical Values":"(of which Sugars)","per 100g":"1.9g"},{"Typical Values":"Fibre","per 100g":"3.5g"},{"Typical Values":"Protein","per 100g":"13.6g"},{"Typical Values":"Salt","per 100g":"0.84g"},{"Typical Values":"Iron","per 100g":"4.9mg (35%)**"},{"Typical Values":"Vitamin B12","per 100g":"1.0µg (40%)**"},{"Typical Values":"**RI% = Reference intake of an average adult (8400kJ/ 2000kcal)","per 100g":"-"}],"gtin13":"05060678710453","sku":"312350367","timestamp":"2023-01-31T12:06:50Z"},{"title":"Tesco Deli Corned Beef 140G 140G","unit_price":"2.00","currency":"£","price_per_quantity":"1.43","quantity":"1","url":"https://www.tesco.com/groceries/en-GB/products/312568231","image":"https://digitalcontent.api.tesco.com/v2/media/ghs/e1211be0-16e3-4f82-a068-831dc2da1182/055797dc-28b3-4400-a89f-1b8cbddaacdb.jpeg?h=540&w=540","rating":"No ratings yet","category":"Fresh Food / Cooked Meats, Antipasti & Dips / Deli Counter","number_of_reviews":"","short_desc":"","nutrition":[{"Energy":"359kJ, 86kcal","nutr_percent":"4%"},{"Fat":"6.0g","nutr_percent":"9%"},{"Saturates":"2.7g","nutr_percent":"14%"},{"Sugars":"0.1g","nutr_percent":"<1%"},{"Salt":"0.56g","nutr_percent":"9%"}],"ingredients":"Beef, Salt, Preservative (Sodium Nitrite).","description":"One slice Energy 359kJ 86kcal 4% of the reference intake Fat 6.0g medium 9% of the reference intake Saturates 2.7g high 14% of the reference intake Sugars 0.1g low <1% of the reference intake Salt 0.56g high 9% of the reference intake of the reference intake * Typical values per 100g: Energy 1027kJ / 247kcal Product Description Cured and cooked corned beef slices. British Beef Selected cuts of British beef, dry cured and slow cooked for a rich flavour Pack size: 140G Information Ingredients INGREDIENTS: Beef, Salt, Preservative (Sodium Nitrite). Legal information Packaged in a protective atmosphere Storage Keep refrigerated. Once opened, consume within 2 days and by 'use by' date shown. Number of uses 4 Servings Warnings Caution: Although every care has been taken to remove bones, some may remain. Recycling info Tray. RecyclenFilm. Recycle at large supermarket Return to Tesco Stores Ltd., Welwyn Garden City AL7 1GA, U.K Net Contents 140g e Nutrition Typical Values Per 100g One slice (35g) Energy 1027kJ / 247kcal 359kJ / 86kcal Fat 17.0g 6.0g Saturates 7.6g 2.7g Carbohydrate 0.3g 0.1g Sugars 0.3g 0.1g Fibre 0.7g 0.2g Protein 22.8g 8.0g Salt 1.60g 0.56g * Reference intake of an average adult (8400 kJ / 2000 kcal) - - As sold - - Safety information View more safety information Caution: Although every care has been taken to remove bones, some may remain.","cooking_instructions":"","storage":"Keep refrigerated. Once opened, consume within 2 days and by 'use by' date shown.","allergy_info":"","produce_of":"","number_of_uses":"4 Servings","recycling_info":"Tray. RecyclenFilm. Recycle at large supermarket","return_to":"Tesco Stores Ltd.,. Welwyn Garden City AL7 1GA,. U.K","net_content":"140g e","nutrition_per_unit":[{"Typical Values":"Fat","Per 100g":"17.0g","One slice (35g)":"6.0g"},{"Typical Values":"Saturates","Per 100g":"7.6g","One slice (35g)":"2.7g"},{"Typical Values":"Carbohydrate","Per 100g":"0.3g","One slice (35g)":"0.1g"},{"Typical Values":"Sugars","Per 100g":"0.3g","One slice (35g)":"0.1g"},{"Typical Values":"Fibre","Per 100g":"0.7g","One slice (35g)":"0.2g"},{"Typical Values":"Protein","Per 100g":"22.8g","One slice (35g)":"8.0g"},{"Typical Values":"Salt","Per 100g":"1.60g","One slice (35g)":"0.56g"},{"Typical Values":"* Reference intake of an average adult (8400 kJ / 2000 kcal)","Per 100g":"-","One slice (35g)":"-"},{"Typical Values":"As sold","Per 100g":"-","One slice (35g)":"-"}],"gtin13":"05059512731396","sku":"312568231","timestamp":"2023-01-31T12:06:54Z"},{"title":"Tesco Plant Chef Hunter Style No Chicken Tray Bake 370G","unit_price":"3.50","currency":"£","price_per_quantity":"9.46","quantity":"1","url":"https://www.tesco.com/groceries/en-GB/products/312367048","image":"https://digitalcontent.api.tesco.com/v2/media/ghs/1534360c-7aca-480c-85af-61d0fe5854e1/69c5bab2-edc2-4fde-951c-4dd771228945.jpeg?h=540&w=540","rating":"4.7","category":"Fresh Food / Chilled Vegetarian & Vegan / Roasts","number_of_reviews":"3","short_desc":"","nutrition":[{"Energy":"1446kJ, 345kcal","nutr_percent":"17%"},{"Fat":"15.4g","nutr_percent":"22%"},{"Saturates":"3.2g","nutr_percent":"16%"},{"Sugars":"14.9g","nutr_percent":"17%"},{"Salt":"2.18g","nutr_percent":"36%"}],"ingredients":"Barbecue Sauce Sachet [Water, White Sugar, Tomato Purée, Brown Sugar, Glucose Syrup, Tomato, Spirit Vinegar, Molasses, Maize Starch, Smoked Salt, Salt, Onion, Garlic Purée, Caramelised Sugar Syrup, Stabiliser (Xanthan Gum), Maltodextrin, Clove], Water, Reconstituted. Protein (22%), Rapeseed Oil, Reconstituted Pea Protein (3.5%),. Protein Concentrate, Pea Protein (1.5%), Rice Flour, Stabiliser (Methyl Cellulose), Coconut Oil, Modified Maize Starch, Flavouring, Potato Starch, Maltodextrin, Salt, Pea Fibre, Yeast Extract, Onion, Sea Salt, Dextrose, Bamboo Fibre, Gelling Agent (Carrageenan),. Gluten, Sugar, Smoked Water, Sunflower Oil, Beetroot, Olive Extract, Caramelised Sugar Syrup, Onion Powder, Colours (Paprika Extract, Beta-Carotene), Modified Tapioca Starch, Vitamin B12.","description":"Suitable for vegans 1/2 of a pack Energy 1446kJ 345kcal 17% of the reference intake Fat 15.4g medium 22% of the reference intake Saturates 3.2g medium 16% of the reference intake Sugars 14.9g medium 17% of the reference intake Salt 2.18g high 36% of the reference intake of the reference intake * Typical values per 100g: Energy 866kJ / 207kcal Product Description Seasoned wheat, pea and soya protein fillet topped with wheat and pea protein rashers with coconut oil alternative to mozzarella and Cheddar cheeses and a sachet of barbecue sauce. The Plant Chef   Derek Sarno   is the culinary talent transforming crowd   pleasing classics into 100% plant based dishes with big, bold flavours that pack a tasty punch. 100% Plant Based Wheat, pea and soya protein fillets topped with BBQ sauce & smoky pieces Pack size: 370G Information Ingredients INGREDIENTS: Barbecue Sauce Sachet [Water, White Sugar, Tomato Purée, Brown Sugar, Glucose Syrup, Tomato, Spirit Vinegar, Molasses, Maize Starch, Smoked Salt, Salt, Onion, Garlic Purée, Caramelised Sugar Syrup, Stabiliser (Xanthan Gum), Maltodextrin, Clove], Water, Reconstituted Wheat Protein (22%), Rapeseed Oil, Reconstituted Pea Protein (3.5%), Soya Protein Concentrate, Pea Protein (1.5%), Rice Flour, Stabiliser (Methyl Cellulose), Coconut Oil, Modified Maize Starch, Flavouring, Potato Starch, Maltodextrin, Salt, Pea Fibre, Yeast Extract, Onion, Sea Salt, Dextrose, Bamboo Fibre, Gelling Agent (Carrageenan), Wheat Gluten, Sugar, Smoked Water, Sunflower Oil, Beetroot, Olive Extract, Caramelised Sugar Syrup, Onion Powder, Colours (Paprika Extract, Beta-Carotene), Modified Tapioca Starch, Vitamin B12. Allergy Information For allergens, including cereals containing gluten, see ingredients in bold. Storage Suitable for home freezing. Ideally freeze as soon as possible after purchase but always by 'use by' date shown. nNot suitable for cooking from frozen. nOnce defrosted, do not refreeze. nFollow the preparation guidelines above. nDefrost thoroughly for a minimum of 12 hours in the fridge.nnKeep refrigerated. Cooking Instructions Oven Instructions: Set sauce sachet to one side. 200°C/Fan 180°C/Gas 6 35-40 mins Place on a non-stick baking tray in the centre of a pre-heated oven and cook for 25-30 minutes. Remove from oven, add contents of sauce sachet across the top and cook for a further 10 minutes. Number of uses 2 Servings Recycling info Tray. RecyclenFilm. Recycle at large supermarketnSleeve. RecyclenSachet. Don't Recycle Return to Tesco Stores Ltd., Welwyn Garden City AL7 1GA, U.K Net Contents 370g e Nutrition Typical Values Per 100g 1/2 of a pack (167g**) Energy 866kJ / 207kcal 1446kJ / 345kcal Fat 9.2g 15.4g Saturates 1.9g 3.2g Carbohydrate 17.1g 28.6g Sugars 8.9g 14.9g Fibre 2.8g 4.7g Protein 12.5g 20.9g Salt 1.30g 2.18g * Reference intake of an average adult (8400 kJ / 2000 kcal) - - When cooked according to instructions. - - ** When cooked according to instructions 370g typically weighs 335g. - -","cooking_instructions":"Oven. Instructions: Set sauce sachet to one side. 200°C/Fan 180°C/Gas 6 35-40 mins Place on a non-stick baking tray in the centre of a pre-heated oven and cook for 25-30 minutes. Remove from oven, add contents of sauce sachet across the top and cook for a further 10 minutes.","storage":"Suitable for home freezing. Ideally freeze as soon as possible after purchase but always by 'use by' date shown. nNot suitable for cooking from frozen. nOnce defrosted, do not refreeze. nFollow the preparation guidelines above. nDefrost thoroughly for a minimum of 12 hours in the fridge.nnKeep refrigerated.","allergy_info":"For allergens, including cereals containing gluten, see ingredients in bold.","produce_of":"","number_of_uses":"2 Servings","recycling_info":"Tray. RecyclenFilm. Recycle at large supermarketnSleeve. RecyclenSachet. Don't Recycle","return_to":"Tesco Stores Ltd.,. Welwyn Garden City AL7 1GA,. U.K","net_content":"370g e","nutrition_per_unit":[{"Typical Values":"Fat","Per 100g":"9.2g","1/2 of a pack (167g**)":"15.4g"},{"Typical Values":"Saturates","Per 100g":"1.9g","1/2 of a pack (167g**)":"3.2g"},{"Typical Values":"Carbohydrate","Per 100g":"17.1g","1/2 of a pack (167g**)":"28.6g"},{"Typical Values":"Sugars","Per 100g":"8.9g","1/2 of a pack (167g**)":"14.9g"},{"Typical Values":"Fibre","Per 100g":"2.8g","1/2 of a pack (167g**)":"4.7g"},{"Typical Values":"Protein","Per 100g":"12.5g","1/2 of a pack (167g**)":"20.9g"},{"Typical Values":"Salt","Per 100g":"1.30g","1/2 of a pack (167g**)":"2.18g"},{"Typical Values":"* Reference intake of an average adult (8400 kJ / 2000 kcal)","Per 100g":"-","1/2 of a pack (167g**)":"-"},{"Typical Values":"When cooked according to instructions.","Per 100g":"-","1/2 of a pack (167g**)":"-"},{"Typical Values":"** When cooked according to instructions 370g typically weighs 335g.","Per 100g":"-","1/2 of a pack (167g**)":"-"}],"gtin13":"05059697401350","sku":"312367048","timestamp":"2023-01-31T12:06:57Z"},{"title":"Quorn Cajun Wings 230G","unit_price":"3.00","currency":"£","price_per_quantity":"13.04","quantity":"1","url":"https://www.tesco.com/groceries/en-GB/products/312560026","image":"https://digitalcontent.api.tesco.com/v2/media/ghs/5fdca27d-9902-4cbb-82d8-6dc0224b8f5a/425aabdf-c231-4003-b8a8-9ed7fc33975f.jpeg?h=540&w=540","rating":"2","category":"Fresh Food / Chilled Vegetarian & Vegan / Escalopes & Nuggets","number_of_reviews":"1","short_desc":"","nutrition":[{"Energy":"804kJ, 192kcal","nutr_percent":"10%"},{"Fat":"8.9g","nutr_percent":"13%"},{"Saturates":"1.2g","nutr_percent":"6%"},{"Sugars":"0.3g","nutr_percent":"0%"},{"Salt":"0.93g","nutr_percent":"16%"}],"ingredients":"Mycoprotein (55%),. Flour (. Flour, Calcium Carbonate, Niacin, Iron Thiamine), Water, Vegetable Oil (Sunflower, Rapeseed), Natural Flavouring, Pea Fibre, Maize Starch, Potato Protein, Pea Protein, Spices (0.8%) (Sweet Paprika, Cayenne Pepper, Cumin, Ginger, Fennel, Allspice, Hot Chilli),. Gluten,. Semolina, Sugar, Salt, Stabiliser: Carrageenan, Herbs (Coriander, Oregano, Thyme, Parsley), Millet Seeds, Black Pepper (0.07%), Dextrose, Garlic Powder, Onion Powder, Tomato Powder, Dried Yeast, Black Pepper Extract","description":"Suitable for vegans Per 3 Cooked Wings (91g) Energy 804kJ 192kcal 10% of the reference intake Fat 8.9g medium 13% of the reference intake Saturates 1.2g low 6% of the reference intake Sugars 0.3g low 0% of the reference intake Salt 0.93g medium 16% of the reference intake of the reference intake * Typical values per 100g: Energy 883kJ/211kcal Product Description Vegan savoury flavour wings, made with mycoprotein, in a spiced coating Sustainable nutrition Quorn products are a source of protein because they contain mycoprotein; a nutritious and sustainable protein source. Mycoprotein's footprint is certified by the Carbon Trust and has less impact on our planet's resources To discover delicious recipes made with Quorn products and to find out more about our approach to sustainable nutrition visit www.quorn.co.uk Deliciously crunchy vegan wings with paprika, cayenne and pepper. Pile high and serve with spicy rice and slaw for the perfect mid week treat Packaged in a protective atmosphere. Quorn® and the Quorn™ logo are trademarks belonging to Marlow Foods Ltd. Vegan wings in a deliciously crunchy Cajun coating High in Protein Low in Saturated Fat High in Fibre Suitable for vegans Pack size: 230G High in Protein Low in Saturated Fat High in Fibre Information Ingredients Mycoprotein (55%), Wheat Flour ( Wheat Flour, Calcium Carbonate, Niacin, Iron Thiamine), Water, Vegetable Oil (Sunflower, Rapeseed), Natural Flavouring, Pea Fibre, Maize Starch, Potato Protein, Pea Protein, Spices (0.8%) (Sweet Paprika, Cayenne Pepper, Cumin, Ginger, Fennel, Allspice, Hot Chilli), Wheat Gluten, Wheat Semolina, Sugar, Salt, Stabiliser: Carrageenan, Herbs (Coriander, Oregano, Thyme, Parsley), Millet Seeds, Black Pepper (0.07%), Dextrose, Garlic Powder, Onion Powder, Tomato Powder, Dried Yeast, Black Pepper Extract Allergy Information There have been rare cases of allergic reactions to Quorn® products, which contain mycoprotein. Mycoprotein is made with a member of the fungi/mould family. Mycoprotein is high in protein and fibre which may cause intolerance in some people. For allergens, including Cereals containing Gluten, see ingredients in bold. Storage Keep refrigerated and use by the date shown on front of pack. Not suitable for home freezing.Use by: See front of pack Cooking Instructions Oven cook Instructions: Remove all packaging. For best result oven cook. 16 Min Preheat oven and baking tray to 220°C/ Fan 200°C/ Gas 7. Cook on the middle shelf. All appliances vary, these are guidelines only. Check product is piping hot before serving. Produce of Made in the UK Number of uses 2-3 Servings Recycling info Film. Don't RecyclenSleeve. RecyclenTray. Recycle Name and address Quorn Foods, Freepost M1927, Station Road, Stokesley, TS9 7BR. Return to We're Here to Help If you have any questions or comments please do get in touch https://www.quorn.co.uk or call us on 0345 602 9000 Quorn Customer Services, Quorn Foods, Freepost M1927, Station Road, Stokesley, TS9 7BR. Net Contents 230g ℮ Nutrition Typical Values (as oven cooked) Per 100g (as oven cooked) Per 3 Wings Energy 883kJ/211kcal 804kJ/192kcal Fat 9.8g 8.9g of which saturates 1.3g 1.2g Carbohydrate 12g 11g of which sugars 0.3g 0.3g Fibre 7.1g 6.5g Protein 15g 14g Salt 1.0g 0.93g Serves 2-3 - -","cooking_instructions":"Oven cook. Instructions: Remove all packaging. For best result oven cook.. 16 Min. Preheat oven and baking tray to 220°C/ Fan 200°C/ Gas 7. Cook on the middle shelf.. All appliances vary, these are guidelines only. Check product is piping hot before serving.","storage":"Keep refrigerated and use by the date shown on front of pack. Not suitable for home freezing.Use by: See front of pack","allergy_info":"There have been rare cases of allergic reactions to Quorn® products, which contain mycoprotein. Mycoprotein is made with a member of the fungi/mould family. Mycoprotein is high in protein and fibre which may cause intolerance in some people. For allergens, including Cereals containing Gluten, see ingredients in bold.","produce_of":"Made in the UK","number_of_uses":"2-3 Servings","recycling_info":"Film. Don't RecyclenSleeve. RecyclenTray. Recycle","return_to":"We're Here to Help. If you have any questions or comments please do get in touch https://www.quorn.co.uk or call us on 0345 602 9000. Quorn Customer Services,. Quorn Foods,. Freepost M1927,. Station Road,. Stokesley,. TS9 7BR.","net_content":"230g ℮","nutrition_per_unit":[{"Typical Values":"Fat","(as oven cooked) Per 100g":"9.8g","(as oven cooked) Per 3 Wings":"8.9g"},{"Typical Values":"of which saturates","(as oven cooked) Per 100g":"1.3g","(as oven cooked) Per 3 Wings":"1.2g"},{"Typical Values":"Carbohydrate","(as oven cooked) Per 100g":"12g","(as oven cooked) Per 3 Wings":"11g"},{"Typical Values":"of which sugars","(as oven cooked) Per 100g":"0.3g","(as oven cooked) Per 3 Wings":"0.3g"},{"Typical Values":"Fibre","(as oven cooked) Per 100g":"7.1g","(as oven cooked) Per 3 Wings":"6.5g"},{"Typical Values":"Protein","(as oven cooked) Per 100g":"15g","(as oven cooked) Per 3 Wings":"14g"},{"Typical Values":"Salt","(as oven cooked) Per 100g":"1.0g","(as oven cooked) Per 3 Wings":"0.93g"},{"Typical Values":"Serves 2-3","(as oven cooked) Per 100g":"-","(as oven cooked) Per 3 Wings":"-"}],"gtin13":"05019503045246","sku":"312560026","timestamp":"2023-01-31T12:07:00Z"},{"title":"Quorn Tempura Fillets 200G","unit_price":"3.00","currency":"£","price_per_quantity":"15.00","quantity":"1","url":"https://www.tesco.com/groceries/en-GB/products/311443305","image":"https://digitalcontent.api.tesco.com/v2/media/ghs/b35d5fc5-cce9-4c0e-89e4-b8aa782126fe/a220ce7f-0450-465e-9aaa-aa61513abf96.jpeg?h=540&w=540","rating":"No ratings yet","category":"Fresh Food / Chilled Vegetarian & Vegan / Escalopes & Nuggets","number_of_reviews":"","short_desc":"","nutrition":[{"Energy":"821kJ, 197kcal","nutr_percent":"10%"},{"Fat":"10g","nutr_percent":"14%"},{"Saturates":"1.1g","nutr_percent":"6%"},{"Sugars":"1.8g","nutr_percent":"2%"},{"Salt":"1.3g","nutr_percent":"22%"}],"ingredients":"Mycoprotein (55%), Water,. Flour (. Flour (Calcium Carbonate, Iron, Niacin, Thiamine), Vegetable Oils (Sunflower, Rapeseed), Natural Flavouring, Maize Starch, Pea Fibre, Maize Flour, Potato Protein, Pea Protein,. Gluten, Rice Flour, Potato Dextrin, Stabiliser: Carrageenan, Salt, Dextrose, Raising Agents: Ammonium Carbonate, Diphosphate, Sodium Bicarbonate, Yeast Extract, Garlic Powder, Onion Powder, Black & White Pepper, Yeast, Colour: Paprika Extract, Black Pepper Extract","description":"Suitable for vegans Per Cooked Fillet (96g) Energy 821kJ 197kcal 10% of the reference intake Fat 10g medium 14% of the reference intake Saturates 1.1g low 6% of the reference intake Sugars 1.8g low 2% of the reference intake Salt 1.3g medium 22% of the reference intake of the reference intake * Typical values per 100g: Energy 855kJ/205kcal Product Description Vegan savoury flavour fillet, made with mycoprotein, coated in a tempura style batter Sustainable nutrition Quorn products are a source of protein because they contain mycoprotein; a nutritious and sustainable protein source. Mycoprotein's footprint is certified by the Carbon Trust and has less impact on our planet's resources. To discover delicious recipes made with Quorn products and to find out more about our approach to sustainable nutrition visit www.quorn.co.uk Our tempura fillets are vegan and totally tasty. Coated in a light crispy batter, load them into a bun with your favourite toppings for the perfectly light and crispy fillet burger. Packaged in a protective atmosphere. Quorn® and the Quorn™ logo are trademarks belonging to Marlow Foods Ltd. Vegan fillets in a light, crispy batter High in Protein Low in Saturated Fat Source of Fibre Suitable for vegans Pack size: 200G High in Protein Low in Saturated Fat Source of Fibre Information Ingredients Mycoprotein (55%), Water, Wheat Flour ( Wheat Flour (Calcium Carbonate, Iron, Niacin, Thiamine), Vegetable Oils (Sunflower, Rapeseed), Natural Flavouring, Maize Starch, Pea Fibre, Maize Flour, Potato Protein, Pea Protein, Wheat Gluten, Rice Flour, Potato Dextrin, Stabiliser: Carrageenan, Salt, Dextrose, Raising Agents: Ammonium Carbonate, Diphosphate, Sodium Bicarbonate, Yeast Extract, Garlic Powder, Onion Powder, Black & White Pepper, Yeast, Colour: Paprika Extract, Black Pepper Extract Allergy Information There have been rare cases of allergic reactions to Quorn® products, which contain mycoprotein. Mycoprotein is made with a member of the fungi/mould family. Mycoprotein is high in protein and fibre which may cause intolerance in some people. For allergens, including Cereals containing Gluten, see ingredients in bold. Storage Keep refrigerated and use by the date shown on front of pack. Not suitable for home freezing.Use by: See front of pack Cooking Instructions Oven cook Instructions: Remove all packaging. For best result oven cook. 18 Min Preheat oven and baking tray to 220°C/ Fan 200°C/Gas 7. Cook on the middle shelf. All appliances vary, these are guidelines only. Check product is piping hot before serving. Produce of Made in the UK Number of uses 2 Servings Recycling info Film. Don't RecyclenSleeve. RecyclenTray. Recycle Name and address Quorn Foods, Freepost M1927, Station Road, Stokesley, TS9 7BR. Return to We're Here to Help If you have any questions or comments please do get in touch https://www.quorn.co.uk or call us on 0345 602 9000 Quorn Customer Services, Quorn Foods, Freepost M1927, Station Road, Stokesley, TS9 7BR. Net Contents 200g ℮ Nutrition Typical Values (as oven cooked) Per 100g (as oven cooked) Per Fillet Energy 855kJ/205kcal 821kJ/197kcal Fat 11g 10g of which saturates 1.1g 1.1g Carbohydrate 13g 12g of which sugars 1.9g 1.8g Fibre 5.6g 5.4g Protein 12g 11g Salt 1.3g 1.3g Serves 2 - -","cooking_instructions":"Oven cook. Instructions: Remove all packaging. For best result oven cook.. 18 Min. Preheat oven and baking tray to 220°C/ Fan 200°C/Gas 7. Cook on the middle shelf.. All appliances vary, these are guidelines only. Check product is piping hot before serving.","storage":"Keep refrigerated and use by the date shown on front of pack. Not suitable for home freezing.Use by: See front of pack","allergy_info":"There have been rare cases of allergic reactions to Quorn® products, which contain mycoprotein. Mycoprotein is made with a member of the fungi/mould family. Mycoprotein is high in protein and fibre which may cause intolerance in some people. For allergens, including Cereals containing Gluten, see ingredients in bold.","produce_of":"Made in the UK","number_of_uses":"2 Servings","recycling_info":"Film. Don't RecyclenSleeve. RecyclenTray. Recycle","return_to":"We're Here to Help. If you have any questions or comments please do get in touch https://www.quorn.co.uk or call us on 0345 602 9000. Quorn Customer Services,. Quorn Foods,. Freepost M1927,. Station Road,. Stokesley,. TS9 7BR.","net_content":"200g ℮","nutrition_per_unit":[{"Typical Values":"Fat","(as oven cooked) Per 100g":"11g","(as oven cooked) Per Fillet":"10g"},{"Typical Values":"of which saturates","(as oven cooked) Per 100g":"1.1g","(as oven cooked) Per Fillet":"1.1g"},{"Typical Values":"Carbohydrate","(as oven cooked) Per 100g":"13g","(as oven cooked) Per Fillet":"12g"},{"Typical Values":"of which sugars","(as oven cooked) Per 100g":"1.9g","(as oven cooked) Per Fillet":"1.8g"},{"Typical Values":"Fibre","(as oven cooked) Per 100g":"5.6g","(as oven cooked) Per Fillet":"5.4g"},{"Typical Values":"Protein","(as oven cooked) Per 100g":"12g","(as oven cooked) Per Fillet":"11g"},{"Typical Values":"Salt","(as oven cooked) Per 100g":"1.3g","(as oven cooked) Per Fillet":"1.3g"},{"Typical Values":"Serves 2","(as oven cooked) Per 100g":"-","(as oven cooked) Per Fillet":"-"}],"gtin13":"05019503045239","sku":"311443305","timestamp":"2023-01-31T12:07:03Z"},{"title":"Tesco Finest 2 Scottish Loch Trout Fillets 260G","unit_price":"5.70","currency":"£","price_per_quantity":"21.92","quantity":"1","url":"https://www.tesco.com/groceries/en-GB/products/294070300","image":"https://digitalcontent.api.tesco.com/v2/media/ghs/f5561c19-ea87-4cbd-bdf1-4710e04a3c31/08956582-19df-4766-87e6-fab4dad601c8.jpeg?h=540&w=540","rating":"3.7","category":"Fresh Food / Chilled Fish & Seafood / Salmon & Trout","number_of_reviews":"6","short_desc":"","nutrition":[{"Energy":"907kJ, 217kcal","nutr_percent":"11%"},{"Fat":"13.2g","nutr_percent":"19%"},{"Saturates":"2.6g","nutr_percent":"13%"},{"Sugars":"0.2g","nutr_percent":"<1%"},{"Salt":"0.12g","nutr_percent":"2%"}],"ingredients":"","description":"One typical trout fillet Energy 907kJ 217kcal 11% of the reference intake Fat 13.2g medium 19% of the reference intake Saturates 2.6g medium 13% of the reference intake Sugars 0.2g low <1% of the reference intake Salt 0.12g low 2% of the reference intake of the reference intake * Typical values per 100g: Energy 898kJ / 215kcal Product Description Skin-on boneless Scottish loch trout (Oncorhynchus mykiss) fillets. Succulent trout farmed in clear, crisp Scottish lochs for a light, delicate flavour Our Tesco Finest trout is RSPCA Assured and farmed in clear crisp Scottish lochs. The water is perfect for producing fish with a fine texture, vivid colour and delicious taste. Pack size: 260G Information Allergy Information Contains fish. Storage Suitable for home freezing. Ideally freeze as soon as possible after purchase but always by 'use by' date shown. nNot suitable for cooking from frozen. nFollow the preparation guidelines above. nDefrost thoroughly for a minimum of 8 hours in the fridge. Once defrosted use within 24 hours and do not refreeze. nnKeep refrigerated. Once opened, consume within 1 day and by ‘use by’ date shown. Cooking Instructions Oven Instructions: 200°C/Fan 180°C/Gas 6 20-22 mins Place on a baking tray in the centre of a pre-heated oven. Produce of Farmed in U.K., Scotland, Packed in the U.K. Number of uses 2 Servings Warnings Caution: This product can contain minor bones.. Recycling info Tray. RecyclenFilm. Recycle at large supermarket Return to Tesco Stores Ltd., Welwyn Garden City AL7 1GA, U.K Drained weight - Net Contents 260g e Nutrition Typical Values Per 100g One typical trout fillet (101g**) Energy 898kJ / 215kcal 907kJ / 217kcal Fat 13.1g 13.2g Saturates 2.6g 2.6g Carbohydrate 0.6g 0.6g Sugars 0.2g 0.2g Fibre 0.4g 0.4g Protein 23.5g 23.7g Salt 0.12g 0.12g Omega-3 (EPA & DHA) 1380mg 1394mg * Reference intake of an average adult (8400 kJ / 2000 kcal) - - When cooked according to instructions. - - ** When oven cooked according to instructions 260g typically weighs 202g. - - Safety information View more safety information Caution: This product can contain minor bones..","cooking_instructions":"Oven. Instructions: 200°C/Fan 180°C/Gas 6 20-22 mins Place on a baking tray in the centre of a pre-heated oven.","storage":"Suitable for home freezing. Ideally freeze as soon as possible after purchase but always by 'use by' date shown. nNot suitable for cooking from frozen. nFollow the preparation guidelines above. nDefrost thoroughly for a minimum of 8 hours in the fridge. Once defrosted use within 24 hours and do not refreeze. nnKeep refrigerated. Once opened, consume within 1 day and by ‘use by’ date shown.","allergy_info":"Contains fish.","produce_of":"Farmed in U.K., Scotland, Packed in the U.K.","number_of_uses":"2 Servings","recycling_info":"Tray. RecyclenFilm. Recycle at large supermarket","return_to":"Tesco Stores Ltd.,. Welwyn Garden City AL7 1GA,. U.K","net_content":"260g e","nutrition_per_unit":[{"Typical Values":"Fat","Per 100g":"13.1g","One typical trout fillet (101g**)":"13.2g"},{"Typical Values":"Saturates","Per 100g":"2.6g","One typical trout fillet (101g**)":"2.6g"},{"Typical Values":"Carbohydrate","Per 100g":"0.6g","One typical trout fillet (101g**)":"0.6g"},{"Typical Values":"Sugars","Per 100g":"0.2g","One typical trout fillet (101g**)":"0.2g"},{"Typical Values":"Fibre","Per 100g":"0.4g","One typical trout fillet (101g**)":"0.4g"},{"Typical Values":"Protein","Per 100g":"23.5g","One typical trout fillet (101g**)":"23.7g"},{"Typical Values":"Salt","Per 100g":"0.12g","One typical trout fillet (101g**)":"0.12g"},{"Typical Values":"Omega-3 (EPA & DHA)","Per 100g":"1380mg","One typical trout fillet (101g**)":"1394mg"},{"Typical Values":"* Reference intake of an average adult (8400 kJ / 2000 kcal)","Per 100g":"-","One typical trout fillet (101g**)":"-"},{"Typical Values":"When cooked according to instructions.","Per 100g":"-","One typical trout fillet (101g**)":"-"},{"Typical Values":"** When oven cooked according to instructions 260g typically weighs 202g.","Per 100g":"-","One typical trout fillet (101g**)":"-"}],"gtin13":"05057008569607","sku":"294070300","timestamp":"2023-01-31T12:07:07Z"},{"title":"Tesco Family Tiramisu 500G","unit_price":"3.00","currency":"£","price_per_quantity":"0.60","quantity":"1","url":"https://www.tesco.com/groceries/en-GB/products/253922368","image":"https://digitalcontent.api.tesco.com/v2/media/ghs/d6fcb151-9dee-4e73-89ae-fef79a464fcb/4cd093b6-1d2a-4eeb-abce-a30e18afda50.jpeg?h=540&w=540","rating":"4.1","category":"Fresh Food / Chilled Desserts / Sharing Desserts & Puddings","number_of_reviews":"45","short_desc":"","nutrition":[{"Energy":"784kJ, 187kcal","nutr_percent":"9%"},{"Fat":"6.7g","nutr_percent":"10%"},{"Saturates":"5.5g","nutr_percent":"28%"},{"Sugars":"15.6g","nutr_percent":"17%"},{"Salt":"0.17g","nutr_percent":"3%"}],"ingredients":"Reconstituted Dried Skimmed. , Glucose Syrup, Water, Pasteurised. , Sugar, Coconut Oil, Mascarpone Full Fat Soft Cheese (. ) (4.5%), Dried Skimmed. ,. Flour, Alcohol, Lactose (. ), Marsala Wine (1%), Cocoa Powder, Citrus Fibre, Coffee Powder, Emulsifier (Mono- and Diglycerides of Fatty Acids), Thickener (Carrageenan), Flavourings (contain. ,. ),. Proteins, Coffee Extract, Raising Agents (Disodium Diphosphate, Sodium Bicarbonate).","description":"Suitable for vegetarians 1/6 of a pack Energy 784kJ 187kcal 9% of the reference intake Fat 6.7g medium 10% of the reference intake Saturates 5.5g high 28% of the reference intake Sugars 15.6g medium 17% of the reference intake Salt 0.17g low 3% of the reference intake of the reference intake * Typical values per 100g: Energy 945kJ / 225kcal Product Description Layered dessert made with coffee soaked sponge, mascarpone full fat soft cheese and Marsala wine, with cocoa powder. A taste of Italy. Coffee sauce soaked sponge with creamy mascarpone and Marsala wine. Pack size: 500G Information Ingredients INGREDIENTS: Reconstituted Dried Skimmed Milk , Glucose Syrup, Water, Pasteurised Egg , Sugar, Coconut Oil, Mascarpone Full Fat Soft Cheese ( Milk ) (4.5%), Dried Skimmed Milk , Wheat Flour, Alcohol, Lactose ( Milk ), Marsala Wine (1%), Cocoa Powder, Citrus Fibre, Coffee Powder, Emulsifier (Mono- and Diglycerides of Fatty Acids), Thickener (Carrageenan), Flavourings (contain Milk , Egg ), Milk Proteins, Coffee Extract, Raising Agents (Disodium Diphosphate, Sodium Bicarbonate). Allergy Information For allergens, including cereals containing gluten, see ingredients in bold. Storage Suitable for home freezing. Ideally freeze as soon as possible after purchase but always by 'use by' date shown. nDefrost thoroughly for a minimum of 6 hours in the fridge. Once defrosted use within 24 hours and do not refreeze. nnKeep refrigerated. Number of uses 6 Servings Warnings Caution: Contains alcohol.. Recycling info Sleeve. RecyclenTray. RecyclenFilm. Recycle at large supermarket Return to Tesco Stores Ltd., Welwyn Garden City AL7 1GA, U.K Net Contents 500g e Nutrition Typical Values Per 100g 1/6 of a pack (83g) Energy 945kJ / 225kcal 784kJ / 187kcal Fat 8.1g 6.7g Saturates 6.6g 5.5g Carbohydrate 30.6g 25.4g Sugars 18.8g 15.6g Fibre 1.3g 1.1g Protein 4.0g 3.3g Salt 0.20g 0.17g * Reference intake of an average adult (8400 kJ / 2000 kcal) - - As sold - - Safety information View more safety information Caution: Contains alcohol..","cooking_instructions":"","storage":"Suitable for home freezing. Ideally freeze as soon as possible after purchase but always by 'use by' date shown. nDefrost thoroughly for a minimum of 6 hours in the fridge. Once defrosted use within 24 hours and do not refreeze. nnKeep refrigerated.","allergy_info":"For allergens, including cereals containing gluten, see ingredients in bold.","produce_of":"","number_of_uses":"6 Servings","recycling_info":"Sleeve. RecyclenTray. RecyclenFilm. Recycle at large supermarket","return_to":"Tesco Stores Ltd.,. Welwyn Garden City AL7 1GA,. U.K","net_content":"500g e","nutrition_per_unit":[{"Typical Values":"Fat","Per 100g":"8.1g","1/6 of a pack (83g)":"6.7g"},{"Typical Values":"Saturates","Per 100g":"6.6g","1/6 of a pack (83g)":"5.5g"},{"Typical Values":"Carbohydrate","Per 100g":"30.6g","1/6 of a pack (83g)":"25.4g"},{"Typical Values":"Sugars","Per 100g":"18.8g","1/6 of a pack (83g)":"15.6g"},{"Typical Values":"Fibre","Per 100g":"1.3g","1/6 of a pack (83g)":"1.1g"},{"Typical Values":"Protein","Per 100g":"4.0g","1/6 of a pack (83g)":"3.3g"},{"Typical Values":"Salt","Per 100g":"0.20g","1/6 of a pack (83g)":"0.17g"},{"Typical Values":"* Reference intake of an average adult (8400 kJ / 2000 kcal)","Per 100g":"-","1/6 of a pack (83g)":"-"},{"Typical Values":"As sold","Per 100g":"-","1/6 of a pack (83g)":"-"}],"gtin13":"05000436532279","sku":"253922368","timestamp":"2023-01-31T12:07:11Z"},{"title":"Tesco Finest Mediterranean Inspired Sea Bass Fillets 301G","unit_price":"5.00","currency":"£","price_per_quantity":"16.61","quantity":"1","url":"https://www.tesco.com/groceries/en-GB/products/312696361","image":"https://digitalcontent.api.tesco.com/v2/media/ghs/272b92de-76a7-410c-8096-e2a8e44cc48e/aed3dc8e-1a68-412f-be5c-f69e9618320d.jpeg?h=540&w=540","rating":"No ratings yet","category":"Fresh Food / Chilled Fish & Seafood / Cod, Haddock & White Fish","number_of_reviews":"","short_desc":"","nutrition":[{"Energy":"848kJ, 203kcal","nutr_percent":"10%"},{"Fat":"10.5g","nutr_percent":"15%"},{"Saturates":"2.0g","nutr_percent":"10%"},{"Sugars":"1.4g","nutr_percent":"2%"},{"Salt":"0.38g","nutr_percent":"6%"}],"ingredients":"Sea Bass (. ) (73%), Tomato, Semi Dried Tomatoes, Black Olives, Dried Red Pepper, Red Wine Vinegar, Olive Oil, Cornflour, Salt, Garlic Purée, Basil, Oregano, Stabiliser (Ferrous Gluconate).","description":"1/2 of a pack Energy 848kJ 203kcal 10% of the reference intake Fat 10.5g medium 15% of the reference intake Saturates 2.0g medium 10% of the reference intake Sugars 1.4g low 2% of the reference intake Salt 0.38g low 6% of the reference intake of the reference intake * Typical values per 100g: Energy 662kJ / 158kcal Product Description Skin-on sea bass (Dicentrarchus labrax) fillets with a tomato and red pepper paste, semi-dried tomatoes and olives. Responsibly sourcing our seafood is important to us, which is why Tesco fish experts work with responsibly managed farms and fisheries to continually improve their high standards of quality, welfare and sustainability. Responsibly Sourced High in protein Butterflied sea bass fillets stuffed with semi dried tomatoes and olives Pack size: 301G Information Ingredients INGREDIENTS: Sea Bass ( Fish ) (73%), Tomato, Semi Dried Tomatoes, Black Olives, Dried Red Pepper, Red Wine Vinegar, Olive Oil, Cornflour, Salt, Garlic Purée, Basil, Oregano, Stabiliser (Ferrous Gluconate). Allergy Information For allergens, see ingredients in bold. Storage Suitable for home freezing. Ideally freeze as soon as possible after purchase but always by 'use by' date shown. nDefrost thoroughly for a minimum of 12 hours in the fridge. Once defrosted use within 24 hours and do not refreeze. nFollow the preparation guidelines above. nNot suitable for cooking from frozen. nnKeep refrigerated. Once opened, consume within 1 day and by ‘use by’ date shown. Cooking Instructions Oven Instructions: 200°C/Fan 180°C/Gas 6 18-19 mins Remove sleeve and film lid. Lightly brush fillets with a little oil and place foil tray on a pre-heated baking tray in the centre of pre-heated oven and cook. Remove from foil tray, ensure pad from the bottom of the tray is removed after cooking. Microwave Instructions: Not suitable for microwave cooking. Shallow Fry Instructions: For best results pan fry Pan Fry Remove all packaging. 10-12 mins. Pre-heat 1 teaspoon (5ml) of oil over a low to medium heat, add the fillets and cook for 5-6 minutes on each side. Produce of Made using sea bass farmed in Turkey. Number of uses 2 Servings Warnings Caution: This product can contain minor bones.. Recycling info Tray. RecyclenFilm. Recycle at large supermarketnPad. Don't RecyclenSleeve. Recycle Return to Tesco Stores Ltd., Welwyn Garden City AL7 1GA, U.K Net Contents 301g e Nutrition Typical Values Per 100g 1/2 of a pack (128g**) Energy 662kJ / 158kcal 848kJ / 203kcal Fat 8.2g 10.5g Saturates 1.6g 2.0g Carbohydrate 1.1g 1.4g Sugars 1.1g 1.4g Fibre 1.1g 1.5g Protein 19.5g 24.9g Salt 0.30g 0.38g Omega-3 (EPA & DHA) 680mg 870mg * Reference intake of an average adult (8400 kJ / 2000 kcal) - - When pan fried according to instructions. - - ** When pan fried according to instructions 301g typically weighs 256g. - - Safety information View more safety information Caution: This product can contain minor bones..","cooking_instructions":"Oven. Instructions: 200°C/Fan 180°C/Gas 6 18-19 mins Remove sleeve and film lid. Lightly brush fillets with a little oil and place foil tray on a pre-heated baking tray in the centre of pre-heated oven and cook. Remove from foil tray, ensure pad from the bottom of the tray is removed after cooking.. Microwave. Instructions: Not suitable for microwave cooking.. Shallow Fry. Instructions: For best results pan fry Pan Fry Remove all packaging. 10-12 mins. Pre-heat 1 teaspoon (5ml) of oil over a low to medium heat, add the fillets and cook for 5-6 minutes on each side.","storage":"Suitable for home freezing. Ideally freeze as soon as possible after purchase but always by 'use by' date shown. nDefrost thoroughly for a minimum of 12 hours in the fridge. Once defrosted use within 24 hours and do not refreeze. nFollow the preparation guidelines above. nNot suitable for cooking from frozen. nnKeep refrigerated. Once opened, consume within 1 day and by ‘use by’ date shown.","allergy_info":"For allergens, see ingredients in bold.","produce_of":"Made using sea bass farmed in Turkey.","number_of_uses":"2 Servings","recycling_info":"Tray. RecyclenFilm. Recycle at large supermarketnPad. Don't RecyclenSleeve. Recycle","return_to":"Tesco Stores Ltd.,. Welwyn Garden City AL7 1GA,. U.K","net_content":"301g e","nutrition_per_unit":[{"Typical Values":"Fat","Per 100g":"8.2g","1/2 of a pack (128g**)":"10.5g"},{"Typical Values":"Saturates","Per 100g":"1.6g","1/2 of a pack (128g**)":"2.0g"},{"Typical Values":"Carbohydrate","Per 100g":"1.1g","1/2 of a pack (128g**)":"1.4g"},{"Typical Values":"Sugars","Per 100g":"1.1g","1/2 of a pack (128g**)":"1.4g"},{"Typical Values":"Fibre","Per 100g":"1.1g","1/2 of a pack (128g**)":"1.5g"},{"Typical Values":"Protein","Per 100g":"19.5g","1/2 of a pack (128g**)":"24.9g"},{"Typical Values":"Salt","Per 100g":"0.30g","1/2 of a pack (128g**)":"0.38g"},{"Typical Values":"Omega-3 (EPA & DHA)","Per 100g":"680mg","1/2 of a pack (128g**)":"870mg"},{"Typical Values":"* Reference intake of an average adult (8400 kJ / 2000 kcal)","Per 100g":"-","1/2 of a pack (128g**)":"-"},{"Typical Values":"When pan fried according to instructions.","Per 100g":"-","1/2 of a pack (128g**)":"-"},{"Typical Values":"** When pan fried according to instructions 301g typically weighs 256g.","Per 100g":"-","1/2 of a pack (128g**)":"-"}],"gtin13":"05059697737282","sku":"312696361","timestamp":"2023-01-31T12:07:15Z"},{"title":"Violife Vegan Crumbly Blue Block 150G","unit_price":"3.25","currency":"£","price_per_quantity":"21.67","quantity":"1","url":"https://www.tesco.com/groceries/en-GB/products/312095035","image":"https://digitalcontent.api.tesco.com/v2/media/ghs/52b458b1-0775-47fe-b773-e00c2f9fb444/bf265a13-7c06-4d1b-b2af-ee2ad3148330_703708657.jpeg?h=540&w=540","rating":"No ratings yet","category":"Fresh Food / Dairy Free & Dairy Alternatives / Dairy Free Cheese Alternatives","number_of_reviews":"","short_desc":"£2.75 Clubcard Price Offer valid for delivery from 01/02/2023 until 21/02/2023","nutrition":[],"ingredients":"","description":"Product Description Violife Vegan Crumbly Blue Block 150g Pack size: 150G Information","cooking_instructions":"","storage":"","allergy_info":"","produce_of":"","number_of_uses":"","recycling_info":"","return_to":"","net_content":"","nutrition_per_unit":[],"gtin13":"05202390029592","sku":"312095035","timestamp":"2023-01-31T12:07:19Z"},{"title":"Meatless Farm Plant-Based Chicken Joint 380G","unit_price":"4.50","currency":"£","price_per_quantity":"11.84","quantity":"1","url":"https://www.tesco.com/groceries/en-GB/products/312566734","image":"https://digitalcontent.api.tesco.com/v2/media/ghs/94fa6fdc-d9fd-495c-9075-de0d9b5fc750/3f6e634e-d914-408f-9930-7398c42e8de7.jpeg?h=540&w=540","rating":"3.7","category":"Fresh Food / Chilled Vegetarian & Vegan / Roasts","number_of_reviews":"14","short_desc":"","nutrition":[{"Energy":"908kJ, 219kcal","nutr_percent":"-%"}],"ingredients":"Water,. Protein (12%), Pea Protein (8%), Rapeseed Oil, Thickener (E461), Vegetable Fibres (Bamboo, Pea), Preservative (E326), Yeast Extract, Salt, Spices, Stabiliser (E425), Sugar, Natural Flavouring, Herbs, Smoked Salt","description":"Suitable for vegans 95g (as sold) provides Energy 908kJ 219kcal -% of the reference intake of the reference intake * Typical values per 100g: Energy Per 100g As Sold Product Description Plant-based chickenless roasting joint with wheat & pea protein with a parsley & sage crust Meatless Farm Plant-based Chickenless Roasting Joint with wheat & pea protein with a parsley & sage crust Give the turkeys Christmas off this year with our vegan chicken roast joint with herb crust. Finally, a meat free alternative that’s even tastier than the real thing – it could be the biggest thing to happen to Christmas dinners since grandma fell off her chair after one too many sherries. Our game-changing plant-based chicken roast joint with herb crust is made from our unique pea and wheat protein recipe for that meaty taste and texture. Along with a delicious herb crust, it comes with a side serving of sustainability so all you need to do is whip up all the festive trimmings. And don’t forget to #JustAddGravy – why not head over to our website for our vegan gravy recipes! Enjoy a vegan Christmas dinner that’s big on taste and small on carbon footprint. It’s time to stop clucking about and get Meatless Farm plant-based chicken on your Christmas dinner table. Just Add Gravy Make it Meatless Change Tastes Great Here at Meatless Farm we have created a delicious plant-based alternatives with great taste and texture! Copyright © 2020 The Meatless Farm Ltd. All Rights Reserved. High in Protein Cooks in 40 minutes Suitable for vegans Pack size: 380G High in Protein Information Ingredients Water, Wheat Protein (12%), Pea Protein (8%), Rapeseed Oil, Thickener (E461), Vegetable Fibres (Bamboo, Pea), Preservative (E326), Yeast Extract, Salt, Spices, Stabiliser (E425), Sugar, Natural Flavouring, Herbs, Smoked Salt Allergy Information Contains: Wheat Storage Keep refrigerated, consume within use by date. Once opened, use within 24 hours. Suitable for freezing. Freeze on day of purchase and use within 1 month. If frozen, defrost before cooking (in a refrigerator) and use within 24 hours. Do not re-freeze. Cooking Instructions Oven cook Instructions: Guidelines only, appliances may vary. Ensure product is piping hot before serving. Oven: Preheat oven to 200°C/Fan 180°C/Gas 6. Remove all packaging and place the joint in an oven proof dish. Add 2-3 tbsp water and cover with foil. Roast in the centre of the oven for 35 mins. Remove the foil and roast for a further 5 mins, basting occasionally. Once cooked, pour any remaining juices over the joint or use in gravy Produce of Made in the United Kingdom Number of uses 4 Servings Recycling info Film. Not RecyclablenSleeve. RecyclablenTray. Recyclable Name and address The Meatless Farm Co., Graphical House, 2 Wharf Street, Leeds, LS2 7EQ, United Kingdom. Return to The Meatless Farm Co., Graphical House, 2 Wharf Street, Leeds, LS2 7EQ, United Kingdom. info@meatlessfarm.com Net Contents 380g Nutrition Typical Values Per 100g As Sold Energy kJ 908 Energy kcal 219 Fat 14.7g of which saturates 1.2g Carbohydrate 5.3g of which sugars <0.1g Fibre 3.7g Protein 15.1g Salt 0.99g","cooking_instructions":"Oven cook. Instructions: Guidelines only, appliances may vary. Ensure product is piping hot before serving.. Oven: Preheat oven to 200°C/Fan 180°C/Gas 6. Remove all packaging and place the joint in an oven proof dish. Add 2-3 tbsp water and cover with foil. Roast in the centre of the oven for 35 mins. Remove the foil and roast for a further 5 mins, basting occasionally.. Once cooked, pour any remaining juices over the joint or use in gravy","storage":"Keep refrigerated, consume within use by date. Once opened, use within 24 hours. Suitable for freezing. Freeze on day of purchase and use within 1 month. If frozen, defrost before cooking (in a refrigerator) and use within 24 hours. Do not re-freeze.","allergy_info":"Contains: Wheat","produce_of":"Made in the United Kingdom","number_of_uses":"4 Servings","recycling_info":"Film. Not RecyclablenSleeve. RecyclablenTray. Recyclable","return_to":"The Meatless Farm Co.,. Graphical House,. 2 Wharf Street,. Leeds,. LS2 7EQ,. United Kingdom.. info@meatlessfarm.com","net_content":"380g","nutrition_per_unit":[{"Typical Values":"Energy kcal","Per 100g As Sold":"219"},{"Typical Values":"Fat","Per 100g As Sold":"14.7g"},{"Typical Values":"of which saturates","Per 100g As Sold":"1.2g"},{"Typical Values":"Carbohydrate","Per 100g As Sold":"5.3g"},{"Typical Values":"of which sugars","Per 100g As Sold":"<0.1g"},{"Typical Values":"Fibre","Per 100g As Sold":"3.7g"},{"Typical Values":"Protein","Per 100g As Sold":"15.1g"},{"Typical Values":"Salt","Per 100g As Sold":"0.99g"}],"gtin13":"05060626404588","sku":"312566734","timestamp":"2023-01-31T12:07:23Z"},{"title":"Tesco Finest 2 Battered Haddock & Tartare Sauce F/Cakes 315G","unit_price":"3.00","currency":"£","price_per_quantity":"0.95","quantity":"1","url":"https://www.tesco.com/groceries/en-GB/products/312358998","image":"https://digitalcontent.api.tesco.com/v2/media/ghs/9db0091a-c280-4fc7-9e39-4ccd0b186ae3/d35582e2-fd9b-4670-a24f-97c8eb87e982.jpeg?h=540&w=540","rating":"1.5","category":"Fresh Food / Chilled Fish & Seafood / Cod, Haddock & White Fish","number_of_reviews":"4","short_desc":"Any 2 for £5 Clubcard Price - Selected Tesco Finest* Fishcakes 290g Or 315g Offer valid for delivery from 01/02/2023 until 14/03/2023","nutrition":[{"Energy":"1059kJ, 252kcal","nutr_percent":"13%"},{"Fat":"8.9g","nutr_percent":"13%"},{"Saturates":"1.7g","nutr_percent":"9%"},{"Sugars":"3.5g","nutr_percent":"4%"},{"Salt":"1.51g","nutr_percent":"25%"}],"ingredients":"Haddock (. ) (32%), Wheat Flour [. Flour, Calcium Carbonate, Iron, Niacin, Thiamin], Potato, Rapeseed Oil, Water, Dried Potato, Potato Starch, Semi Skimmed. , Double Cream (. ), Gherkin, Lemon Juice, Cornflour,. Starch, Onion, Parsley, Salt, Capers, Palm Oil, Chive, Shallot, White Wine Vinegar, Dried Skimmed. , Maize Flour, Butter (. ),. Gelatine,. Gluten, Sunflower Oil, Spirit Vinegar, Vinegar, White Pepper.","description":"One fishcake Energy 1059kJ 252kcal 13% of the reference intake Fat 8.9g medium 13% of the reference intake Saturates 1.7g low 9% of the reference intake Sugars 3.5g low 4% of the reference intake Salt 1.51g medium 25% of the reference intake of the reference intake * Typical values per 100g: Energy 670kJ / 160kcal Product Description Pieces of haddock (Melanogrammus aeglefinus) fillet and mashed potato with double cream, gherkin and caper sauce centre, coated in batter. Responsibly sourcing our seafood is important to us, which is why Tesco fish experts work with responsibly managed farms and fisheries to continually improve their high standards of quality, welfare and sustainability. The haddock in this product comes from a fishery that has been independently certified to the MSC's standard for a well managed and sustainable fishery. www.msc.org CRISPY GOLDEN BATTER WILD CAUGHT HADDOCK Filled with a tangy gherkin and caper sauce, coated in a light crispy batter Pack size: 315G Information Ingredients INGREDIENTS: Haddock ( Fish ) (32%), Wheat Flour [ Wheat Flour, Calcium Carbonate, Iron, Niacin, Thiamin], Potato, Rapeseed Oil, Water, Dried Potato, Potato Starch, Semi Skimmed Milk , Double Cream ( Milk ), Gherkin, Lemon Juice, Cornflour, Wheat Starch, Onion, Parsley, Salt, Capers, Palm Oil, Chive, Shallot, White Wine Vinegar, Dried Skimmed Milk , Maize Flour, Butter ( Milk ), Fish Gelatine, Wheat Gluten, Sunflower Oil, Spirit Vinegar, Vinegar, White Pepper. Allergy Information For allergens, including cereals containing gluten, see ingredients in bold. Storage Suitable for home freezing. Ideally freeze as soon as possible after purchase but always by 'use by' date shown. nNot suitable for cooking from frozen. nDefrost thoroughly for a minimum of 16 hours in the fridge. Once defrosted use within 24 hours and do not refreeze. nFollow the preparation guidelines above. nnKeep refrigerated. Once opened, consume within 1 day and by ‘use by’ date shown. Cooking Instructions Oven Instructions: 200ºC / Fan 180ºC / Gas 6 22 mins Place on a pre-heated baking tray in the centre of a pre-heated oven. Microwave Instructions: Not suitable for microwave cooking. Number of uses 2 Servings Warnings Caution: Hot centre.Immediately after cooking the centre of this product will be extremely hot.Allow it to cool slightly before eating.Caution: This product can contain minor bones.. Recycling info Tray. RecyclenFilm. Recycle at large supermarket Return to Tesco Stores Ltd., Welwyn Garden City AL7 1GA, U.K Net Contents 315g e Nutrition Typical Values Per 100g One fishcake (158g) Energy 670kJ / 160kcal 1059kJ / 252kcal Fat 5.6g 8.9g Saturates 1.1g 1.7g Carbohydrate 19.3g 30.4g Sugars 2.2g 3.5g Fibre 1.3g 2.1g Protein 7.3g 11.5g Salt 0.96g 1.51g * Reference intake of an average adult (8400 kJ / 2000 kcal) - - When cooked according to instructions. - - Safety information View more safety information Caution: Hot centre.Immediately after cooking the centre of this product will be extremely hot.Allow it to cool slightly before eating.Caution: This product can contain minor bones..","cooking_instructions":"Oven. Instructions: 200ºC / Fan 180ºC / Gas 6 22 mins Place on a pre-heated baking tray in the centre of a pre-heated oven.. Microwave. Instructions: Not suitable for microwave cooking.","storage":"Suitable for home freezing. Ideally freeze as soon as possible after purchase but always by 'use by' date shown. nNot suitable for cooking from frozen. nDefrost thoroughly for a minimum of 16 hours in the fridge. Once defrosted use within 24 hours and do not refreeze. nFollow the preparation guidelines above. nnKeep refrigerated. Once opened, consume within 1 day and by ‘use by’ date shown.","allergy_info":"For allergens, including cereals containing gluten, see ingredients in bold.","produce_of":"","number_of_uses":"2 Servings","recycling_info":"Tray. RecyclenFilm. Recycle at large supermarket","return_to":"Tesco Stores Ltd.,. Welwyn Garden City AL7 1GA,. U.K","net_content":"315g e","nutrition_per_unit":[{"Typical Values":"Fat","Per 100g":"5.6g","One fishcake (158g)":"8.9g"},{"Typical Values":"Saturates","Per 100g":"1.1g","One fishcake (158g)":"1.7g"},{"Typical Values":"Carbohydrate","Per 100g":"19.3g","One fishcake (158g)":"30.4g"},{"Typical Values":"Sugars","Per 100g":"2.2g","One fishcake (158g)":"3.5g"},{"Typical Values":"Fibre","Per 100g":"1.3g","One fishcake (158g)":"2.1g"},{"Typical Values":"Protein","Per 100g":"7.3g","One fishcake (158g)":"11.5g"},{"Typical Values":"Salt","Per 100g":"0.96g","One fishcake (158g)":"1.51g"},{"Typical Values":"* Reference intake of an average adult (8400 kJ / 2000 kcal)","Per 100g":"-","One fishcake (158g)":"-"},{"Typical Values":"When cooked according to instructions.","Per 100g":"-","One fishcake (158g)":"-"}],"gtin13":"05057753916077","sku":"312358998","timestamp":"2023-01-31T12:07:27Z"},{"title":"Tesco 8 Turkey Sausages 454G","unit_price":"2.75","currency":"£","price_per_quantity":"6.06","quantity":"1","url":"https://www.tesco.com/groceries/en-GB/products/312364224","image":"https://digitalcontent.api.tesco.com/v2/media/ghs/870d48a8-9168-4960-bb57-1e189a4dc30f/09977436-6590-40e4-b3ea-a9b15c926969.jpeg?h=540&w=540","rating":"5","category":"Fresh Food / Fresh Meat & Poultry / Sausages","number_of_reviews":"1","short_desc":"","nutrition":[{"Energy":"704kJ, 167kcal","nutr_percent":"8%"},{"Fat":"5.6g","nutr_percent":"8%"},{"Saturates":"1.8g","nutr_percent":"9%"},{"Sugars":"0.9g","nutr_percent":"1%"},{"Salt":"1.08g","nutr_percent":"18%"}],"ingredients":"Turkey (72%), Water, Rice Flour, Gram Flour, Salt, Maize Starch, Potato Starch, Dextrose, Spices, Stabiliser (Pentasodium Triphosphate), Herbs, Preservative (Sodium. ), Antioxidant (Citric Acid).","description":"2 sausages Energy 704kJ 167kcal 8% of the reference intake Fat 5.6g medium 8% of the reference intake Saturates 1.8g medium 9% of the reference intake Sugars 0.9g low 1% of the reference intake Salt 1.08g medium 18% of the reference intake of the reference intake * Typical values per 100g: Energy 704kJ / 167kcal Product Description 8 Turkey sausages with a herb seasoning. BRITISH TURKEY Seasoned with herbs for extra flavour Pack size: 454G Information Ingredients INGREDIENTS: Turkey (72%), Water, Rice Flour, Gram Flour, Salt, Maize Starch, Potato Starch, Dextrose, Spices, Stabiliser (Pentasodium Triphosphate), Herbs, Preservative (Sodium Sulphite ), Antioxidant (Citric Acid). Allergy Information For allergens, see ingredients in bold. Legal information Packaged in a protective atmosphere.Filled into UK & non-UK natural beef collagen casings Storage Suitable for home freezing. Ideally freeze as soon as possible after purchase but always by 'use by' date shown. nFollow the preparation guidelines above. nOnce defrosted use within 24 hours and do not refreeze. nDefrost thoroughly for a minimum of 24 hours in the fridge.nnKeep refrigerated. nOnce opened, use immediately. Cooking Instructions Oven Instructions: 190°C/Fan 170°C/Gas 5 18-20mins Place on a baking tray in the centre of a pre-heated oven for 18-20 minutes. Turn occasionally. Microwave Instructions: Not suitable for microwave cooking. Grill Instructions: For best results grill. Time: 16-18 mins Temperature: Medium Place under a pre-heated grill for 16-18 minutes. Turn occasionally. Shallow Fry Instructions: 12-15 mins Heat a little oil in a frying pan until hot. Fry for 12-15 minutes over a moderate heat, turning frequently. Drain well before serving. Produce of Made using British turkey. Number of uses 4 Servings Warnings Caution: Although every care has been taken to remove bones, some may remain.Caution: Always wash hands, surfaces and utensils after contact with raw meat..Caution: This product contains raw meat.. Recycling info Film. Don't Recycle Return to Tesco Stores Ltd., Welwyn Garden City AL7 1GA, U.K Net Contents 454g e Nutrition Typical Values Per 100g 2 sausages (100g**) Energy 704kJ / 167kcal 704kJ / 167kcal Fat 5.6g 5.6g Saturates 1.8g 1.8g Carbohydrate 9.6g 9.6g Sugars 0.9g 0.9g Fibre 0.5g 0.5g Protein 19.4g 19.4g Salt 1.08g 1.08g * Reference intake of an average adult (8400 kJ / 2000 kcal) - - When grilled according to instructions. - - ** When grilled according to instructions 454g typically weighs 400g. - - Safety information View more safety information Caution: Although every care has been taken to remove bones, some may remain.Caution: Always wash hands, surfaces and utensils after contact with raw meat..Caution: This product contains raw meat..","cooking_instructions":"Oven. Instructions: 190°C/Fan 170°C/Gas 5 18-20mins Place on a baking tray in the centre of a pre-heated oven for 18-20 minutes. Turn occasionally.. Microwave. Instructions: Not suitable for microwave cooking.. Grill. Instructions: For best results grill. Time: 16-18 mins Temperature: Medium Place under a pre-heated grill for 16-18 minutes. Turn occasionally.. Shallow Fry. Instructions: 12-15 mins Heat a little oil in a frying pan until hot. Fry for 12-15 minutes over a moderate heat, turning frequently. Drain well before serving.","storage":"Suitable for home freezing. Ideally freeze as soon as possible after purchase but always by 'use by' date shown. nFollow the preparation guidelines above. nOnce defrosted use within 24 hours and do not refreeze. nDefrost thoroughly for a minimum of 24 hours in the fridge.nnKeep refrigerated. nOnce opened, use immediately.","allergy_info":"For allergens, see ingredients in bold.","produce_of":"Made using British turkey.","number_of_uses":"4 Servings","recycling_info":"Film. Don't Recycle","return_to":"Tesco Stores Ltd.,. Welwyn Garden City AL7 1GA,. U.K","net_content":"454g e","nutrition_per_unit":[{"Typical Values":"Fat","Per 100g":"5.6g","2 sausages (100g**)":"5.6g"},{"Typical Values":"Saturates","Per 100g":"1.8g","2 sausages (100g**)":"1.8g"},{"Typical Values":"Carbohydrate","Per 100g":"9.6g","2 sausages (100g**)":"9.6g"},{"Typical Values":"Sugars","Per 100g":"0.9g","2 sausages (100g**)":"0.9g"},{"Typical Values":"Fibre","Per 100g":"0.5g","2 sausages (100g**)":"0.5g"},{"Typical Values":"Protein","Per 100g":"19.4g","2 sausages (100g**)":"19.4g"},{"Typical Values":"Salt","Per 100g":"1.08g","2 sausages (100g**)":"1.08g"},{"Typical Values":"* Reference intake of an average adult (8400 kJ / 2000 kcal)","Per 100g":"-","2 sausages (100g**)":"-"},{"Typical Values":"When grilled according to instructions.","Per 100g":"-","2 sausages (100g**)":"-"},{"Typical Values":"** When grilled according to instructions 454g typically weighs 400g.","Per 100g":"-","2 sausages (100g**)":"-"}],"gtin13":"05059697390210","sku":"312364224","timestamp":"2023-01-31T12:07:32Z"},{"title":"Tesco Deli Roast Turkey Breast 120G","unit_price":"2.50","currency":"£","price_per_quantity":"2.08","quantity":"1","url":"https://www.tesco.com/groceries/en-GB/products/312712723","image":"https://digitalcontent.api.tesco.com/v2/media/ghs/5c269170-a0b0-45b9-957e-ab889879e53d/373df169-770c-436c-adcc-f17e5d06f881.jpeg?h=540&w=540","rating":"No ratings yet","category":"Fresh Food / Cooked Meats, Antipasti & Dips / Deli Counter","number_of_reviews":"","short_desc":"Any 3 for £6 Clubcard Price - Selected Cheese And Sliced Cooked Meats 30g - 220g Offer valid for delivery from 20/10/2022 until 30/04/2023","nutrition":[{"Energy":"135kJ, 32kcal","nutr_percent":"2%"},{"Fat":"0.3g","nutr_percent":"<1%"},{"Saturates":"<0.1g","nutr_percent":"<1%"},{"Sugars":"0.2g","nutr_percent":"<1%"},{"Salt":"0.25g","nutr_percent":"4%"}],"ingredients":"Turkey Breast (99%), Pea Starch, Dextrose, Salt, Butter (. ), Stabilisers (Disodium Diphosphate, Tetrapotassium Diphosphate), Caramelised Sugar Syrup, Flavouring, Maltodextrin, Acidity Regulator (Monopotassium Citrate), Emulsifier (Monopotassium Phosphate).","description":"One slice Energy 135kJ 32kcal 2% of the reference intake Fat 0.3g low <1% of the reference intake Saturates <0.1g low <1% of the reference intake Sugars 0.2g low <1% of the reference intake Salt 0.25g medium 4% of the reference intake of the reference intake * Typical values per 100g: Energy 450kJ / 106kcal Product Description Sliced, cooked and roasted, formed turkey breast with butter. We work with a long established group of dedicated farms using selected turkey breasts. The turkey is then roasted to give a fuller flavour and succulent texture. Butter basted and roasted for a full flavour 4 Slices Pack size: 120G Information Ingredients INGREDIENTS: Turkey Breast (99%), Pea Starch, Dextrose, Salt, Butter ( Milk ), Stabilisers (Disodium Diphosphate, Tetrapotassium Diphosphate), Caramelised Sugar Syrup, Flavouring, Maltodextrin, Acidity Regulator (Monopotassium Citrate), Emulsifier (Monopotassium Phosphate). Allergy Information For allergens, see ingredients in bold. Legal information Packaged in a protective atmosphere Storage Not suitable for freezing. Keep refrigerated. Once opened, consume within 2 days and by 'use by' date shown. Produce of Made using British turkey. Number of uses 4 Servings Warnings Caution: Although every care has been taken to remove bones, some may remain.Caution: It is normal for there to be an odour from this product which will disappear quickly after opening. Recycling info Film. Recycle at large supermarketnTray. Recycle Return to Tesco Stores Ltd., Welwyn Garden City AL7 1GA, U.K Net Contents 120g e Nutrition Typical Values Per 100g One slice (30g) Energy 450kJ / 106kcal 135kJ / 32kcal Fat 0.8g 0.3g Saturates 0.2g <0.1g Carbohydrate 0.7g 0.2g Sugars 0.7g 0.2g Fibre 0.6g 0.2g Protein 23.6g 7.1g Salt 0.83g 0.25g * Reference intake of an average adult (8400 kJ / 2000 kcal) - - As sold - - Safety information View more safety information Caution: Although every care has been taken to remove bones, some may remain.Caution: It is normal for there to be an odour from this product which will disappear quickly after opening.","cooking_instructions":"","storage":"Not suitable for freezing. Keep refrigerated. Once opened, consume within 2 days and by 'use by' date shown.","allergy_info":"For allergens, see ingredients in bold.","produce_of":"Made using British turkey.","number_of_uses":"4 Servings","recycling_info":"Film. Recycle at large supermarketnTray. Recycle","return_to":"Tesco Stores Ltd.,. Welwyn Garden City AL7 1GA,. U.K","net_content":"120g e","nutrition_per_unit":[{"Typical Values":"Fat","Per 100g":"0.8g","One slice (30g)":"0.3g"},{"Typical Values":"Saturates","Per 100g":"0.2g","One slice (30g)":"<0.1g"},{"Typical Values":"Carbohydrate","Per 100g":"0.7g","One slice (30g)":"0.2g"},{"Typical Values":"Sugars","Per 100g":"0.7g","One slice (30g)":"0.2g"},{"Typical Values":"Fibre","Per 100g":"0.6g","One slice (30g)":"0.2g"},{"Typical Values":"Protein","Per 100g":"23.6g","One slice (30g)":"7.1g"},{"Typical Values":"Salt","Per 100g":"0.83g","One slice (30g)":"0.25g"},{"Typical Values":"* Reference intake of an average adult (8400 kJ / 2000 kcal)","Per 100g":"-","One slice (30g)":"-"},{"Typical Values":"As sold","Per 100g":"-","One slice (30g)":"-"}],"gtin13":"05059512732904","sku":"312712723","timestamp":"2023-01-31T12:07:36Z"},{"title":"Tesco Plant Chef 6 Leek & Mushroom Meat Free Bangers 300G","unit_price":"2.15","currency":"£","price_per_quantity":"7.17","quantity":"1","url":"https://www.tesco.com/groceries/en-GB/products/312234816","image":"https://digitalcontent.api.tesco.com/v2/media/ghs/a1794399-d40d-4705-86c8-3a8289521eee/b07430d9-d2b1-46ee-95ab-c4603a4c2560.jpeg?h=540&w=540","rating":"5","category":"Fresh Food / Chilled Vegetarian & Vegan / Sausages","number_of_reviews":"3","short_desc":"","nutrition":[{"Energy":"744kJ, 179kcal","nutr_percent":"9%"},{"Fat":"10.0g","nutr_percent":"14%"},{"Saturates":"1.8g","nutr_percent":"9%"},{"Sugars":"1.1g","nutr_percent":"1%"},{"Salt":"1.10g","nutr_percent":"18%"}],"ingredients":"Water, Leek (11%), Mushroom (11%), Reconstituted. Protein (11%), Rapeseed Oil,. Protein Concentrate, Pea Protein, Rice Flour, Potato Starch, Stabilisers (Methyl Cellulose, Konjac Gum), Parsley, Maize Flour, Pea Fibre, Shea Fat, Salt, Yeast Extract, Maltodextrin, Dextrose, Colour (Plain Caramel), Coconut Oil, Flavouring, Thyme, Black Pepper, Maize Starch, Beetroot Powder, Onion Powder.","description":"Suitable for vegans 2 bangers Energy 744kJ 179kcal 9% of the reference intake Fat 10.0g medium 14% of the reference intake Saturates 1.8g medium 9% of the reference intake Sugars 1.1g low 1% of the reference intake Salt 1.10g medium 18% of the reference intake of the reference intake * Typical values per 100g: Energy 846kJ / 203kcal Product Description Seasoned leek and mushroom with soya and pea protein. The Plant Chef   Derek Sarno   is the culinary talent transforming crowd   pleasing classics into 100% plant based dishes with big, bold flavours that pack a tasty punch. 100% Plant Based SOYA and PEA protein with leek, mushrooms and thyme. Pack size: 300G Information Ingredients INGREDIENTS: Water, Leek (11%), Mushroom (11%), Reconstituted Soya Protein (11%), Rapeseed Oil, S oya Protein Concentrate, Pea Protein, Rice Flour, Potato Starch, Stabilisers (Methyl Cellulose, Konjac Gum), Parsley, Maize Flour, Pea Fibre, Shea Fat, Salt, Yeast Extract, Maltodextrin, Dextrose, Colour (Plain Caramel), Coconut Oil, Flavouring, Thyme, Black Pepper, Maize Starch, Beetroot Powder, Onion Powder. Allergy Information For allergens, see ingredients in bold. Legal information Filled into plant-based casings. Storage Suitable for home freezing. Ideally freeze as soon as possible after purchase but always by 'use by' date shown. nKeep refrigerated. Once opened, consume within 2 days and by 'use by' date shown. Cooking Instructions Oven Instructions: 200°C/Fan 180°C/Gas 6 16-17 mins Place onto a non-stick baking tray and place in the centre of a pre-heated oven, turning halfway through cooking. Oven from frozen Instructions: 200°C/Fan 180°C/Gas 6 23 mins Place onto a non-stick baking tray and place in the centre of a pre-heated oven, turning halfway through cooking. Microwave Instructions: Not suitable for microwave cooking. Grill Instructions: Chilled: 13 mins Frozen: 14 mins Place on a non-stick tray and grill under a medium heat, turning occasionally. Shallow Fry Instructions: For best results, pan fry. Pan Fry Chilled: 8 mins Frozen: 16 mins Heat a little oil in a frying pan until hot and then fry on a medium heat, turning frequently. Number of uses 3 Servings Recycling info Tray. RecyclenSleeve. RecyclenFilm. Recycle at large supermarket Return to Tesco Stores Ltd., Welwyn Garden City AL7 1GA, U.K Net Contents 300g e Nutrition Typical Values Per 100g 2 bangers (88g**) Energy 846kJ / 203kcal 744kJ / 179kcal Fat 11.4g 10.0g Saturates 2.0g 1.8g Carbohydrate 11.2g 9.9g Sugars 1.3g 1.1g Fibre 5.0g 4.4g Protein 11.4g 10.0g Salt 1.25g 1.10g * Reference intake of an average adult (8400 kJ / 2000 kcal) - - When pan fried according to instructions. - - ** When pan fried according to instructions 300g typically weighs 264g. - -","cooking_instructions":"Oven. Instructions: 200°C/Fan 180°C/Gas 6 16-17 mins Place onto a non-stick baking tray and place in the centre of a pre-heated oven, turning halfway through cooking.. Oven from frozen. Instructions: 200°C/Fan 180°C/Gas 6 23 mins Place onto a non-stick baking tray and place in the centre of a pre-heated oven, turning halfway through cooking.. Microwave. Instructions: Not suitable for microwave cooking.. Grill. Instructions: Chilled: 13 mins Frozen: 14 mins Place on a non-stick tray and grill under a medium heat, turning occasionally.. Shallow Fry. Instructions: For best results, pan fry. Pan Fry Chilled: 8 mins Frozen: 16 mins Heat a little oil in a frying pan until hot and then fry on a medium heat, turning frequently.","storage":"Suitable for home freezing. Ideally freeze as soon as possible after purchase but always by 'use by' date shown. nKeep refrigerated. Once opened, consume within 2 days and by 'use by' date shown.","allergy_info":"For allergens, see ingredients in bold.","produce_of":"","number_of_uses":"3 Servings","recycling_info":"Tray. RecyclenSleeve. RecyclenFilm. Recycle at large supermarket","return_to":"Tesco Stores Ltd.,. Welwyn Garden City AL7 1GA,. U.K","net_content":"300g e","nutrition_per_unit":[{"Typical Values":"Fat","Per 100g":"11.4g","2 bangers (88g**)":"10.0g"},{"Typical Values":"Saturates","Per 100g":"2.0g","2 bangers (88g**)":"1.8g"},{"Typical Values":"Carbohydrate","Per 100g":"11.2g","2 bangers (88g**)":"9.9g"},{"Typical Values":"Sugars","Per 100g":"1.3g","2 bangers (88g**)":"1.1g"},{"Typical Values":"Fibre","Per 100g":"5.0g","2 bangers (88g**)":"4.4g"},{"Typical Values":"Protein","Per 100g":"11.4g","2 bangers (88g**)":"10.0g"},{"Typical Values":"Salt","Per 100g":"1.25g","2 bangers (88g**)":"1.10g"},{"Typical Values":"* Reference intake of an average adult (8400 kJ / 2000 kcal)","Per 100g":"-","2 bangers (88g**)":"-"},{"Typical Values":"When pan fried according to instructions.","Per 100g":"-","2 bangers (88g**)":"-"},{"Typical Values":"** When pan fried according to instructions 300g typically weighs 264g.","Per 100g":"-","2 bangers (88g**)":"-"}],"gtin13":"05059697724282","sku":"312234816","timestamp":"2023-01-31T12:07:39Z"},{"title":"Tesco Perfectly Ripe Conference Minimum 4 Pack Pear","unit_price":"2.00","currency":"£","price_per_quantity":"0.50","quantity":"1","url":"https://www.tesco.com/groceries/en-GB/products/284475129","image":"https://digitalcontent.api.tesco.com/v2/media/ghs/69737486-ff90-4b6e-b665-2948fad3c0e8/e9362a8e-db2c-4326-ad37-e3bdd1a03e9d.jpeg?h=540&w=540","rating":"3.9","category":"Fresh Food / Fresh Fruit / Apples & Pears","number_of_reviews":"12","short_desc":"","nutrition":[{"Energy":"287kJ, 68kcal","nutr_percent":"3%"},{"Fat":"0.1g","nutr_percent":"<1%"},{"Saturates":"<0.1g","nutr_percent":"<1%"},{"Sugars":"14.5g","nutr_percent":"16%"},{"Salt":"<0.01g","nutr_percent":"<1%"}],"ingredients":"Pear","description":"One typical pear Energy 287kJ 68kcal 3% of the reference intake Fat 0.1g low <1% of the reference intake Saturates <0.1g low <1% of the reference intake Sugars 14.5g medium 16% of the reference intake Salt <0.01g low <1% of the reference intake of the reference intake * Typical values per 100g: Energy 216kJ / 51kcal Product Description Pears. Hand picked. Gently ripened for their sweet flavour and soft, juicy bite Working in partnership with trusted growers from across Europe, all our Conference pears are hand picked from carefully tended orchards. Each pear is gently ripened so you can enjoy its sweet flavour and soft, juicy bite. Hand picked. Gently ripened for their sweet flavour and soft, juicy bite. Working in partnership with trusted growers from across Europe, all our Conference pears are hand picked from carefully tended orchards. Each pear is gently ripened so you can enjoy its sweet flavour and soft, juicy bite. Information Ingredients Pear Storage Keep in the fridge. Produce of Produce of Preparation and Usage Wash before use. Number of uses 4 Servings Return to Tesco Stores Ltd., Welwyn Garden City AL7 1GA, U.K Net Contents 4 Nutrition Typical Values 100g contains A serving contains Energy 216kJ / 51kcal 287kJ / 68kcal Fat 0.1g 0.1g Saturates <0.1g <0.1g Carbohydrate 10.9g 14.5g Sugars 10.9g 14.5g Fibre 2.7g 3.6g Protein 0.3g 0.4g Salt <0.01g <0.01g * Reference intake of an average adult (8400 kJ / 2000 kcal) - - As sold - -","cooking_instructions":"Wash before use.","storage":"Keep in the fridge.","allergy_info":"","produce_of":"Produce of","number_of_uses":"4 Servings","recycling_info":"","return_to":"Tesco Stores Ltd.,. Welwyn Garden City AL7 1GA,. U.K","net_content":"4","nutrition_per_unit":[{"Typical Values":"Fat","100g contains":"0.1g","A serving contains":"0.1g"},{"Typical Values":"Saturates","100g contains":"<0.1g","A serving contains":"<0.1g"},{"Typical Values":"Carbohydrate","100g contains":"10.9g","A serving contains":"14.5g"},{"Typical Values":"Sugars","100g contains":"10.9g","A serving contains":"14.5g"},{"Typical Values":"Fibre","100g contains":"2.7g","A serving contains":"3.6g"},{"Typical Values":"Protein","100g contains":"0.3g","A serving contains":"0.4g"},{"Typical Values":"Salt","100g contains":"<0.01g","A serving contains":"<0.01g"},{"Typical Values":"* Reference intake of an average adult (8400 kJ / 2000 kcal)","100g contains":"-","A serving contains":"-"},{"Typical Values":"As sold","100g contains":"-","A serving contains":"-"}],"gtin13":"00000003249550","sku":"284475129","timestamp":"2023-01-31T12:07:43Z"},{"title":"Tesco Finest Ranch Steaks 280G","unit_price":"6.00","currency":"£","price_per_quantity":"21.43","quantity":"1","url":"https://www.tesco.com/groceries/en-GB/products/311792847","image":"https://digitalcontent.api.tesco.com/v2/media/ghs-mktg/b0b04216-fa73-466d-a9d7-c9fcfa1ce9b3/no-image.jpeg?h=540&w=540","rating":"No ratings yet","category":"Fresh Food / Ready Meals / Tesco Finest £12 Dinner For Two","number_of_reviews":"","short_desc":"Tesco Finest* Meal Deal for £12 Clubcard Price - Buy 1 Main, 1 Side, 1 Dessert & A Drink Offer valid for delivery from 01/02/2023 until 08/02/2023","nutrition":[{"Energy":"885kJ, 211kcal","nutr_percent":"11%"},{"Fat":"10.2g","nutr_percent":"15%"},{"Saturates":"3.8g","nutr_percent":"19%"},{"Sugars":"0g","nutr_percent":"<1%"},{"Salt":"0.14g","nutr_percent":"2%"}],"ingredients":"","description":"One typical steak Energy 885kJ 211kcal 11% of the reference intake Fat 10.2g medium 15% of the reference intake Saturates 3.8g medium 19% of the reference intake Sugars 0g low <1% of the reference intake Salt 0.14g low 2% of the reference intake of the reference intake * Typical values per 100g: Energy 632kJ / 151kcal Product Description 2 Beef steaks. *Maturing cuts of our prime beef for at least 30 days allows all the full flavour of the meat to develop. 30 day matured cuts of tender, full flavoured beef. Pack size: 280G Information Storage Not suitable for cooking from frozen. Defrost thoroughly for a minimum of 12 hours in the fridge. Once defrosted use within 24 hours and do not refreeze. nFollow the preparation guidelines above. nnKeep refrigerated. Once opened, consume within 1 day and by ‘use by’ date shown. nSuitable for home freezing. Ideally freeze as soon as possible after purchase but always by date shown. Cooking Instructions Microwave Instructions: Not suitable for microwave cooking. Shallow Fry Instructions: PAN FRY 2-4 mins Lightly brush each side of the steak with olive oil and season. Fry in a very hot dry heavy based pan over a high heat for 1 minute on each side. For a rare steak remove from the pan. Reduce to a medium heat and continue to cook for a further 1 minute (medium) or 2 minutes (well done), turning once. Remove the steak from the pan and allow to rest in a warm place for 2 minutes before serving. Cooking Precautions Always wash hands, surfaces and utensils thoroughly after contact with raw meat. Produce of Produced in the U.K., Origin the U.K. Preparation and Usage Allow the meat to rest at room temperature for 10 minutes before cooking. Number of uses 2 Servings Warnings Caution: Vacuum packed for freshness. Recycling info Film. Don't RecyclenTray. Recycle Return to Tesco Stores Ltd., Welwyn Garden City AL7 1GA, U.K Net Contents 280g e Nutrition Typical Values Per 100g One typical steak (140g) Energy 632kJ / 151kcal 885kJ / 211kcal Fat 7.3g 10.2g Saturates 2.7g 3.8g Carbohydrate 0g 0g Sugars 0g 0g Fibre 0g 0g Protein 21.4g 29.9g Salt 0.10g 0.14g * Reference intake of an average adult (8400 kJ / 2000 kcal) - - As sold - - Safety information View more safety information Caution: Vacuum packed for freshness.","cooking_instructions":"Microwave. Instructions: Not suitable for microwave cooking.. Shallow Fry. Instructions: PAN FRY 2-4 mins Lightly brush each side of the steak with olive oil and season. Fry in a very hot dry heavy based pan over a high heat for 1 minute on each side. For a rare steak remove from the pan. Reduce to a medium heat and continue to cook for a further 1 minute (medium) or 2 minutes (well done), turning once. Remove the steak from the pan and allow to rest in a warm place for 2 minutes before serving.","storage":"Not suitable for cooking from frozen. Defrost thoroughly for a minimum of 12 hours in the fridge. Once defrosted use within 24 hours and do not refreeze. nFollow the preparation guidelines above. nnKeep refrigerated. Once opened, consume within 1 day and by ‘use by’ date shown. nSuitable for home freezing. Ideally freeze as soon as possible after purchase but always by date shown.","allergy_info":"","produce_of":"Produced in the U.K., Origin the U.K.","number_of_uses":"2 Servings","recycling_info":"Film. Don't RecyclenTray. Recycle","return_to":"Tesco Stores Ltd.,. Welwyn Garden City AL7 1GA,. U.K","net_content":"280g e","nutrition_per_unit":[{"Typical Values":"Fat","Per 100g":"7.3g","One typical steak (140g)":"10.2g"},{"Typical Values":"Saturates","Per 100g":"2.7g","One typical steak (140g)":"3.8g"},{"Typical Values":"Carbohydrate","Per 100g":"0g","One typical steak (140g)":"0g"},{"Typical Values":"Sugars","Per 100g":"0g","One typical steak (140g)":"0g"},{"Typical Values":"Fibre","Per 100g":"0g","One typical steak (140g)":"0g"},{"Typical Values":"Protein","Per 100g":"21.4g","One typical steak (140g)":"29.9g"},{"Typical Values":"Salt","Per 100g":"0.10g","One typical steak (140g)":"0.14g"},{"Typical Values":"* Reference intake of an average adult (8400 kJ / 2000 kcal)","Per 100g":"-","One typical steak (140g)":"-"},{"Typical Values":"As sold","Per 100g":"-","One typical steak (140g)":"-"}],"gtin13":"05059697699047","sku":"311792847","timestamp":"2023-01-31T12:07:47Z"},{"title":"Tesco Finest Deli Smoked Lemon & Herb Turkey Breast 100G","unit_price":"3.00","currency":"£","price_per_quantity":"3.00","quantity":"1","url":"https://www.tesco.com/groceries/en-GB/products/312563417","image":"https://digitalcontent.api.tesco.com/v2/media/ghs/bea9d860-94cd-436d-9277-6583b933ab63/dd02677b-6485-4cef-a2a9-af122d1a1b04.jpeg?h=540&w=540","rating":"No ratings yet","category":"Fresh Food / Cooked Meats, Antipasti & Dips / Deli Counter","number_of_reviews":"","short_desc":"Any 3 for £6 Clubcard Price - Selected Cheese And Sliced Cooked Meats 30g - 220g Offer valid for delivery from 20/10/2022 until 30/04/2023","nutrition":[{"Energy":"142kJ, 34kcal","nutr_percent":"2%"},{"Fat":"0.3g","nutr_percent":"<1%"},{"Saturates":"<0.1g","nutr_percent":"1%"},{"Sugars":"0.4g","nutr_percent":"<1%"},{"Salt":"0.23g","nutr_percent":"4%"}],"ingredients":"Turkey Breast, Glucose Syrup, Fructose, Rice Flour, Sea Salt, Olive Oil, Maize Flour, White Wine Vinegar, Parsley, Smoked Salt, Garlic Powder, Garlic Extract, Chicken Gelatine, Cornflour, Antioxidant (Ascorbic Acid), Maize Starch, Salt, Oregano, Basil, Flavouring, Black Pepper, Acidity Regulator (Acetic Acid), Dextrose.","description":"One slice Energy 142kJ 34kcal 2% of the reference intake Fat 0.3g low <1% of the reference intake Saturates <0.1g low 1% of the reference intake Sugars 0.4g low <1% of the reference intake Salt 0.23g medium 4% of the reference intake of the reference intake * Typical values per 100g: Energy 568kJ / 134kcal Product Description Cooked and smoked, formed turkey breast slices coated with gluten free herb crumb. Our Tesco Finest* cooked meats are made for us by a family owned business with a heritage of over 100 years, making premium quality products. Our British turkey breasts are seasoned with a lemon and herb dressing. They are then slowly cooked, smoked over lemon tree wood chips and hand coated in a gluten free herb crumb. 4 SLICES Smoked with lemon tree wood chips, and coated with a herb crumb. Pack size: 100G Information Ingredients INGREDIENTS: Turkey Breast, Glucose Syrup, Fructose, Rice Flour, Sea Salt, Olive Oil, Maize Flour, White Wine Vinegar, Parsley, Smoked Salt, Garlic Powder, Garlic Extract, Chicken Gelatine, Cornflour, Antioxidant (Ascorbic Acid), Maize Starch, Salt, Oregano, Basil, Flavouring, Black Pepper, Acidity Regulator (Acetic Acid), Dextrose. Storage Keep refrigerated. Once opened, consume within 2 days and by 'use by' date shown. Number of uses 4 Servings Warnings Caution: Although every care has been taken to remove bones, some may remain. Recycling info Base. RecyclenFilm. Recycle at large supermarket Return to Tesco Stores Ltd., Welwyn Garden City AL7 1GA, U.K Net Contents 100g e Nutrition Typical Values Per 100g One slice (25g) Energy 568kJ / 134kcal 142kJ / 34kcal Fat 1.4g 0.3g Saturates 0.4g <0.1g Carbohydrate 1.4g 0.4g Sugars 1.4g 0.4g Fibre 1.3g 0.3g Protein 28.4g 7.1g Salt 0.94g 0.23g * Reference intake of an average adult (8400 kJ / 2000 kcal) - - As sold - - Safety information View more safety information Caution: Although every care has been taken to remove bones, some may remain.","cooking_instructions":"","storage":"Keep refrigerated. Once opened, consume within 2 days and by 'use by' date shown.","allergy_info":"","produce_of":"","number_of_uses":"4 Servings","recycling_info":"Base. RecyclenFilm. Recycle at large supermarket","return_to":"Tesco Stores Ltd.,. Welwyn Garden City AL7 1GA,. U.K","net_content":"100g e","nutrition_per_unit":[{"Typical Values":"Fat","Per 100g":"1.4g","One slice (25g)":"0.3g"},{"Typical Values":"Saturates","Per 100g":"0.4g","One slice (25g)":"<0.1g"},{"Typical Values":"Carbohydrate","Per 100g":"1.4g","One slice (25g)":"0.4g"},{"Typical Values":"Sugars","Per 100g":"1.4g","One slice (25g)":"0.4g"},{"Typical Values":"Fibre","Per 100g":"1.3g","One slice (25g)":"0.3g"},{"Typical Values":"Protein","Per 100g":"28.4g","One slice (25g)":"7.1g"},{"Typical Values":"Salt","Per 100g":"0.94g","One slice (25g)":"0.23g"},{"Typical Values":"* Reference intake of an average adult (8400 kJ / 2000 kcal)","Per 100g":"-","One slice (25g)":"-"},{"Typical Values":"As sold","Per 100g":"-","One slice (25g)":"-"}],"gtin13":"05059697698453","sku":"312563417","timestamp":"2023-01-31T12:07:59Z"},{"title":"This Isn't Beef Plant Based Mince 250G","unit_price":"3.00","currency":"£","price_per_quantity":"12.00","quantity":"1","url":"https://www.tesco.com/groceries/en-GB/products/312582714","image":"https://digitalcontent.api.tesco.com/v2/media/ghs/7bad8f32-99bc-43fc-8caa-c8d9d71e5ea4/e67602bf-cfed-4bd0-aee2-5ce69069fa7c.jpeg?h=540&w=540","rating":"5","category":"Fresh Food / Chilled Vegetarian & Vegan / Mince","number_of_reviews":"6","short_desc":"","nutrition":[{"Energy":"750kJ, 179kcal","nutr_percent":"9%"},{"Fat":"11.0g","nutr_percent":"16%"},{"Saturates":"2.4g","nutr_percent":"12%"},{"Sugars":"<0.1g","nutr_percent":"<1%"},{"Salt":"0.50g","nutr_percent":"8%"}],"ingredients":"Rehydrated Textured. Protein (56%), Water, Rapeseed Oil, Shea Oil, Natural Flavouring, Thickener (Methylcellulose),. Fibre, Potato Starch,. Protein Concentrate (1%), Caramelised Sugar, Colour (Beetroot Red), Salt,. Malt Extract, Vitamin B12, Iron","description":"Suitable for vegans Suitable for vegetarians Of an adult's Reference Intake, one portion (83g) contains: Energy 750kJ 179kcal 9% of the reference intake Fat 11.0g medium 16% of the reference intake Saturates 2.4g medium 12% of the reference intake Sugars <0.1g low <1% of the reference intake Salt 0.50g medium 8% of the reference intake of the reference intake * Typical values per 100g: Energy per 100g Product Description Plant-based beef flavoured mince made from soya protein. 55% Less Saturated Fat* *Compared with a standard portion of 15% fat beef mince of the same weight. This™ is plant-based food for meat loverssss yesss wee knowwwwww iiiit's on everyyy pacckkkkkkkk ummm haveihittheword countyet whambamthank youmammmm iicccannnntt tbeeellieeevveetthhhaattt thiiiisssissssssmyyyy joobbbbbbbbbbbbblollltho idovaluethecreativefree doommmzzztheysaiidicould writeliterallyanythingiwant unluckyyyybyeeeeeethanks cheersbye 100% Plant-Based High in Protein High in Fibre Suitable for Vegetarians & Vegans Pack size: 250G High in Protein High in Fibre Information Ingredients Rehydrated Textured Soya Protein (56%), Water, Rapeseed Oil, Shea Oil, Natural Flavouring, Thickener (Methylcellulose), Oat Fibre, Potato Starch, Soya Protein Concentrate (1%), Caramelised Sugar, Colour (Beetroot Red), Salt, Barley Malt Extract, Vitamin B12, Iron Allergy Information For allergens, including Cereals containing Gluten, see ingredients in bold. Storage Keep refrigerated. Once opened, consume within 24 hours. Do not exceed the use by date. Suitable for freezing. Freeze on day of purchase and use within 1 month. Once defrosted (in a refrigerator) use within 24 hours. Do not re-freeze. Cooking Instructions Shallow Fry Instructions: For best results, pan fry from chilled. 1. Pre-heat 1 tbsp of oil in a non-stick pan over a medium heat. 2. Add mince. Evenly distribute in pan and cook for 8 mins, stirring frequently. 3. Stir into pre-heated sauce or add sauce and simmer for 5 mins. Not suitable for microwave cooking. Produce of Produced in the UK Number of uses One pack contains 3 portions Recycling info Card. RecyclenFilm. Don't RecyclenTray. Recycle Name and address This™, The Aircraft Factory, 100 Cambridge Grove, London W6 0LE. Return to Contact This™ Email us: shout@this.co Or write to us: This™, The Aircraft Factory, 100 Cambridge Grove, London W6 0LE. this.co Net Contents 250g ℮ Nutrition Typical Values per 100g Energy kJ 904 Energy kcal 216 Fat 13.3g (of which Saturates) 2.9g Carbohydrate 2.8g (of which Sugars) 0.1g Fibre 8.3g Protein 17.2g Salt 0.60g Iron 4.9mg (35%)** Vitamin B12 1.0µg (40%)** **RI% = Reference intake of an average adult (8400kJ/2000kcal) -","cooking_instructions":"Shallow Fry. Instructions: For best results, pan fry from chilled.. 1. Pre-heat 1 tbsp of oil in a non-stick pan over a medium heat.. 2. Add mince. Evenly distribute in pan and cook for 8 mins, stirring frequently.. 3. Stir into pre-heated sauce or add sauce and simmer for 5 mins.. Not suitable for microwave cooking.","storage":"Keep refrigerated. Once opened, consume within 24 hours. Do not exceed the use by date. Suitable for freezing. Freeze on day of purchase and use within 1 month. Once defrosted (in a refrigerator) use within 24 hours. Do not re-freeze.","allergy_info":"For allergens, including Cereals containing Gluten, see ingredients in bold.","produce_of":"Produced in the UK","number_of_uses":"One pack contains 3 portions","recycling_info":"Card. RecyclenFilm. Don't RecyclenTray. Recycle","return_to":"Contact This™. Email us: shout@this.co. Or write to us:. This™,. The Aircraft Factory,. 100 Cambridge Grove,. London. W6 0LE.. this.co","net_content":"250g ℮","nutrition_per_unit":[{"Typical Values":"Energy kcal","per 100g":"216"},{"Typical Values":"Fat","per 100g":"13.3g"},{"Typical Values":"(of which Saturates)","per 100g":"2.9g"},{"Typical Values":"Carbohydrate","per 100g":"2.8g"},{"Typical Values":"(of which Sugars)","per 100g":"0.1g"},{"Typical Values":"Fibre","per 100g":"8.3g"},{"Typical Values":"Protein","per 100g":"17.2g"},{"Typical Values":"Salt","per 100g":"0.60g"},{"Typical Values":"Iron","per 100g":"4.9mg (35%)**"},{"Typical Values":"Vitamin B12","per 100g":"1.0µg (40%)**"},{"Typical Values":"**RI% = Reference intake of an average adult (8400kJ/2000kcal)","per 100g":"-"}],"gtin13":"05060678710460","sku":"312582714","timestamp":"2023-01-31T12:08:02Z"},{"title":"Heck Steak & Butter Meatball 12 Pack 300G","unit_price":"3.50","currency":"£","price_per_quantity":"11.67","quantity":"1","url":"https://www.tesco.com/groceries/en-GB/products/312215033","image":"https://digitalcontent.api.tesco.com/v2/media/ghs/4b5b8369-880f-4ca6-adad-deb6e01e3fd8/fa4c41ab-8de5-404a-adf3-553bfeeeac34.jpeg?h=540&w=540","rating":"1","category":"Fresh Food / Fresh Meat & Poultry / Burgers, Meatballs & BBQ Meat","number_of_reviews":"1","short_desc":"","nutrition":[],"ingredients":"British Beef (89%), Water, Butter (. ) (2%), Seasoning (Salt, Spices, Vegetable Oil, Preservative (Sodium. **), Natural Flavouring, Antioxidant (Ascorbic Acid)), **We use this to help our Meatballs stay fresh for longer","description":"Product Description Beef (89%) and butter meatballs with seasoning. At Heck, we do things our own way We choose the finest ingredients, we make our food in small batches and we take our time over preparation. The result? Flavour you can swear by. Crossed Grain Symbol - GB-176-021 Gluten Free Flavour You Can Swear By Indulgent steak and butter meatballs Made with prime cuts of British beef and a generous helping of butter British by Heck High Protein Pack size: 300G High Protein Information Ingredients British Beef (89%), Water, Butter ( Milk ) (2%), Seasoning (Salt, Spices, Vegetable Oil, Preservative (Sodium Sulphite **), Natural Flavouring, Antioxidant (Ascorbic Acid)), **We use this to help our Meatballs stay fresh for longer Allergy Information Allergens refer to ingredients in bold. Storage Keep refrigerated below 5°C. Suitable for home freezing. Freeze on day of purchase.Please use within one month. Defrost fully before cooking: do not refreeze once defrosted. Cooking Instructions Cooking Instructions Instructions: Remove all packaging before cooking. Cooking instructions are a guide only from chilled. Ensure piping hot throughout before serving. Grill Instructions: Place on the middle shelf under a pre-heated medium hot grill for 12-14 minutes, turning occasionally. Oven cook Instructions: Pre-heat oven to 200°C/ Fan 180°C/ Gas Mark 6. Evenly place the meatballs on a baking tray in the centre of the oven. Cook for 16-18 minutes, turn halfway through. Produce of Produced in the UK using British beef Name and address Heck! Food Ltd, Heck Q, Kirklington, North Yorkshire, DL8 2NY. Return to Heck! Food Ltd, Heck Q, Kirklington, North Yorkshire, DL8 2NY. Net Contents 300g ℮ Nutrition Typical Values Per 100g (grilled) Per 4 Meatballs (62g) (grilled) Energy 894kJ/214kcal 554kJ/133kcal Fat 14g 8.7g of which saturates 5.8g 3.6g Carbohydrate 1.7g 1.1g of which sugars 0.2g 0.1g Protein 20g 12g Salt 1.0g 0.6g","cooking_instructions":"Cooking Instructions. Instructions: Remove all packaging before cooking. Cooking instructions are a guide only from chilled. Ensure piping hot throughout before serving.. Grill. Instructions: Place on the middle shelf under a pre-heated medium hot grill for 12-14 minutes, turning occasionally.. Oven cook. Instructions: Pre-heat oven to 200°C/ Fan 180°C/ Gas Mark 6.. Evenly place the meatballs on a baking tray in the centre of the oven. Cook for 16-18 minutes, turn halfway through.","storage":"Keep refrigerated below 5°C. Suitable for home freezing. Freeze on day of purchase.Please use within one month. Defrost fully before cooking: do not refreeze once defrosted.","allergy_info":"Allergens refer to ingredients in bold.","produce_of":"Produced in the UK using British beef","number_of_uses":"","recycling_info":"","return_to":"Heck! Food Ltd,. Heck Q,. Kirklington,. North Yorkshire,. DL8 2NY.","net_content":"300g ℮","nutrition_per_unit":[{"Typical Values":"Fat","Per 100g (grilled)":"14g","Per 4 Meatballs (62g) (grilled)":"8.7g"},{"Typical Values":"of which saturates","Per 100g (grilled)":"5.8g","Per 4 Meatballs (62g) (grilled)":"3.6g"},{"Typical Values":"Carbohydrate","Per 100g (grilled)":"1.7g","Per 4 Meatballs (62g) (grilled)":"1.1g"},{"Typical Values":"of which sugars","Per 100g (grilled)":"0.2g","Per 4 Meatballs (62g) (grilled)":"0.1g"},{"Typical Values":"Protein","Per 100g (grilled)":"20g","Per 4 Meatballs (62g) (grilled)":"12g"},{"Typical Values":"Salt","Per 100g (grilled)":"1.0g","Per 4 Meatballs (62g) (grilled)":"0.6g"}],"gtin13":"05060317354680","sku":"312215033","timestamp":"2023-01-31T12:08:06Z"},{"title":"Tesco Beef & Ale Stew 580G","unit_price":"6.00","currency":"£","price_per_quantity":"10.34","quantity":"1","url":"https://www.tesco.com/groceries/en-GB/products/306820448","image":"https://digitalcontent.api.tesco.com/v2/media/ghs/55b8b857-8ac6-4fda-939b-b0e1952bf6f4/snapshotimagehandler_1579163074.jpeg?h=540&w=540","rating":"3.1","category":"Fresh Food / Fresh Meat & Poultry / Ready to Cook","number_of_reviews":"9","short_desc":"","nutrition":[{"Energy":"1304kJ, 311kcal","nutr_percent":"16%"},{"Fat":"14.6g","nutr_percent":"21%"},{"Saturates":"6.1g","nutr_percent":"31%"},{"Sugars":"7.3g","nutr_percent":"8%"},{"Salt":"1.48g","nutr_percent":"25%"}],"ingredients":"Beef (50%), Carrot, Leek, Bacon Lardons with Added Water (6%) [Pork, Water, Salt, Antioxidant (Sodium Ascorbate) Preservatives (Sodium Nitrite, Sodium Nitrate, Potassium Nitrate)], Beer (. ), Onion, Corn Starch, Sugar, Red Wine Vinegar, Beef Extract, Tomato, Garlic, Colour (Plain Caramel), Molasses, Salt, Parsley, Thyme, Bay Leaf, Preservative (Potassium Sorbate), Black Pepper.","description":"1/2 of a pack Energy 1304kJ 311kcal 16% of the reference intake Fat 14.6g medium 21% of the reference intake Saturates 6.1g high 31% of the reference intake Sugars 7.3g low 8% of the reference intake Salt 1.48g medium 25% of the reference intake of the reference intake * Typical values per 100g: Energy 532kJ / 127kcal Product Description Slow cooked diced beef in an ale gravy with carrot, leek and bacon lardons. Tender beef chunks in ale gravy with bacon lardons, carrots and leeks Pack size: 580G Information Ingredients INGREDIENTS: Beef (50%), Carrot, Leek, Bacon Lardons with Added Water (6%) [Pork, Water, Salt, Antioxidant (Sodium Ascorbate) Preservatives (Sodium Nitrite, Sodium Nitrate, Potassium Nitrate)], Beer ( Barley ), Onion, Corn Starch, Sugar, Red Wine Vinegar, Beef Extract, Tomato, Garlic, Colour (Plain Caramel), Molasses, Salt, Parsley, Thyme, Bay Leaf, Preservative (Potassium Sorbate), Black Pepper. Allergy Information For allergens, see ingredients in bold. Storage Suitable for home freezing. Ideally freeze as soon as possible after purchase but always by 'use by' date shown. nNot suitable for cooking from frozen. nOnce defrosted use within 24 hours and do not refreeze. nDefrost thoroughly for a minimum of 12 hours in the fridge.nnKeep refrigerated. Cooking Instructions Oven Instructions: 200°C/Fan 180°C/Gas 6 40 mins Pour contents of the pouch into an ovenproof dish and cover with foil. Place in the centre of a pre-heated oven for 20 minutes. Remove foil and stir sauce before returning to oven for a further 20 minutes. Microwave Instructions: 800W/900W 8 mins / 7mins 30 secs Pierce pouch several times and place on a microwavable plate. Cook on full power for 6 minutes (800W) / 6 minutes (900W). Gently shake pouch and cook on full power for a further 2 minutes (800W) / 1 minute 30 seconds (900W). Stand for 2 minutes after cooking. Stir gravy before serving. Hob Instructions: For best results cook on the hob 8-10 mins Empty contents of pouch into a saucepan. Heat gently for 8-10 minutes, stirring occasionally. until piping hot. Do not allow to boil. Produce of Made using British and Irish beef and British and EU pork. Number of uses 2 Servings Warnings Caution: Although every care has been taken to remove bones, some may remain. Recycling info Carton. RecyclenPouch. Don't Recycle Return to Tesco Stores Ltd., Welwyn Garden City AL7 1GA, U.K Net Contents 580g e Nutrition Typical Values Per 100g 1/2 of a pack (245g**) Energy 532kJ / 127kcal 1304kJ / 311kcal Fat 6.0g 14.6g Saturates 2.5g 6.1g Carbohydrate 4.3g 10.6g Sugars 3.0g 7.3g Fibre 1.2g 3.0g Protein 13.4g 32.8g Salt 0.61g 1.48g * Reference intake of an average adult (8400 kJ / 2000 kcal) - - When cooked on hob according to instructions. - - ** When cooked on hob according to instructions 580g typically weighs 490g. - - Safety information View more safety information Caution: Although every care has been taken to remove bones, some may remain.","cooking_instructions":"Oven. Instructions: 200°C/Fan 180°C/Gas 6 40 mins Pour contents of the pouch into an ovenproof dish and cover with foil. Place in the centre of a pre-heated oven for 20 minutes. Remove foil and stir sauce before returning to oven for a further 20 minutes.. Microwave. Instructions: 800W/900W 8 mins / 7mins 30 secs. Pierce pouch several times and place on a microwavable plate.. Cook on full power for 6 minutes (800W) / 6 minutes (900W). Gently shake pouch and cook on full power for a further 2 minutes (800W) / 1 minute 30 seconds (900W).. Stand for 2 minutes after cooking. Stir gravy before serving.. Hob. Instructions: For best results cook on the hob. 8-10 mins. Empty contents of pouch into a saucepan.. Heat gently for 8-10 minutes, stirring occasionally. until piping hot.. Do not allow to boil.","storage":"Suitable for home freezing. Ideally freeze as soon as possible after purchase but always by 'use by' date shown. nNot suitable for cooking from frozen. nOnce defrosted use within 24 hours and do not refreeze. nDefrost thoroughly for a minimum of 12 hours in the fridge.nnKeep refrigerated.","allergy_info":"For allergens, see ingredients in bold.","produce_of":"Made using British and Irish beef and British and EU pork.","number_of_uses":"2 Servings","recycling_info":"Carton. RecyclenPouch. Don't Recycle","return_to":"Tesco Stores Ltd.,. Welwyn Garden City AL7 1GA,. U.K","net_content":"580g e","nutrition_per_unit":[{"Typical Values":"Fat","Per 100g":"6.0g","1/2 of a pack (245g**)":"14.6g"},{"Typical Values":"Saturates","Per 100g":"2.5g","1/2 of a pack (245g**)":"6.1g"},{"Typical Values":"Carbohydrate","Per 100g":"4.3g","1/2 of a pack (245g**)":"10.6g"},{"Typical Values":"Sugars","Per 100g":"3.0g","1/2 of a pack (245g**)":"7.3g"},{"Typical Values":"Fibre","Per 100g":"1.2g","1/2 of a pack (245g**)":"3.0g"},{"Typical Values":"Protein","Per 100g":"13.4g","1/2 of a pack (245g**)":"32.8g"},{"Typical Values":"Salt","Per 100g":"0.61g","1/2 of a pack (245g**)":"1.48g"},{"Typical Values":"* Reference intake of an average adult (8400 kJ / 2000 kcal)","Per 100g":"-","1/2 of a pack (245g**)":"-"},{"Typical Values":"When cooked on hob according to instructions.","Per 100g":"-","1/2 of a pack (245g**)":"-"},{"Typical Values":"** When cooked on hob according to instructions 580g typically weighs 490g.","Per 100g":"-","1/2 of a pack (245g**)":"-"}],"gtin13":"05057753918392","sku":"306820448","timestamp":"2023-01-31T12:08:10Z"},{"title":"Tesco Finest Beef Shin With Beef & Truffle Jus 1.61Kg","unit_price":"20.00","currency":"£","price_per_quantity":"12.42","quantity":"1","url":"https://www.tesco.com/groceries/en-GB/products/312084857","image":"https://digitalcontent.api.tesco.com/v2/media/ghs/790c86f3-4526-48c6-a4f3-c88e930a8235/daef9cc7-7e31-4d66-a88b-f68d3f6b5b5a_1173214678.jpeg?h=540&w=540","rating":"1","category":"Fresh Food / Fresh Meat & Poultry / Ready to Cook","number_of_reviews":"1","short_desc":"£18.00 Clubcard Price Offer valid for delivery from 01/02/2023 until 21/02/2023","nutrition":[{"Energy":"1834kJ, 439kcal","nutr_percent":"22%"},{"Fat":"23.7g","nutr_percent":"34%"},{"Saturates":"8.4g","nutr_percent":"42%"},{"Sugars":"1.0g","nutr_percent":"1%"},{"Salt":"1.02g","nutr_percent":"17%"}],"ingredients":"Beef (86%), Beef and Truffle Jus [Water, Red Wine (. ), Onion, Beef Extract, Tomato Purée, Butter (. ), Sugar, Cornflour, Truffle, Garlic Purée, Salt, Caramelised Sugar Syrup, Sunflower Oil, Thyme, Carrot, Extra Virgin Olive Oil, Redcurrant Concentrate, Black Pepper, Molasses, Bay, Gelling Agent (Pectin), Flavouring], Sugar, Black Pepper, Salt, Maltodextrin, Cornflour, Yeast Extract, Green Pepper, Red Pepper, Rapeseed Oil, Black Peppercorns, Pink Peppercorns, Green Peppercorns.","description":"1/4 of a pack Energy 1834kJ 439kcal 22% of the reference intake Fat 23.7g high 34% of the reference intake Saturates 8.4g high 42% of the reference intake Sugars 1.0g low 1% of the reference intake Salt 1.02g medium 17% of the reference intake of the reference intake * Typical values per 100g: Energy 771kJ / 184kcal Product Description Slow cooked seasoned beef with a sachet of beef and truffle jus. Sous Vide: The joint has been sealed in an air tight bag and slowly cooked to lock in juices and give a succulent texture. Tender beef shin with a sea salt and peppercorn rub, served with a rich beef and truffle jus Pack size: 1.61KG Information Ingredients INGREDIENTS: Beef (86%), Beef and Truffle Jus [Water, Red Wine ( Sulphites ), Onion, Beef Extract, Tomato Purée, Butter ( Milk ), Sugar, Cornflour, Truffle, Garlic Purée, Salt, Caramelised Sugar Syrup, Sunflower Oil, Thyme, Carrot, Extra Virgin Olive Oil, Redcurrant Concentrate, Black Pepper, Molasses, Bay, Gelling Agent (Pectin), Flavouring], Sugar, Black Pepper, Salt, Maltodextrin, Cornflour, Yeast Extract, Green Pepper, Red Pepper, Rapeseed Oil, Black Peppercorns, Pink Peppercorns, Green Peppercorns. Allergy Information For allergens, see ingredients in bold. Storage Suitable for home freezing. Ideally freeze as soon as possible after purchase but always by 'use by' date shown. nDefrost thoroughly for a minimum of 48 hours in the fridge. Once defrosted use within 24 hours and do not refreeze. nNot suitable for cooking from frozen. nFollow the preparation guidelines above. nnKeep refrigerated. Once opened, consume within 1 day and by ‘use by’ date shown. Cooking Instructions Oven Instructions: 200°C/Fan 180°C/Gas 6 60 mins Remove outer packaging and place sauce sachet to one side. Transfer beef joint and juices into a roasting tray and cover with foil. Place in the centre of a pre-heated oven and cook for 45 minutes, basting at regular intervals. Remove from the oven and discard the foil. Return to oven and cook for the final 15 minutes. Remove from oven and stand for 5 minutes. Oven from frozen Instructions: Not suitable for oven cooking from frozen. Microwave Instructions: Not suitable for microwave cooking. Hob Instructions: Pour contents of jus sachet into a saucepan and heat gently for 3-4 minutes stirring occasionally. Serve with the beef. Produce of Made using British beef. Number of uses 4 Servings Warnings Caution: This product will contain bones..Caution: Contains alcohol.. Recycling info Carton. RecyclenPouch. Don't RecyclenSachet. Don't Recycle Return to Tesco Stores Ltd., Welwyn Garden City AL7 1GA, U.K Net Contents 1.61kg e Nutrition Typical Values Per 100g 1/4 of a pack (238g) Energy 771kJ / 184kcal 1834kJ / 439kcal Fat 9.9g 23.7g Saturates 3.5g 8.4g Carbohydrate 0.4g 1.0g Sugars 0.4g 1.0g Fibre 0.6g 1.3g Protein 23.0g 54.7g Salt 0.43g 1.02g * Reference intake of an average adult (8400 kJ / 2000 kcal) - - When cooked according to instructions. - - Safety information View more safety information Caution: This product will contain bones..Caution: Contains alcohol..","cooking_instructions":"Oven. Instructions: 200°C/Fan 180°C/Gas 6 60 mins Remove outer packaging and place sauce sachet to one side. Transfer beef joint and juices into a roasting tray and cover with foil. Place in the centre of a pre-heated oven and cook for 45 minutes, basting at regular intervals. Remove from the oven and discard the foil. Return to oven and cook for the final 15 minutes. Remove from oven and stand for 5 minutes.. Oven from frozen. Instructions: Not suitable for oven cooking from frozen.. Microwave. Instructions: Not suitable for microwave cooking.. Hob. Instructions: Pour contents of jus sachet into a saucepan and heat gently for 3-4 minutes stirring occasionally. Serve with the beef.","storage":"Suitable for home freezing. Ideally freeze as soon as possible after purchase but always by 'use by' date shown. nDefrost thoroughly for a minimum of 48 hours in the fridge. Once defrosted use within 24 hours and do not refreeze. nNot suitable for cooking from frozen. nFollow the preparation guidelines above. nnKeep refrigerated. Once opened, consume within 1 day and by ‘use by’ date shown.","allergy_info":"For allergens, see ingredients in bold.","produce_of":"Made using British beef.","number_of_uses":"4 Servings","recycling_info":"Carton. RecyclenPouch. Don't RecyclenSachet. Don't Recycle","return_to":"Tesco Stores Ltd.,. Welwyn Garden City AL7 1GA,. U.K","net_content":"1.61kg e","nutrition_per_unit":[{"Typical Values":"Fat","Per 100g":"9.9g","1/4 of a pack (238g)":"23.7g"},{"Typical Values":"Saturates","Per 100g":"3.5g","1/4 of a pack (238g)":"8.4g"},{"Typical Values":"Carbohydrate","Per 100g":"0.4g","1/4 of a pack (238g)":"1.0g"},{"Typical Values":"Sugars","Per 100g":"0.4g","1/4 of a pack (238g)":"1.0g"},{"Typical Values":"Fibre","Per 100g":"0.6g","1/4 of a pack (238g)":"1.3g"},{"Typical Values":"Protein","Per 100g":"23.0g","1/4 of a pack (238g)":"54.7g"},{"Typical Values":"Salt","Per 100g":"0.43g","1/4 of a pack (238g)":"1.02g"},{"Typical Values":"* Reference intake of an average adult (8400 kJ / 2000 kcal)","Per 100g":"-","1/4 of a pack (238g)":"-"},{"Typical Values":"When cooked according to instructions.","Per 100g":"-","1/4 of a pack (238g)":"-"}],"gtin13":"05059697691355","sku":"312084857","timestamp":"2023-01-31T12:08:14Z"},{"title":"Tesco Sugar Snap Peas 150G","unit_price":"1.05","currency":"£","price_per_quantity":"7.00","quantity":"1","url":"https://www.tesco.com/groceries/en-GB/products/293953011","image":"https://digitalcontent.api.tesco.com/v2/media/ghs/7d999a88-18ef-47dd-863c-f3419db53b63/snapshotimagehandler_1758620577.jpeg?h=540&w=540","rating":"2.8","category":"Fresh Food / Fresh Vegetables / Peas, Beans, Sweetcorn & Asparagus","number_of_reviews":"32","short_desc":"","nutrition":[{"Energy":"119kJ, 28kcal","nutr_percent":"1%"},{"Fat":"0.2g","nutr_percent":"<1%"},{"Saturates":"0g","nutr_percent":"0%"},{"Sugars":"2.8g","nutr_percent":"3%"},{"Salt":"<0.01g","nutr_percent":"<1%"}],"ingredients":"Sugarsnap Peas","description":"per 75g Energy 119kJ 28kcal 1% of the reference intake Fat 0.2g low <1% of the reference intake Saturates 0g low 0% of the reference intake Sugars 2.8g low 3% of the reference intake Salt <0.01g low <1% of the reference intake of the reference intake * Typical values per 100g: Energy 159kJ / 38kcal Product Description Sugarsnaps. Harvested by hand Sweet, whole pods picked for their size and crisp texture At Tesco we believe in the importance of expertly selecting our seasonal produce for its freshness and quality. Working in partnership with trusted growers from around the world, our Sugarsnaps are grown in carefully tended fields where the pods are harvested by hand and specially selected for their size, maturity and sweet flavour. Pack size: 150G Information Ingredients Sugarsnap Peas Storage Keep refrigerated. Produce of Produce of China, Egypt, Ethiopia, Guatemala, India, Kenya, Peru, USA, Zimbabwe, United Kingdom Preparation and Usage Remove all packaging. Wash before use. Cooking Warnings: Stir Fry Time: 4-5 mins Heat a tablespoon of Vegetable oil in a heavy based frying pan or wok. Stir-fry for 4-5 minutes or until tender. Steam Time: 3-4 mins Place in a steamer. Steam over a pan of simmering water for 3-4 minutes or until tender. Check food is piping hot throughout before serving. Number of uses 2 Servings Return to Tesco Stores Ltd., Welwyn Garden City AL7 1GA, U.K Net Contents 150g e Nutrition Typical Values 100g contains A serving contains Energy 159kJ / 38kcal 119kJ / 28kcal Fat 0.2g 0.2g Saturates 0g 0g Carbohydrate 4.8g 3.6g Sugars 3.7g 2.8g Fibre 1.5g 1.1g Protein 3.4g 2.6g Salt <0.01g <0.01g Vitamin C 32mg (40%NRV) 24mg (30%NRV) * Reference intake of an average adult (8400 kJ / 2000 kcal) - - As sold - -","cooking_instructions":"Remove all packaging. Wash before use.. Cooking Warnings:. Stir Fry. Time: 4-5 mins. Heat a tablespoon of Vegetable oil in a heavy based frying pan or wok.. Stir-fry for 4-5 minutes or until tender.. Steam. Time: 3-4 mins. Place in a steamer.. Steam over a pan of simmering water for 3-4 minutes or until tender.. Check food is piping hot throughout before serving.","storage":"Keep refrigerated.","allergy_info":"","produce_of":"Produce of China, Egypt, Ethiopia, Guatemala, India, Kenya, Peru, USA, Zimbabwe, United Kingdom","number_of_uses":"2 Servings","recycling_info":"","return_to":"Tesco Stores Ltd.,. Welwyn Garden City AL7 1GA,. U.K","net_content":"150g e","nutrition_per_unit":[{"Typical Values":"Fat","100g contains":"0.2g","A serving contains":"0.2g"},{"Typical Values":"Saturates","100g contains":"0g","A serving contains":"0g"},{"Typical Values":"Carbohydrate","100g contains":"4.8g","A serving contains":"3.6g"},{"Typical Values":"Sugars","100g contains":"3.7g","A serving contains":"2.8g"},{"Typical Values":"Fibre","100g contains":"1.5g","A serving contains":"1.1g"},{"Typical Values":"Protein","100g contains":"3.4g","A serving contains":"2.6g"},{"Typical Values":"Salt","100g contains":"<0.01g","A serving contains":"<0.01g"},{"Typical Values":"Vitamin C","100g contains":"32mg (40%NRV)","A serving contains":"24mg (30%NRV)"},{"Typical Values":"* Reference intake of an average adult (8400 kJ / 2000 kcal)","100g contains":"-","A serving contains":"-"},{"Typical Values":"As sold","100g contains":"-","A serving contains":"-"}],"gtin13":"00000003271445","sku":"293953011","timestamp":"2023-01-31T12:08:18Z"},{"title":"Tesco Mangetout 150G","unit_price":"","currency":"","price_per_quantity":"","quantity":"","url":"https://www.tesco.com/groceries/en-GB/products/293952968","image":"https://digitalcontent.api.tesco.com/v2/media/ghs/8d16064d-9bdd-491b-985e-d20af63ef3d8/ac6d92d6-e71b-4697-8709-b203af5a10d5_294208375.jpeg?h=540&w=540","rating":"3.4","category":"Fresh Food / Fresh Vegetables / Peas, Beans, Sweetcorn & Asparagus","number_of_reviews":"13","short_desc":"","nutrition":[{"Energy":"119kJ, 28kcal","nutr_percent":"1%"},{"Fat":"<0.5","nutr_percent":"<1%"},{"Saturates":"<0.1","nutr_percent":"0%"},{"Sugars":"2.6g","nutr_percent":"3%"},{"Salt":"<0.01","nutr_percent":"0%"}],"ingredients":"Mangetout","description":"per 75g Energy 119kJ 28kcal 1% of the reference intake Fat <0.5 low <1% of the reference intake Saturates <0.1 low 0% of the reference intake Sugars 2.6g low 3% of the reference intake Salt <0.01 low 0% of the reference intake of the reference intake * Typical values per 100g: Energy 159kJ / 38kcal Product Description Mangetout. Harvested by hand Sweet, whole pods picked for their size and crisp texture Harvested by hand Sweet, whole pods picked for their size and crisp texture Pack size: 150G Information Ingredients Mangetout Storage Keep refrigerated. Produce of Produce of Guatemala, Kenya, Peru, Zimbabwe, Zambia, Ethiopia Preparation and Usage Remove all packaging. Wash before use. Cooking Warnings: Stir Fry Time: 4-5 mins Heat a tablespoon of Vegetable oil in a heavy based frying pan or wok. Stir-fry for 4-5 minutes or until tender. Steam Time: 3-4 mins Place in a steamer. Steam over a pan of simmering water for 3-4 minutes or until tender. Check food is piping hot throughout before serving. Number of uses 2 Servings Return to Tesco Stores Ltd., Welwyn Garden City AL7 1GA, U.K Net Contents 150g e Nutrition Typical Values per 100g per 75g Energy 159kJ / 38kcal 119kJ / 28kcal Fat <0.5g <0.5g Saturates <0.1g <0.1g Carbohydrate 4.1g 3.1g Sugars 3.4g 2.6g Fibre 2.6g 2.0g Protein 3.6g 2.7g Salt <0.01g <0.01g Vitamin C 54.0mg (68%NRV) 41.0mg (51%NRV) * Reference intake of an average adult (8400 kJ / 2000 kcal) - - As sold - -","cooking_instructions":"","storage":"Keep refrigerated.","allergy_info":"","produce_of":"Produce of Guatemala, Kenya, Peru, Zimbabwe, Zambia, Ethiopia","number_of_uses":"2 Servings","recycling_info":"","return_to":"Tesco Stores Ltd.,. Welwyn Garden City AL7 1GA,. U.K","net_content":"150g e","nutrition_per_unit":[{"Typical Values":"Fat","per 100g":"<0.5g","per 75g":"<0.5g"},{"Typical Values":"Saturates","per 100g":"<0.1g","per 75g":"<0.1g"},{"Typical Values":"Carbohydrate","per 100g":"4.1g","per 75g":"3.1g"},{"Typical Values":"Sugars","per 100g":"3.4g","per 75g":"2.6g"},{"Typical Values":"Fibre","per 100g":"2.6g","per 75g":"2.0g"},{"Typical Values":"Protein","per 100g":"3.6g","per 75g":"2.7g"},{"Typical Values":"Salt","per 100g":"<0.01g","per 75g":"<0.01g"},{"Typical Values":"Vitamin C","per 100g":"54.0mg (68%NRV)","per 75g":"41.0mg (51%NRV)"},{"Typical Values":"* Reference intake of an average adult (8400 kJ / 2000 kcal)","per 100g":"-","per 75g":"-"},{"Typical Values":"As sold","per 100g":"-","per 75g":"-"}],"gtin13":"00000003271438","sku":"293952968","timestamp":"2023-01-31T12:08:20Z"},{"title":"Tesco Herbs Great For Roasting 30G","unit_price":"0.60","currency":"£","price_per_quantity":"0.20","quantity":"1","url":"https://www.tesco.com/groceries/en-GB/products/289765781","image":"https://digitalcontent.api.tesco.com/v2/media/ghs/bb560825-1592-4671-a5a0-f3804df11a4c/e91c2e77-f28c-4e23-a613-f2f51bdf6fee_439526850.jpeg?h=540&w=540","rating":"No ratings yet","category":"Fresh Food / Fresh Vegetables / Fresh Chillies, Herbs, Garlic & Ginger","number_of_reviews":"","short_desc":"","nutrition":[{"Energy":"54kJ, 13kcal","nutr_percent":"1%"},{"Fat":"0.3g","nutr_percent":"<1%"},{"Saturates":"0.1g","nutr_percent":"1%"},{"Sugars":"<0.1g","nutr_percent":"<1%"},{"Salt":"<0.01g","nutr_percent":"<1%"}],"ingredients":"Rosemary, Sage, Thyme","description":"Energy 54kJ 13kcal 1% of the reference intake Fat 0.3g low <1% of the reference intake Saturates 0.1g low 1% of the reference intake Sugars <0.1g low <1% of the reference intake Salt <0.01g low <1% of the reference intake of the reference intake * Typical values per 100g: Energy 544kJ / 130kcal Product Description Rosemary, sage, thyme. Fragrant Classics A mix of thyme, rosemary and sage, perfect for roasts Fragrant Classics A mix of thyme, rosemary and sage, perfect for roasts Pack size: 30G Information Ingredients Rosemary, Sage, Thyme Storage Keep refrigerated. Herbs can be frozen - chop into ice cube trays, add a little water and freeze. To use just pop the whole herb ice cube into your dish during cooking. Produce of Produce of Preparation and Usage Wash before use Remove elastic band before cooking. Number of uses 3 Servings Return to Tesco Stores Ltd., Welwyn Garden City AL7 1GA, U.K Net Contents 30g e Nutrition Typical Values 100g contains A serving contains Energy 544kJ / 130kcal 54kJ / 13kcal Fat 2.8g 0.3g Saturates 1.4g 0.1g Carbohydrate 15.8g 1.6g Sugars 0.2g <0.1g Fibre 12.5g 1.3g Protein 4.3g 0.4g Salt 0.03g <0.01g * Reference intake of an average adult (8400 kJ / 2000 kcal) - - As sold - -","cooking_instructions":"Wash before use. Remove elastic band before cooking.","storage":"Keep refrigerated. Herbs can be frozen - chop into ice cube trays, add a little water and freeze. To use just pop the whole herb ice cube into your dish during cooking.","allergy_info":"","produce_of":"Produce of","number_of_uses":"3 Servings","recycling_info":"","return_to":"Tesco Stores Ltd.,. Welwyn Garden City AL7 1GA,. U.K","net_content":"30g e","nutrition_per_unit":[{"Typical Values":"Fat","100g contains":"2.8g","A serving contains":"0.3g"},{"Typical Values":"Saturates","100g contains":"1.4g","A serving contains":"0.1g"},{"Typical Values":"Carbohydrate","100g contains":"15.8g","A serving contains":"1.6g"},{"Typical Values":"Sugars","100g contains":"0.2g","A serving contains":"<0.1g"},{"Typical Values":"Fibre","100g contains":"12.5g","A serving contains":"1.3g"},{"Typical Values":"Protein","100g contains":"4.3g","A serving contains":"0.4g"},{"Typical Values":"Salt","100g contains":"0.03g","A serving contains":"<0.01g"},{"Typical Values":"* Reference intake of an average adult (8400 kJ / 2000 kcal)","100g contains":"-","A serving contains":"-"},{"Typical Values":"As sold","100g contains":"-","A serving contains":"-"}],"gtin13":"00000003262795","sku":"289765781","timestamp":"2023-01-31T12:08:24Z"},{"title":"Tesco Bacon Steaks With Cream Cheese & Caramelised Onion 330G","unit_price":"4.00","currency":"£","price_per_quantity":"12.12","quantity":"1","url":"https://www.tesco.com/groceries/en-GB/products/312343416","image":"https://digitalcontent.api.tesco.com/v2/media/ghs/62f69245-3465-45fa-b0a7-bec32967755d/b2c1efaf-f406-4c07-bc6c-3e75ba909111.jpeg?h=540&w=540","rating":"No ratings yet","category":"Fresh Food / Fresh Meat & Poultry / Ready to Cook","number_of_reviews":"","short_desc":"","nutrition":[{"Energy":"1519kJ, 365kcal","nutr_percent":"18%"},{"Fat":"23.5g","nutr_percent":"34%"},{"Saturates":"10.4g","nutr_percent":"52%"},{"Sugars":"10.3g","nutr_percent":"11%"},{"Salt":"1.69g","nutr_percent":"28%"}],"ingredients":"Cured Bacon Steak (63%) [Pork, Water, Salt, Antioxidant (Sodium Ascorbate), Preservatives (Sodium Nitrite, Potassium Nitrate)], Full Fat Soft Cheese (. ), Cream (. ), Red Onion, Water, Sugar, Mature Cheddar Cheese (. ), Mozzarella Full Fat Soft Cheese (. ), White Wine Vinegar, Apple, Rice Flour, Cornflour, High Amylose Maize Starch, Rapeseed Oil, Butter (. ), Brown Sugar, Tapioca Starch, Treacle [Cane Molasses, Partially Inverted Refiners Syrup], Parsley, Lemon Juice, Yeast, Gelling Agent (Powdered Cellulose), Thickeners (Hydroxypropyl Methyl Cellulose, Xanthan Gum, Cross-linked Sodium Carboxy Methyl Cellulose, Methyl Cellulose), Psyllium Husk Powder, Potato Starch, Balsamic Vinegar [Red Wine Vinegar, White Wine Vinegar, Grape Must Concentrate], Onion Powder, Salt, Garlic, Ginger, White Pepper, Black Pepper, Antioxidant (Ascorbic Acid), Acidity Regulator (Citric Acid), Preservative (Calcium Propionate), Firming Agent (Calcium Chloride).","description":"1/2 of a pack Energy 1519kJ 365kcal 18% of the reference intake Fat 23.5g high 34% of the reference intake Saturates 10.4g high 52% of the reference intake Sugars 10.3g medium 11% of the reference intake Salt 1.69g medium 28% of the reference intake of the reference intake * Typical values per 100g: Energy 1033kJ / 248kcal Product Description Cured bacon steaks with added water, topped with a cream cheese melt, caramelised onion chutney and a black pepper and parsley crumb. READY TO COOK Topped with a sweet red onion chutney and a creamy cheese melt Pack size: 330G Information Ingredients INGREDIENTS: Cured Bacon Steak (63%) [Pork, Water, Salt, Antioxidant (Sodium Ascorbate), Preservatives (Sodium Nitrite, Potassium Nitrate)], Full Fat Soft Cheese ( Milk ), Cream ( Milk ), Red Onion, Water, Sugar, Mature Cheddar Cheese ( Milk ), Mozzarella Full Fat Soft Cheese ( Milk ), White Wine Vinegar, Apple, Rice Flour, Cornflour, High Amylose Maize Starch, Rapeseed Oil, Butter ( Milk ), Brown Sugar, Tapioca Starch, Treacle [Cane Molasses, Partially Inverted Refiners Syrup], Parsley, Lemon Juice, Yeast, Gelling Agent (Powdered Cellulose), Thickeners (Hydroxypropyl Methyl Cellulose, Xanthan Gum, Cross-linked Sodium Carboxy Methyl Cellulose, Methyl Cellulose), Psyllium Husk Powder, Potato Starch, Balsamic Vinegar [Red Wine Vinegar, White Wine Vinegar, Grape Must Concentrate], Onion Powder, Salt, Garlic, Ginger, White Pepper, Black Pepper, Antioxidant (Ascorbic Acid), Acidity Regulator (Citric Acid), Preservative (Calcium Propionate), Firming Agent (Calcium Chloride). Allergy Information For allergens, see ingredients in bold. Legal information Packaged in a protective atmosphere Storage Suitable for home freezing. Ideally freeze as soon as possible after purchase but always by 'use by' date shown. nNot suitable for cooking from frozen. nFollow the preparation guidelines above. nOnce defrosted use within 24 hours and do not refreeze. nDefrost thoroughly for a minimum of 12 hours in the fridge.nnKeep refrigerated. Once opened, consume within 1 day and by ‘use by’ date shown. Cooking Instructions Oven Instructions: 200°C / Fan 180°C / Gas 6 Chilled: 25 mins Remove sleeve and film lid. Retain pad underneath steaks during cooking to absorb excess cooking liquid. Place foil tray on a baking tray in the centre of a pre-heated oven. For extra crispy topping, cook for an additional 5 mins. Remove pad from bottom of steaks before serving. Do not overcook. Microwave Instructions: Not suitable for microwave cooking. Produce of Made using EU pork. Number of uses 2 Servings Warnings Caution: This product contains raw meat. Recycling info Tray. RecyclenFilm. Recycle at large supermarketnSleeve. RecyclenPad. Don't Recycle Return to Tesco Stores Ltd., Welwyn Garden City AL7 1GA, U.K Net Contents 330g e Nutrition Typical Values Per 100g 1/2 of a pack (147g**) Energy 1033kJ / 248kcal 1519kJ / 365kcal Fat 16.0g 23.5g Saturates 7.1g 10.4g Carbohydrate 10.1g 14.8g Sugars 7.0g 10.3g Fibre 1.2g 1.8g Protein 15.3g 22.5g Salt 1.15g 1.69g * Reference intake of an average adult (8400 kJ / 2000 kcal) - - ** When cooked according to instructions 330g typically weighs 294g. - - When cooked according to instructions. - - Safety information View more safety information Caution: This product contains raw meat.","cooking_instructions":"Oven. Instructions: 200°C / Fan 180°C / Gas 6 Chilled: 25 mins Remove sleeve and film lid. Retain pad underneath steaks during cooking to absorb excess cooking liquid. Place foil tray on a baking tray in the centre of a pre-heated oven. For extra crispy topping, cook for an additional 5 mins. Remove pad from bottom of steaks before serving. Do not overcook.. Microwave. Instructions: Not suitable for microwave cooking.","storage":"Suitable for home freezing. Ideally freeze as soon as possible after purchase but always by 'use by' date shown. nNot suitable for cooking from frozen. nFollow the preparation guidelines above. nOnce defrosted use within 24 hours and do not refreeze. nDefrost thoroughly for a minimum of 12 hours in the fridge.nnKeep refrigerated. Once opened, consume within 1 day and by ‘use by’ date shown.","allergy_info":"For allergens, see ingredients in bold.","produce_of":"Made using EU pork.","number_of_uses":"2 Servings","recycling_info":"Tray. RecyclenFilm. Recycle at large supermarketnSleeve. RecyclenPad. Don't Recycle","return_to":"Tesco Stores Ltd.,. Welwyn Garden City AL7 1GA,. U.K","net_content":"330g e","nutrition_per_unit":[{"Typical Values":"Fat","Per 100g":"16.0g","1/2 of a pack (147g**)":"23.5g"},{"Typical Values":"Saturates","Per 100g":"7.1g","1/2 of a pack (147g**)":"10.4g"},{"Typical Values":"Carbohydrate","Per 100g":"10.1g","1/2 of a pack (147g**)":"14.8g"},{"Typical Values":"Sugars","Per 100g":"7.0g","1/2 of a pack (147g**)":"10.3g"},{"Typical Values":"Fibre","Per 100g":"1.2g","1/2 of a pack (147g**)":"1.8g"},{"Typical Values":"Protein","Per 100g":"15.3g","1/2 of a pack (147g**)":"22.5g"},{"Typical Values":"Salt","Per 100g":"1.15g","1/2 of a pack (147g**)":"1.69g"},{"Typical Values":"* Reference intake of an average adult (8400 kJ / 2000 kcal)","Per 100g":"-","1/2 of a pack (147g**)":"-"},{"Typical Values":"** When cooked according to instructions 330g typically weighs 294g.","Per 100g":"-","1/2 of a pack (147g**)":"-"},{"Typical Values":"When cooked according to instructions.","Per 100g":"-","1/2 of a pack (147g**)":"-"}],"gtin13":"05059512730658","sku":"312343416","timestamp":"2023-01-31T12:08:27Z"},{"title":"Tesco 2 Breaded Pork Loins With Katsu Sauce 320G","unit_price":"3.75","currency":"£","price_per_quantity":"11.72","quantity":"1","url":"https://www.tesco.com/groceries/en-GB/products/311956729","image":"https://digitalcontent.api.tesco.com/v2/media/ghs/32478c3e-703b-461f-9139-0c277345b5e5/55822a46-c741-4b34-9fed-45ca009ed60c.jpeg?h=540&w=540","rating":"No ratings yet","category":"Fresh Food / Fresh Meat & Poultry / Fresh Pork","number_of_reviews":"","short_desc":"","nutrition":[{"Energy":"995kJ, 236kcal","nutr_percent":"12%"},{"Fat":"6.5g","nutr_percent":"9%"},{"Saturates":"1.6g","nutr_percent":"8%"},{"Sugars":"3.4g","nutr_percent":"4%"},{"Salt":"0.90g","nutr_percent":"15%"}],"ingredients":"Pork Loin (68%), Katsu Curry Sauce (15%) [Water, Rapeseed Oil, Glucose Syrup, Apple Concentrate, Maize Starch, Sugar, Turmeric, Yeast Extract, Salt, Cayenne Pepper, Onion, Cumin, Fenugreek, Garlic Purée, Cane Molasses, Fennel, Cinnamon, Sunflower Oil], Rice Flour, Water, Rapeseed Oil, Desiccated Coconut, Potato Starch, Chickpea Flour, Dextrose Powder, Maize Starch, Sea Salt, Tapioca Starch, Salt, Honey Powder, Sugar, Yeast, Stabiliser (Hydroxypropyl Methyl Cellulose), Parsley, Garlic Powder, Onion Powder, Yeast Extract, Coriander Powder, Psyllium Husk Fibre, Ginger Powder, Mushroom Extract Powder, Cayenne Pepper, Turmeric Powder, Flavouring, Caraway, Fennel, Turmeric Extract.","description":"One breaded loin with sauce (150g**) Energy 995kJ 236kcal 12% of the reference intake Fat 6.5g medium 9% of the reference intake Saturates 1.6g low 8% of the reference intake Sugars 3.4g low 4% of the reference intake Salt 0.90g medium 15% of the reference intake of the reference intake * Typical values per 100g: Energy 663kJ / 157kcal Product Description Pork loin medallions covered with a Katsu style batter and coated in breadcrumb with a sachet of Katsu style curry sauce. Inspired by popular Japanese cuisine, our lean pork loin medallions are coated in a spiced batter and aromatic spiced crumb. Simply pan fry for 10 to 12 minutes, serve sliced over rice with the warmed Katsu sauce poured over. From Trusted Farms Coated in an aromatic crisp crumb with a katsu curry sauce Pack size: 320G Information Ingredients INGREDIENTS: Pork Loin (68%), Katsu Curry Sauce (15%) [Water, Rapeseed Oil, Glucose Syrup, Apple Concentrate, Maize Starch, Sugar, Turmeric, Yeast Extract, Salt, Cayenne Pepper, Onion, Cumin, Fenugreek, Garlic Purée, Cane Molasses, Fennel, Cinnamon, Sunflower Oil], Rice Flour, Water, Rapeseed Oil, Desiccated Coconut, Potato Starch, Chickpea Flour, Dextrose Powder, Maize Starch, Sea Salt, Tapioca Starch, Salt, Honey Powder, Sugar, Yeast, Stabiliser (Hydroxypropyl Methyl Cellulose), Parsley, Garlic Powder, Onion Powder, Yeast Extract, Coriander Powder, Psyllium Husk Fibre, Ginger Powder, Mushroom Extract Powder, Cayenne Pepper, Turmeric Powder, Flavouring, Caraway, Fennel, Turmeric Extract. Legal information Packaged in a protective atmosphere Storage Suitable for home freezing. Ideally freeze as soon as possible after purchase but always by 'use by' date shown. nOnce defrosted use within 24 hours and do not refreeze. nNot suitable for cooking from frozen. nFollow the preparation guidelines above. nnKeep refrigerated. Once opened, consume within 1 day and by ‘use by’ date shown. Cooking Instructions Shallow Fry Instructions: Chilled: 10-12 mins. Heat one to two tablespoons of oil in a non stick pan on a medium heat until hot. Fry Breaded Pork Loins for 10-12 minutes, turn occasionally during cooking. Place sauce sachet in a container of boiling water for 2 minutes and serve alongside. Produce of Made using British or EU pork. See front of pack for specific origin. Preparation and Usage To enjoy your Katsu medlallions at their best, take out of the fridge and remove packaging 10 minutes before cooking. Place sachet sauce to one side. Number of uses 2 Servings Warnings Caution: This product contains raw meat.. Recycling info Film. Recycle at large supermarketnTray. RecyclenSachet. Don't Recycle Return to Tesco Stores Ltd., Welwyn Garden City AL7 1GA, U.K Drained weight - Net Contents 320g e Nutrition Typical Values Per 100g One breaded loin with sauce (150g**) Energy 663kJ / 157kcal 995kJ / 236kcal Fat 4.3g 6.5g Saturates 1.0g 1.6g Carbohydrate 8.6g 12.9g Sugars 2.3g 3.4g Fibre 0.5g 0.7g Protein 20.7g 31.1g Salt 0.60g 0.90g * Reference intake of an average adult (8400 kJ / 2000 kcal) - - When pan fried according to instructions. - - ** When pan fried according to instructions 320g typically weighs 300g. - - Safety information View more safety information Caution: This product contains raw meat..","cooking_instructions":"Shallow Fry. Instructions: Chilled: 10-12 mins. Heat one to two tablespoons of oil in a non stick pan on a medium heat until hot. Fry Breaded Pork Loins for 10-12 minutes, turn occasionally during cooking. Place sauce sachet in a container of boiling water for 2 minutes and serve alongside.","storage":"Suitable for home freezing. Ideally freeze as soon as possible after purchase but always by 'use by' date shown. nOnce defrosted use within 24 hours and do not refreeze. nNot suitable for cooking from frozen. nFollow the preparation guidelines above. nnKeep refrigerated. Once opened, consume within 1 day and by ‘use by’ date shown.","allergy_info":"","produce_of":"Made using British or EU pork. See front of pack for specific origin.","number_of_uses":"2 Servings","recycling_info":"Film. Recycle at large supermarketnTray. RecyclenSachet. Don't Recycle","return_to":"Tesco Stores Ltd.,. Welwyn Garden City AL7 1GA,. U.K","net_content":"320g e","nutrition_per_unit":[{"Typical Values":"Fat","Per 100g":"4.3g","One breaded loin with sauce (150g**)":"6.5g"},{"Typical Values":"Saturates","Per 100g":"1.0g","One breaded loin with sauce (150g**)":"1.6g"},{"Typical Values":"Carbohydrate","Per 100g":"8.6g","One breaded loin with sauce (150g**)":"12.9g"},{"Typical Values":"Sugars","Per 100g":"2.3g","One breaded loin with sauce (150g**)":"3.4g"},{"Typical Values":"Fibre","Per 100g":"0.5g","One breaded loin with sauce (150g**)":"0.7g"},{"Typical Values":"Protein","Per 100g":"20.7g","One breaded loin with sauce (150g**)":"31.1g"},{"Typical Values":"Salt","Per 100g":"0.60g","One breaded loin with sauce (150g**)":"0.90g"},{"Typical Values":"* Reference intake of an average adult (8400 kJ / 2000 kcal)","Per 100g":"-","One breaded loin with sauce (150g**)":"-"},{"Typical Values":"When pan fried according to instructions.","Per 100g":"-","One breaded loin with sauce (150g**)":"-"},{"Typical Values":"** When pan fried according to instructions 320g typically weighs 300g.","Per 100g":"-","One breaded loin with sauce (150g**)":"-"}],"gtin13":"05059697749650","sku":"311956729","timestamp":"2023-01-31T12:08:38Z"},{"title":"Jolly Hog Pork Loin Ribs With Bbq Glaze 625G","unit_price":"7.00","currency":"£","price_per_quantity":"11.20","quantity":"1","url":"https://www.tesco.com/groceries/en-GB/products/311942106","image":"https://digitalcontent.api.tesco.com/v2/media/ghs/fc36c67b-9acd-488c-91d1-ca1d31f3e7d0/5a250ee1-4535-4813-adce-cee55f0a1424.jpeg?h=540&w=540","rating":"4.4","category":"Fresh Food / Fresh Meat & Poultry / Ready to Cook","number_of_reviews":"7","short_desc":"","nutrition":[],"ingredients":"Marinated Pork Ribs (86%) (Pork Ribs (93%), Water, Sugar, Chilli Powder, Tapioca Starch, Black Pepper, Brown Sugar, Onion Powder, Maltodextrin, Smoked Paprika, Cornflour, Sea Salt, Ground Cumin, Caramelised Sugar Syrup, Salt, Paprika, Garlic Powder, Smoke Flavouring, Smoked Salt, Apple Juice Powder, Acid (Citric Acid)), Apple BBQ Sauce (14%) (Water, Sugar, Glucose Syrup, Tomato Puree, Spirit Vinegar, Cornflour, Black Treacle, Molasses, Apple Juice Concentrate, Caramelised Sugar Syrup, Salt, Smoke Flavouring, Onion Powder, Garlic Powder, Black Pepper, Cayenne Pepper, Chilli Powder, Cumin, Garlic Powder, Oregano)","description":"Product Description Marinated slow cooked pork ribs, in a smoky barbecue flavour dry rub with a sachet of apple barbecue flavour sauce. And Now... Enjoy! Try out our serving suggestions here or visit our website for more delicious meal inspiration: www.thejollyhog.com/cook The Secret to The Ultimate Barbecue Pork Loin Ribs The Pork British Pork we only use British pork, farmed to British farming standards. The Flavour Seasoned & Slowey Cooked Flavoured with smoky apple brine and brushed in Jolly hog BBQ dry rub, our pork loin ribs are slow cooked for extra fall off the bone tenderness and juicy succulence. The Glaze Sticky BBQ Glaze Smother the ribs in our sticky BBQ glaze. Hints of black treacle add an irresistible rich, deep taste. Jolly Good Ribs from Three Brothers Our Story Once upon a time there were three jolly brothers...a rugby player, a ship broker and a cabinet maker! The three brothers loved eating meat and decided to create their own meaty delights, which would one day become the best and most delicious in the whole land... We hope that you love our products as much as we do. Max, Josh, Olly We are generally up to fun stuff. So if you have a few minutes, come check us out. Cooks in 30 Minutes Pack size: 625G Information Ingredients Marinated Pork Ribs (86%) (Pork Ribs (93%), Water, Sugar, Chilli Powder, Tapioca Starch, Black Pepper, Brown Sugar, Onion Powder, Maltodextrin, Smoked Paprika, Cornflour, Sea Salt, Ground Cumin, Caramelised Sugar Syrup, Salt, Paprika, Garlic Powder, Smoke Flavouring, Smoked Salt, Apple Juice Powder, Acid (Citric Acid)), Apple BBQ Sauce (14%) (Water, Sugar, Glucose Syrup, Tomato Puree, Spirit Vinegar, Cornflour, Black Treacle, Molasses, Apple Juice Concentrate, Caramelised Sugar Syrup, Salt, Smoke Flavouring, Onion Powder, Garlic Powder, Black Pepper, Cayenne Pepper, Chilli Powder, Cumin, Garlic Powder, Oregano) Storage Keep refrigerated below 5°C. Once opened, keep refrigerated and use within 24 hours. Suitable for freezing. Freeze by date mark shown and use within one month. Defrost thoroughly at the bottom of the fridge before use and use within 24 hours. Never defrost in a warm room. Do not refreeze once defrosted. Cooking Instructions Oven cook Instructions: Conventional 200°C/ Fan 180°C/Gas 6-30 mins. Remove outer packaging and set aside sachet for later use. Do not use if vacuum seal is broken. Empty contents of the pouch and place bone side down on a baking tray and place in the oven for 15 minutes. Remove from the oven, pour the sachet of sauce over the ribs, coating evenly. Return to the oven and continue cooking for a further 15 minutes. Leave to stand for 1 minute before serving. Ensure product is thoroughly cooked and piping hot throughout. Do not reheat. Not suitable for cooking from frozen. Not suitable for microwave cooking. Produce of Produced in UK using British pork Preparation and Usage Try Me... Serve as a whole rack with a side of mac and cheese, or for something lighter shred white cabbage, carrots, and spring onion. Then mix 3tbsp of mayonnaise with 1tbsp of wholegrain mustard and add to the slaw mix. Make the ultimate pork rib roll with a brioche bun, rib meat and the slaw. Number of uses 2 Servings Warnings WARNING: Do not use if vacuum seal is broken. Contains bones - our thick cut ribs are really meaty and whilst we try to remove any element of soft bone, some may still remain. Recycling info Film. Plastic - Not Currently RecyclednSachet. Plastic - Not Currently RecyclednSleeve. Card - Widely Recycled Name and address The Jolly Hog HQ, Museum Street, Bristol, BS1 6ZA. Return to The Jolly Hog HQ, Museum Street, Bristol, BS1 6ZA. thejollyhog.com Net Contents 625g ℮ Nutrition Typical Values (cooked edible portion only) Per 100g (cooked edible portion only) Per 1/2 pack (142g) Energy kJ 1016kJ 1480kJ Energy kcal 243kcal 354kcal Fat 13g 19g of which saturates 4.5g 6.4g Carbohydrates 11g 16g of which sugars 11g 15g Fibre 1g 1.5g Protein 20g 29g Salt 0.51g 0.72g Safety information View more safety information WARNING: Do not use if vacuum seal is broken. Contains bones - our thick cut ribs are really meaty and whilst we try to remove any element of soft bone, some may still remain.","cooking_instructions":"Oven cook. Instructions: Conventional 200°C/ Fan 180°C/Gas 6-30 mins.. Remove outer packaging and set aside sachet for later use. Do not use if vacuum seal is broken. Empty contents of the pouch and place bone side down on a baking tray and place in the oven for 15 minutes. Remove from the oven, pour the sachet of sauce over the ribs, coating evenly. Return to the oven and continue cooking for a further 15 minutes. Leave to stand for 1 minute before serving. Ensure product is thoroughly cooked and piping hot throughout. Do not reheat. Not suitable for cooking from frozen. Not suitable for microwave cooking.","storage":"Keep refrigerated below 5°C. Once opened, keep refrigerated and use within 24 hours. Suitable for freezing. Freeze by date mark shown and use within one month. Defrost thoroughly at the bottom of the fridge before use and use within 24 hours. Never defrost in a warm room. Do not refreeze once defrosted.","allergy_info":"","produce_of":"Produced in UK using British pork","number_of_uses":"2 Servings","recycling_info":"Film. Plastic - Not Currently RecyclednSachet. Plastic - Not Currently RecyclednSleeve. Card - Widely Recycled","return_to":"The Jolly Hog HQ,. Museum Street,. Bristol,. BS1 6ZA.. thejollyhog.com","net_content":"625g ℮","nutrition_per_unit":[{"Typical Values":"Energy kcal","(cooked edible portion only) Per 100g":"243kcal","(cooked edible portion only) Per 1/2 pack (142g)":"354kcal"},{"Typical Values":"Fat","(cooked edible portion only) Per 100g":"13g","(cooked edible portion only) Per 1/2 pack (142g)":"19g"},{"Typical Values":"of which saturates","(cooked edible portion only) Per 100g":"4.5g","(cooked edible portion only) Per 1/2 pack (142g)":"6.4g"},{"Typical Values":"Carbohydrates","(cooked edible portion only) Per 100g":"11g","(cooked edible portion only) Per 1/2 pack (142g)":"16g"},{"Typical Values":"of which sugars","(cooked edible portion only) Per 100g":"11g","(cooked edible portion only) Per 1/2 pack (142g)":"15g"},{"Typical Values":"Fibre","(cooked edible portion only) Per 100g":"1g","(cooked edible portion only) Per 1/2 pack (142g)":"1.5g"},{"Typical Values":"Protein","(cooked edible portion only) Per 100g":"20g","(cooked edible portion only) Per 1/2 pack (142g)":"29g"},{"Typical Values":"Salt","(cooked edible portion only) Per 100g":"0.51g","(cooked edible portion only) Per 1/2 pack (142g)":"0.72g"}],"gtin13":"05032824124025","sku":"311942106","timestamp":"2023-01-31T12:08:42Z"},{"title":"Tesco Finest Chicken Jalfrezi With Pilau Rice 400G","unit_price":"4.00","currency":"£","price_per_quantity":"NaN","quantity":"1","url":"https://www.tesco.com/groceries/en-GB/products/312846109","image":"https://digitalcontent.api.tesco.com/v2/media/ghs/b9c2a1d2-d46a-4db4-bac9-de62ad987301/e9592f6e-fc79-439b-83f7-25c9465c8e42.jpeg?h=540&w=540","rating":"No ratings yet","category":"Fresh Food / Ready Meals / Tesco Finest & Premium Ready Meals","number_of_reviews":"","short_desc":"Any 2 for £7 Clubcard Price - Selected Tesco Finest* Ready Meals 350g - 475g Offer valid for delivery from 07/09/2022 until 21/02/2023","nutrition":[{"Energy":"1737kJ, 411kcal","nutr_percent":"21%"},{"Fat":"7.2g","nutr_percent":"10%"},{"Saturates":"1.3g","nutr_percent":"7%"},{"Sugars":"7.2g","nutr_percent":"8%"},{"Salt":"1.06g","nutr_percent":"18%"}],"ingredients":"Cooked Pilau Rice [Water, Basmati Rice, Ginger Purée, Lemon Juice, Rapeseed Oil, Cumin Seed, Curry Leaves, Green Chilli Purée, Colour (Curcumin)], Cooked Marinated Chicken (20%) [Chicken Breast, Yogurt (. ), Garlic Purée, Rapeseed Oil, Ginger Purée, Smoked Sugar, Coriander Powder, Cumin Powder, Smoked Paprika, Colour (Paprika Extract), Salt, Turmeric, Kashmiri Chilli Powder, Cinnamon, Ground Cardamom, Clove Powder, Fennel Powder, Dill], Onion, Tomato, Tomato Purée, Water, Red Pepper, Green Pepper, Garlic Purée, Ginger Purée, Yogurt (. ), Coriander, Tomato Juice, Cornflour, Rapeseed Oil, Coriander Powder, Salt, Red Chilli Purée, Tamarind Paste, Cumin Powder, Sugar, Cumin Seed, Turmeric, Kashmiri Chilli Powder, Fennel Seed, Concentrated Lemon Juice, Smoked Paprika, Cinnamon, Ground Fenugreek Seed, Colour (Paprika Extract), Clove Powder, Ground Cardamom, Fennel Powder, Dill.","description":"Each pack Energy 1737kJ 411kcal 21% of the reference intake Fat 7.2g low 10% of the reference intake Saturates 1.3g low 7% of the reference intake Sugars 7.2g low 8% of the reference intake Salt 1.06g low 18% of the reference intake of the reference intake * Typical values per 100g: Energy 434kJ / 103kcal Product Description Cooked marinated chicken breast pieces in a tomato, red pepper and chilli sauce with cooked pilau rice. Our experts flame sear our tandoori marinated chicken breast before adding it to a spicy tomato and onion sauce with chunky peppers. The curry is finished with fresh coriander. Our rice is enhanced with a bespoke blend of spices, all tempered to release their natural flavours. Tandoori marinated chicken breast pieces in a rich, spicy tomato and onion sauce with peppers. Pack size: 400G Information Ingredients INGREDIENTS: Cooked Pilau Rice [Water, Basmati Rice, Ginger Purée, Lemon Juice, Rapeseed Oil, Cumin Seed, Curry Leaves, Green Chilli Purée, Colour (Curcumin)], Cooked Marinated Chicken (20%) [Chicken Breast, Yogurt ( Milk ), Garlic Purée, Rapeseed Oil, Ginger Purée, Smoked Sugar, Coriander Powder, Cumin Powder, Smoked Paprika, Colour (Paprika Extract), Salt, Turmeric, Kashmiri Chilli Powder, Cinnamon, Ground Cardamom, Clove Powder, Fennel Powder, Dill], Onion, Tomato, Tomato Purée, Water, Red Pepper, Green Pepper, Garlic Purée, Ginger Purée, Yogurt ( Milk ), Coriander, Tomato Juice, Cornflour, Rapeseed Oil, Coriander Powder, Salt, Red Chilli Purée, Tamarind Paste, Cumin Powder, Sugar, Cumin Seed, Turmeric, Kashmiri Chilli Powder, Fennel Seed, Concentrated Lemon Juice, Smoked Paprika, Cinnamon, Ground Fenugreek Seed, Colour (Paprika Extract), Clove Powder, Ground Cardamom, Fennel Powder, Dill. Allergy Information For allergens, see ingredients in bold. Storage Suitable for home freezing. Ideally freeze as soon as possible after purchase but always by 'use by' date shown. nOnce defrosted use within 24 hours and do not refreeze. nNot suitable for cooking from frozen. nFollow the preparation guidelines above. nDefrost thoroughly for a minimum of 12 hours in the fridge.nnKeep refrigerated. Cooking Instructions Oven Instructions: 190°C/Fan 170°C/Gas 5 30 mins Pierce film lid several times. Place on a baking tray in the centre of a pre-heated oven and stir halfway through heating. Leave to stand for 2 minutes after heating. Stir before serving. Microwave Instructions: For best results microwave heat. 800W 6 mins / 900W 5 mins Pierce film lid several times. Heat on full power and stir halfway through heating. Leave to stand for 2 minutes after heating. Stir before serving. Produce of Made using EU chicken. Number of uses 1 Servings Warnings Caution: Although every care has been taken to remove bones, some may remain. Recycling info Sleeve. RecyclenTray. RecyclenFilm. Recycle at large supermarket Return to Tesco Stores Ltd., Welwyn Garden City AL7 1GA, U.K Net Contents 400g e Nutrition Typical Values Per 100g Each pack (400g) Energy 434kJ / 103kcal 1737kJ / 411kcal Fat 1.8g 7.2g Saturates 0.3g 1.3g Carbohydrate 13.9g 55.6g Sugars 1.8g 7.2g Fibre 1.1g 4.4g Protein 7.2g 28.9g Salt 0.27g 1.06g * Reference intake of an average adult (8400 kJ / 2000 kcal) - - When microwaved according to instructions. - - Safety information View more safety information Caution: Although every care has been taken to remove bones, some may remain.","cooking_instructions":"Oven. Instructions: 190°C/Fan 170°C/Gas 5 30 mins Pierce film lid several times. Place on a baking tray in the centre of a pre-heated oven and stir halfway through heating. Leave to stand for 2 minutes after heating. Stir before serving.. Microwave. Instructions: For best results microwave heat.. 800W 6 mins / 900W 5 mins. Pierce film lid several times.. Heat on full power and stir halfway through heating.. Leave to stand for 2 minutes after heating.. Stir before serving.","storage":"Suitable for home freezing. Ideally freeze as soon as possible after purchase but always by 'use by' date shown. nOnce defrosted use within 24 hours and do not refreeze. nNot suitable for cooking from frozen. nFollow the preparation guidelines above. nDefrost thoroughly for a minimum of 12 hours in the fridge.nnKeep refrigerated.","allergy_info":"For allergens, see ingredients in bold.","produce_of":"Made using EU chicken.","number_of_uses":"1 Servings","recycling_info":"Sleeve. RecyclenTray. RecyclenFilm. Recycle at large supermarket","return_to":"Tesco Stores Ltd.,. Welwyn Garden City AL7 1GA,. U.K","net_content":"400g e","nutrition_per_unit":[{"Typical Values":"Fat","Per 100g":"1.8g","Each pack (400g)":"7.2g"},{"Typical Values":"Saturates","Per 100g":"0.3g","Each pack (400g)":"1.3g"},{"Typical Values":"Carbohydrate","Per 100g":"13.9g","Each pack (400g)":"55.6g"},{"Typical Values":"Sugars","Per 100g":"1.8g","Each pack (400g)":"7.2g"},{"Typical Values":"Fibre","Per 100g":"1.1g","Each pack (400g)":"4.4g"},{"Typical Values":"Protein","Per 100g":"7.2g","Each pack (400g)":"28.9g"},{"Typical Values":"Salt","Per 100g":"0.27g","Each pack (400g)":"1.06g"},{"Typical Values":"* Reference intake of an average adult (8400 kJ / 2000 kcal)","Per 100g":"-","Each pack (400g)":"-"},{"Typical Values":"When microwaved according to instructions.","Per 100g":"-","Each pack (400g)":"-"}],"gtin13":"05059697689086","sku":"312846109","timestamp":"2023-01-31T12:08:46Z"},{"title":"Tesco Sage & Onion Pork Steaks With Apple Sauce 360G","unit_price":"4.00","currency":"£","price_per_quantity":"11.11","quantity":"1","url":"https://www.tesco.com/groceries/en-GB/products/312088467","image":"https://digitalcontent.api.tesco.com/v2/media/ghs/ab2ee14e-be88-4247-bce3-90875d5bb99e/55f0d30c-8032-4bc8-91fc-9363752f2186_706128975.jpeg?h=540&w=540","rating":"5","category":"Fresh Food / Fresh Meat & Poultry / Ready to Cook","number_of_reviews":"1","short_desc":"£3.50 Clubcard Price Offer valid for delivery from 01/02/2023 until 21/02/2023","nutrition":[{"Energy":"1198kJ, 286kcal","nutr_percent":"14%"},{"Fat":"13.3g","nutr_percent":"19%"},{"Saturates":"5.2g","nutr_percent":"26%"},{"Sugars":"12.1g","nutr_percent":"13%"},{"Salt":"0.34g","nutr_percent":"6%"}],"ingredients":"Pork Loin (63%), Bramley Apple Sauce (27%) [Apple, Water, Sugar, Dried Apple, Cider Vinegar, Partially Inverted Sugar Syrup, Cornflour, Cider, Brown Sugar, Concentrated Lemon Juice, Salt], Water, Sugar, Salt, Cornflour, Dried Onion, Onion, Glucose Syrup, Dried Sage, Onion Powder, Dried Parsley, Acidity Regulator (Sodium Carbonate), Black Pepper, Dried Yeast, Tapioca Starch, Spirit Vinegar, Garlic Powder, Rapeseed Oil, Citric Acid, Dried Thyme, Coriander Powder, Stabiliser (Xanthan Gum), Paprika Extract, Sage Extract.","description":"1/2 of a pack Energy 1198kJ 286kcal 14% of the reference intake Fat 13.3g medium 19% of the reference intake Saturates 5.2g medium 26% of the reference intake Sugars 12.1g medium 13% of the reference intake Salt 0.34g low 6% of the reference intake of the reference intake * Typical values per 100g: Energy 888kJ / 212kcal Product Description Boneless pork loin steaks with an onion and sage flavoured coating, and a Bramley apple sauce sachet. READY TO COOK Herby and savoury pork loin steaks served with classic apple sauce Pack size: 360G Information Ingredients INGREDIENTS: Pork Loin (63%), Bramley Apple Sauce (27%) [Apple, Water, Sugar, Dried Apple, Cider Vinegar, Partially Inverted Sugar Syrup, Cornflour, Cider, Brown Sugar, Concentrated Lemon Juice, Salt], Water, Sugar, Salt, Cornflour, Dried Onion, Onion, Glucose Syrup, Dried Sage, Onion Powder, Dried Parsley, Acidity Regulator (Sodium Carbonate), Black Pepper, Dried Yeast, Tapioca Starch, Spirit Vinegar, Garlic Powder, Rapeseed Oil, Citric Acid, Dried Thyme, Coriander Powder, Stabiliser (Xanthan Gum), Paprika Extract, Sage Extract. Legal information Packaged in a protective atmosphere Storage Suitable for home freezing. Ideally freeze as soon as possible after purchase but always by 'use by' date shown. nDefrost thoroughly for a minimum of 12 hours in the fridge. Once defrosted use within 24 hours and do not refreeze. nNot suitable for cooking from frozen. nFollow the preparation guidelines above. nnKeep refrigerated. Once opened, consume within 1 day and by ‘use by’ date shown. Cooking Instructions Oven Instructions: 200°C/Fan 180°C/Gas 6 23 mins Remove sleeve and film lid and set sauce sachet to one side. Place foil tray on a baking tray in the centre of a pre-heated oven for 18 minutes. Remove from the oven, drain excess cooking liquid. Add sauce to the side of the steaks and return to the oven for 5 minutes. Microwave Instructions: Not suitable for microwave cooking. Produce of Made using British or EU pork. See front of pack for specific origin. Number of uses 2 Servings Warnings Caution: This product contains raw meat..Caution: Always wash hands, surfaces and utensils after contact with raw meat.. Recycling info Tray. RecyclenFilm. Recycle at large supermarketnSleeve. RecyclenSachet. Don't Recycle Return to Tesco Stores Ltd., Welwyn Garden City AL7 1GA, U.K Net Contents 360g e Nutrition Typical Values Per 100g 1/2 of a pack (135g**) Energy 888kJ / 212kcal 1198kJ / 286kcal Fat 9.9g 13.3g Saturates 3.8g 5.2g Carbohydrate 9.6g 12.9g Sugars 8.9g 12.1g Fibre 1.2g 1.6g Protein 20.6g 27.9g Salt 0.25g 0.34g * Reference intake of an average adult (8400 kJ / 2000 kcal) - - ** When cooked according to instructions 360g typically weighs 270g. - - When cooked according to instructions. - - Safety information View more safety information Caution: This product contains raw meat..Caution: Always wash hands, surfaces and utensils after contact with raw meat..","cooking_instructions":"Oven. Instructions: 200°C/Fan 180°C/Gas 6 23 mins Remove sleeve and film lid and set sauce sachet to one side. Place foil tray on a baking tray in the centre of a pre-heated oven for 18 minutes. Remove from the oven, drain excess cooking liquid. Add sauce to the side of the steaks and return to the oven for 5 minutes.. Microwave. Instructions: Not suitable for microwave cooking.","storage":"Suitable for home freezing. Ideally freeze as soon as possible after purchase but always by 'use by' date shown. nDefrost thoroughly for a minimum of 12 hours in the fridge. Once defrosted use within 24 hours and do not refreeze. nNot suitable for cooking from frozen. nFollow the preparation guidelines above. nnKeep refrigerated. Once opened, consume within 1 day and by ‘use by’ date shown.","allergy_info":"","produce_of":"Made using British or EU pork. See front of pack for specific origin.","number_of_uses":"2 Servings","recycling_info":"Tray. RecyclenFilm. Recycle at large supermarketnSleeve. RecyclenSachet. Don't Recycle","return_to":"Tesco Stores Ltd.,. Welwyn Garden City AL7 1GA,. U.K","net_content":"360g e","nutrition_per_unit":[{"Typical Values":"Fat","Per 100g":"9.9g","1/2 of a pack (135g**)":"13.3g"},{"Typical Values":"Saturates","Per 100g":"3.8g","1/2 of a pack (135g**)":"5.2g"},{"Typical Values":"Carbohydrate","Per 100g":"9.6g","1/2 of a pack (135g**)":"12.9g"},{"Typical Values":"Sugars","Per 100g":"8.9g","1/2 of a pack (135g**)":"12.1g"},{"Typical Values":"Fibre","Per 100g":"1.2g","1/2 of a pack (135g**)":"1.6g"},{"Typical Values":"Protein","Per 100g":"20.6g","1/2 of a pack (135g**)":"27.9g"},{"Typical Values":"Salt","Per 100g":"0.25g","1/2 of a pack (135g**)":"0.34g"},{"Typical Values":"* Reference intake of an average adult (8400 kJ / 2000 kcal)","Per 100g":"-","1/2 of a pack (135g**)":"-"},{"Typical Values":"** When cooked according to instructions 360g typically weighs 270g.","Per 100g":"-","1/2 of a pack (135g**)":"-"},{"Typical Values":"When cooked according to instructions.","Per 100g":"-","1/2 of a pack (135g**)":"-"}],"gtin13":"05059697692017","sku":"312088467","timestamp":"2023-01-31T12:08:55Z"},{"title":"Cinnamon Kitchen Old Delhi Butter Chicken 600G","unit_price":"7.00","currency":"£","price_per_quantity":"11.67","quantity":"1","url":"https://www.tesco.com/groceries/en-GB/products/312984325","image":"https://digitalcontent.api.tesco.com/v2/media/ghs/0074fdbc-eeed-49a4-b855-c8894b58e960/c5de85c2-fc5a-488c-b2fe-510c1a28b83f_1929255479.jpeg?h=540&w=540","rating":"5","category":"Fresh Food / Ready Meals / Indian Ready Meals","number_of_reviews":"1","short_desc":"£5.00 Clubcard Price Offer valid for delivery from 01/02/2023 until 21/02/2023","nutrition":[],"ingredients":"Turmeric and Lemon Rice (34%): Cooked Basmati Rice (88%) (Water, Basmati Rice), Onions, Lemon Juice (2.5%), Toasted. Oil, Ginger Purée, Salt, Lemon Zest, Curry Leaves, Black. Seeds, Cumin Seeds, Turmeric, Whole Black Cardamom Seeds, Cracked Black Pepper, Crushed Red Chillies, Bombay Aloo (33%): Potatoes (47%), Tomatoes (24%), Onions (15%), Rapeseed Oil, Ginger Purée, Cane Sugar, Tomato Paste, Ground Coriander, Green Chillies, Salt, Turmeric, Garlic Purée, Tamarind Extract, Coriander, Black. Seeds, Ground Cumin, Cornflour, Curry Leaves, Ground Garam Masala (Roasted Coriander, Roasted Cumin, Black Pepper, Cinnamon, Mace, Roasted Green Cardamom Seeds, Ginger, Fennel, Cloves, Nutmeg, Bay Leaves), Black Onion Seeds, Ginger, Chilli Powder, Colour: Paprika Extract, Ground Paprika, Chilli Extract, Butter Chicken (33%): Tomatoes (29%), Cooked Chicken Breast (21%), Whipping Cream (. ) (12%), Water, Tomato Paste, Butter (. ) (5%), Rapeseed Oil, Ginger Purée, Ginger, Cornflour, Brown Sugar, Garlic Purée, Full Fat Soft Cheese (. ), Salt, Chicken Stock (Water, Chicken Bones), Smoked Water, Ground Paprika, Green Chillies, Lemon Juice, Green Chilli Purée, Fenugreek Leaves, Ground Coriander, Chilli Powder, Ground Garam Masala (Roasted Coriander, Roasted Cumin, Black Pepper, Cinnamon, Mace, Roasted Green Cardamom Seeds, Ginger, Fennel, Cloves, Nutmeg, Bay Leaves), Whole Black Cardamom Seeds, Gelling Agent: Pectin, Sugar, Turmeric, Roasted Green Cardamom, Cloves, Black Onion Seeds, Roasted Coriander, Roasted Cumin, Chilli Extract","description":"Product Description Basmati Rice with Turmeric and Flavoured with Lemon Juice and Lemon ZestnPotatoes in a Mildly Spiced Tomato and Onion Sauce with Garam MasalanA Mildly Spiced Smoky Tomato, Cream and Butter Curry with Marinated Chicken Breast Topped with Ginger, Green Chillies and Black Onion Seeds Visit us at www.cinnamon-kitchen.com Since Cinnamon Kitchen opened it has established itself as one of the finest modern Indian restaurants in London. Bringing the essence of this fine dining experience into your own home, Cinnamon Kitchen continues to challenge the status quo by fusing the spice of the subcontinent with the finest ingredients and British culinary traditions to create modern dishes that remain classic and timeless. We hope you enjoy! Chilli rating - mild - 1 Pack size: 600G Information Ingredients Turmeric and Lemon Rice (34%): Cooked Basmati Rice (88%) (Water, Basmati Rice), Onions, Lemon Juice (2.5%), Toasted Sesame Oil, Ginger Purée, Salt, Lemon Zest, Curry Leaves, Black Mustard Seeds, Cumin Seeds, Turmeric, Whole Black Cardamom Seeds, Cracked Black Pepper, Crushed Red Chillies, Bombay Aloo (33%): Potatoes (47%), Tomatoes (24%), Onions (15%), Rapeseed Oil, Ginger Purée, Cane Sugar, Tomato Paste, Ground Coriander, Green Chillies, Salt, Turmeric, Garlic Purée, Tamarind Extract, Coriander, Black Mustard Seeds, Ground Cumin, Cornflour, Curry Leaves, Ground Garam Masala (Roasted Coriander, Roasted Cumin, Black Pepper, Cinnamon, Mace, Roasted Green Cardamom Seeds, Ginger, Fennel, Cloves, Nutmeg, Bay Leaves), Black Onion Seeds, Ginger, Chilli Powder, Colour: Paprika Extract, Ground Paprika, Chilli Extract, Butter Chicken (33%): Tomatoes (29%), Cooked Chicken Breast (21%), Whipping Cream ( Milk ) (12%), Water, Tomato Paste, Butter ( Milk ) (5%), Rapeseed Oil, Ginger Purée, Ginger, Cornflour, Brown Sugar, Garlic Purée, Full Fat Soft Cheese ( Milk ), Salt, Chicken Stock (Water, Chicken Bones), Smoked Water, Ground Paprika, Green Chillies, Lemon Juice, Green Chilli Purée, Fenugreek Leaves, Ground Coriander, Chilli Powder, Ground Garam Masala (Roasted Coriander, Roasted Cumin, Black Pepper, Cinnamon, Mace, Roasted Green Cardamom Seeds, Ginger, Fennel, Cloves, Nutmeg, Bay Leaves), Whole Black Cardamom Seeds, Gelling Agent: Pectin, Sugar, Turmeric, Roasted Green Cardamom, Cloves, Black Onion Seeds, Roasted Coriander, Roasted Cumin, Chilli Extract Allergy Information For allergens see ingredients in bold. Storage For use by date see front of pack. Keep refrigerated 0°C to 5°C. Not suitable for freezing. Cooking Instructions Microwave Instructions: Pierce film on all containers. Cat D 750W 7 mins Cat E 900W 6 mins 30 secs Cat E 1000W 6 mins Cooking Instructions Instructions: Remove all items from the carton. For best results microwave all components together Stir thoroughly after cooking. Do not reheat once cooled. Oven cook Instructions: 180 °C / Fan 160°C / Gas 4 25 mins Preheat oven and baking tray. Pierce film. Place all containers on a baking tray. Produce of Made in the UK with assured chicken from farms in the UK and rice, vegetables and other ingredients from multiple countries Number of uses 1 Servings Warnings WARNING: May contain whole spices and herbs. May contain bones. Recycling info Carton. RecyclenFilm. Don't RecyclenTray. Recycle Name and address Cinnamon Kitchen, 2nd Floor Colmore Court, 9 Colmore Row, Birmingham, B3 2BJ. Return to Cinnamon Kitchen, 2nd Floor Colmore Court, 9 Colmore Row, Birmingham, B3 2BJ. www.cinnamon-kitchen.com Net Contents 600g ℮ Nutrition Typical Values Per 100g Per pack (600g) Reference Intake (Adult) Energy kJ 547kJ 3282kJ 8400kJ/ Energy kcal 131kcal 786kcal 2000kcal Fat 5.6g 33.6g 70g -of which saturates 1.8g 10.8g 20g Carbohydrate 14.6g 87.6g of which sugars 2.6g 15.6g 90g Fibre 1.3g 7.8g Protein 4.8g 28.8g Salt 0.55g 3.30g 6g Serves 1 - - - Safety information View more safety information WARNING: May contain whole spices and herbs. May contain bones.","cooking_instructions":"Microwave. Instructions: Pierce film on all containers.. Cat D 750W 7 mins. Cat E 900W 6 mins 30 secs. Cat E 1000W 6 mins. Cooking Instructions. Instructions: Remove all items from the carton.. For best results microwave all components together. Stir thoroughly after cooking. Do not reheat once cooled.. Oven cook. Instructions: 180 °C / Fan 160°C / Gas 4 25 mins. Preheat oven and baking tray.. Pierce film. Place all containers on a baking tray.","storage":"For use by date see front of pack. Keep refrigerated 0°C to 5°C. Not suitable for freezing.","allergy_info":"For. allergens. see ingredients in bold.","produce_of":"Made in the UK with assured chicken from farms in the UK and rice, vegetables and other ingredients from multiple countries","number_of_uses":"1 Servings","recycling_info":"Carton. RecyclenFilm. Don't RecyclenTray. Recycle","return_to":"Cinnamon Kitchen,. 2nd Floor Colmore Court,. 9 Colmore Row,. Birmingham,. B3 2BJ.. www.cinnamon-kitchen.com","net_content":"600g ℮","nutrition_per_unit":[{"Typical Values":"Energy kcal","Per 100g":"131kcal","Per pack (600g)":"786kcal","Reference Intake (Adult)":"2000kcal"},{"Typical Values":"Fat","Per 100g":"5.6g","Per pack (600g)":"33.6g","Reference Intake (Adult)":"70g"},{"Typical Values":"-of which saturates","Per 100g":"1.8g","Per pack (600g)":"10.8g","Reference Intake (Adult)":"20g"},{"Typical Values":"Carbohydrate","Per 100g":"14.6g","Per pack (600g)":"87.6g","Reference Intake (Adult)":""},{"Typical Values":"of which sugars","Per 100g":"2.6g","Per pack (600g)":"15.6g","Reference Intake (Adult)":"90g"},{"Typical Values":"Fibre","Per 100g":"1.3g","Per pack (600g)":"7.8g","Reference Intake (Adult)":""},{"Typical Values":"Protein","Per 100g":"4.8g","Per pack (600g)":"28.8g","Reference Intake (Adult)":""},{"Typical Values":"Salt","Per 100g":"0.55g","Per pack (600g)":"3.30g","Reference Intake (Adult)":"6g"},{"Typical Values":"Serves 1","Per 100g":"-","Per pack (600g)":"-","Reference Intake (Adult)":"-"}],"gtin13":"05030705000130","sku":"312984325","timestamp":"2023-01-31T12:08:59Z"},{"title":"Tesco British Turkey Breast Quickcook Steaks 380G","unit_price":"4.50","currency":"£","price_per_quantity":"11.84","quantity":"1","url":"https://www.tesco.com/groceries/en-GB/products/293819816","image":"https://digitalcontent.api.tesco.com/v2/media/ghs/e94ad3c2-1d4c-43ca-9a62-d6a0ad609f47/824f60b6-3f22-446e-9b37-533f9d75d80f.jpeg?h=540&w=540","rating":"3.4","category":"Fresh Food / Fresh Meat & Poultry / Fresh Turkey","number_of_reviews":"16","short_desc":"","nutrition":[{"Energy":"486kJ, 115kcal","nutr_percent":"6%"},{"Fat":"2.0g","nutr_percent":"3%"},{"Saturates":"0.6g","nutr_percent":"3%"},{"Sugars":"<0.1","nutr_percent":"<1%"},{"Salt":"0.2g","nutr_percent":"3%"}],"ingredients":"Turkey Breast (100%).","description":"One typical turkey breast steak Energy 486kJ 115kcal 6% of the reference intake Fat 2.0g low 3% of the reference intake Saturates 0.6g low 3% of the reference intake Sugars <0.1 low <1% of the reference intake Salt 0.2g low 3% of the reference intake of the reference intake * Typical values per 100g: Energy 578kJ / 137kcal Product Description Fresh Class A skinless, boneless turkey breast steaks. From trusted British farms. Our British turkeys are reared by selected farmers and are free to roam in spacious barns with natural daylight to ensure their wellbeing. Hand selected by butchers and thinly sliced for a quick cook Pack size: 380G Information Ingredients INGREDIENTS: Turkey Breast (100%). Storage Suitable for home freezing. Ideally freeze as soon as possible after purchase but always by 'use by' date shown. nNot suitable for cooking from frozen. nFollow the preparation guidelines above. nOnce defrosted use on the same day and do not refreeze. nDefrost thoroughly for a minimum of 24 hours in the fridge.nnKeep refrigerated. Once opened, use immediately. nKeep refrigerated below 4°C. Cooking Instructions Microwave Instructions: Not suitable for microwave cooking. Grill Instructions: Place under a pre-heated grill for 6-8 minutes. Turn occasionally. Produce of Produced in the U.K., Origin UK Preparation and Usage To avoid cross contamination do not wash raw poultry and use separate chopping boards and utensils for raw poultry and ready to eat foods. Was hands after touching raw poultry. Number of uses approx. 4 Servings Warnings Caution: Although every care has been taken to remove bones, some may remain. Recycling info Tray. Plastic check local recyclingnFilm. Plastic not currently recycled Return to Tesco Stores Ltd., Welwyn Garden City AL7 1GA, U.K Net Contents 380g ℮ Nutrition Typical Values Per 100g / Per 100ml A serving contains Energy 578kJ / 137kcal 486kJ / 115kcal Fat 2.3g 2.0g Saturates 0.8g 0.6g Carbohydrate 0.7g 0.6g Sugars 0.1g <0.1g Fibre 0g 0g Protein 28.3g 23.7g Salt 0.2g 0.2g * Reference intake of an average adult (8400 kJ / 2000 kcal) - - ** When cooked according to instructions 380g typically weighs 336g. - - Safety information View more safety information Caution: Although every care has been taken to remove bones, some may remain.","cooking_instructions":"Microwave. Instructions: Not suitable for microwave cooking.. Grill. Instructions: Place under a pre-heated grill for 6-8 minutes. Turn occasionally.","storage":"Suitable for home freezing. Ideally freeze as soon as possible after purchase but always by 'use by' date shown. nNot suitable for cooking from frozen. nFollow the preparation guidelines above. nOnce defrosted use on the same day and do not refreeze. nDefrost thoroughly for a minimum of 24 hours in the fridge.nnKeep refrigerated. Once opened, use immediately. nKeep refrigerated below 4°C.","allergy_info":"","produce_of":"Produced in the U.K., Origin UK","number_of_uses":"approx. 4 Servings","recycling_info":"Tray. Plastic check local recyclingnFilm. Plastic not currently recycled","return_to":"Tesco Stores Ltd.,. Welwyn Garden City AL7 1GA,. U.K","net_content":"380g ℮","nutrition_per_unit":[{"Typical Values":"Fat","Per 100g / Per 100ml":"2.3g","A serving contains":"2.0g"},{"Typical Values":"Saturates","Per 100g / Per 100ml":"0.8g","A serving contains":"0.6g"},{"Typical Values":"Carbohydrate","Per 100g / Per 100ml":"0.7g","A serving contains":"0.6g"},{"Typical Values":"Sugars","Per 100g / Per 100ml":"0.1g","A serving contains":"<0.1g"},{"Typical Values":"Fibre","Per 100g / Per 100ml":"0g","A serving contains":"0g"},{"Typical Values":"Protein","Per 100g / Per 100ml":"28.3g","A serving contains":"23.7g"},{"Typical Values":"Salt","Per 100g / Per 100ml":"0.2g","A serving contains":"0.2g"},{"Typical Values":"* Reference intake of an average adult (8400 kJ / 2000 kcal)","Per 100g / Per 100ml":"-","A serving contains":"-"},{"Typical Values":"** When cooked according to instructions 380g typically weighs 336g.","Per 100g / Per 100ml":"-","A serving contains":"-"}],"gtin13":"05057008455672","sku":"293819816","timestamp":"2023-01-31T12:09:03Z"},{"title":"Tesco Calorie Controlled Tomato & Basil Chicken 380G","unit_price":"3.00","currency":"£","price_per_quantity":"7.90","quantity":"1","url":"https://www.tesco.com/groceries/en-GB/products/312224932","image":"https://digitalcontent.api.tesco.com/v2/media/ghs/da28ff64-b7eb-40b3-aead-7111955a025a/93fd2f50-ed85-46ac-943b-55ec8f3222b2.jpeg?h=540&w=540","rating":"3.2","category":"Fresh Food / Ready Meals / Healthier & Low Calorie Ready Meals","number_of_reviews":"4","short_desc":"Any 2 for £5 Clubcard Price - Selected Tesco Ready Meals 360g - 450g Offer valid for delivery from 25/01/2023 until 21/02/2023","nutrition":[{"Energy":"1204kJ, 286kcal","nutr_percent":"14%"},{"Fat":"6.2g","nutr_percent":"9%"},{"Saturates":"0.8g","nutr_percent":"4%"},{"Sugars":"10.8g","nutr_percent":"12%"},{"Salt":"0.79g","nutr_percent":"13%"}],"ingredients":"Potato, Cooked Chicken (21%) [Chicken Breast, Corn Starch], Green Bean, Tomato, Water, Onion, Tomato Juice, Semi Dried Cherry Tomatoes [Tomato, Rapeseed Oil, Salt, Garlic, Oregano], Tomato Purée, Cornflour, Rapeseed Oil, Sugar, Garlic Purée, Sundried Tomatoes, Chicken Extract, Basil, Sunflower Oil, Salt, Gelling Agent (Amidated Pectin), Vegetable Juice Concentrates [Carrot, Mushroom, Onion], Black Pepper, Garlic Powder, Oregano Powder.","description":"Each pack Energy 1204kJ 286kcal 14% of the reference intake Fat 6.2g low 9% of the reference intake Saturates 0.8g low 4% of the reference intake Sugars 10.8g low 12% of the reference intake Salt 0.79g low 13% of the reference intake of the reference intake * Typical values per 100g: Energy 341kJ / 81kcal Product Description Cooked chicken in a tomato and basil sauce with baby potatoes, green beans and semi dried cherry tomatoes. CALORIE CONTROLLED LOW FAT RECIPE 286kcal 1204kJ / 286kcal per serving Pack size: 380G Information Ingredients INGREDIENTS: Potato, Cooked Chicken (21%) [Chicken Breast, Corn Starch], Green Bean, Tomato, Water, Onion, Tomato Juice, Semi Dried Cherry Tomatoes [Tomato, Rapeseed Oil, Salt, Garlic, Oregano], Tomato Purée, Cornflour, Rapeseed Oil, Sugar, Garlic Purée, Sundried Tomatoes, Chicken Extract, Basil, Sunflower Oil, Salt, Gelling Agent (Amidated Pectin), Vegetable Juice Concentrates [Carrot, Mushroom, Onion], Black Pepper, Garlic Powder, Oregano Powder. Storage Suitable for home freezing. Ideally freeze as soon as possible after purchase but always by 'use by' date shown. nOnce defrosted use within 24 hours and do not refreeze. nNot suitable for cooking from frozen. nFollow the preparation guidelines above. nDefrost thoroughly for a minimum of 12 hours in the fridge.nnKeep refrigerated. Cooking Instructions Oven Instructions: 190°C/ Fan 170°C/ Gas 5 20-25 minutes Place on a baking tray in the centre of a pre-heated oven. Leave to stand for 1 minute after heating. Stir before serving. Oven from frozen Instructions: Not suitable for heating from frozen. Microwave Instructions: For best results microwave heat. 800W 4 minutes 30 seconds / 900W 4 minutes Heat on full power for 2 mins (800W)/(900W) Peel back film lid and stir, re-cover and heat for a further 2 minutes 30 seconds (800W) / 2 min (900W) Leave to stand for 1 minute after heating. Stir before serving. Produce of Made using Thai chicken. Preparation and Usage Allow tray to stand until it regains its rigidity. Number of uses 1 Servings Warnings Caution: Although every care has been taken to remove bones, some may remain. Recycling info Sleeve. RecyclenTray. RecyclenFilm. Recycle at large supermarket Return to Tesco Stores Ltd., Welwyn Garden City AL7 1GA, U.K Drained weight - Net Contents 380g e Nutrition Typical Values Per 100g Each pack (353g**) Energy 341kJ / 81kcal 1204kJ / 286kcal Fat 1.8g 6.2g Saturates 0.2g 0.8g Carbohydrate 7.8g 27.6g Sugars 3.1g 10.8g Fibre 1.6g 5.7g Protein 7.6g 27.0g Salt 0.23g 0.79g * Reference intake of an average adult (8400 kJ / 2000 kcal) - - When microwaved according to instructions. - - ** When microwaved according to instructions 380g typically weighs 353g. - - Safety information View more safety information Caution: Although every care has been taken to remove bones, some may remain.","cooking_instructions":"Oven. Instructions: 190°C/ Fan 170°C/ Gas 5 20-25 minutes Place on a baking tray in the centre of a pre-heated oven. Leave to stand for 1 minute after heating. Stir before serving.. Oven from frozen. Instructions: Not suitable for heating from frozen.. Microwave. Instructions: For best results microwave heat.. 800W 4 minutes 30 seconds / 900W 4 minutes. Heat on full power for 2 mins (800W)/(900W). Peel back film lid and stir, re-cover and heat for a further 2 minutes 30 seconds (800W) / 2 min (900W). Leave to stand for 1 minute after heating.. Stir before serving.","storage":"Suitable for home freezing. Ideally freeze as soon as possible after purchase but always by 'use by' date shown. nOnce defrosted use within 24 hours and do not refreeze. nNot suitable for cooking from frozen. nFollow the preparation guidelines above. nDefrost thoroughly for a minimum of 12 hours in the fridge.nnKeep refrigerated.","allergy_info":"","produce_of":"Made using Thai chicken.","number_of_uses":"1 Servings","recycling_info":"Sleeve. RecyclenTray. RecyclenFilm. Recycle at large supermarket","return_to":"Tesco Stores Ltd.,. Welwyn Garden City AL7 1GA,. U.K","net_content":"380g e","nutrition_per_unit":[{"Typical Values":"Fat","Per 100g":"1.8g","Each pack (353g**)":"6.2g"},{"Typical Values":"Saturates","Per 100g":"0.2g","Each pack (353g**)":"0.8g"},{"Typical Values":"Carbohydrate","Per 100g":"7.8g","Each pack (353g**)":"27.6g"},{"Typical Values":"Sugars","Per 100g":"3.1g","Each pack (353g**)":"10.8g"},{"Typical Values":"Fibre","Per 100g":"1.6g","Each pack (353g**)":"5.7g"},{"Typical Values":"Protein","Per 100g":"7.6g","Each pack (353g**)":"27.0g"},{"Typical Values":"Salt","Per 100g":"0.23g","Each pack (353g**)":"0.79g"},{"Typical Values":"* Reference intake of an average adult (8400 kJ / 2000 kcal)","Per 100g":"-","Each pack (353g**)":"-"},{"Typical Values":"When microwaved according to instructions.","Per 100g":"-","Each pack (353g**)":"-"},{"Typical Values":"** When microwaved according to instructions 380g typically weighs 353g.","Per 100g":"-","Each pack (353g**)":"-"}],"gtin13":"05059697711176","sku":"312224932","timestamp":"2023-01-31T12:09:07Z"},{"title":"Tesco Finest Ham Hock & Piccalilli Pate 125G","unit_price":"4.00","currency":"£","price_per_quantity":"3.20","quantity":"1","url":"https://www.tesco.com/groceries/en-GB/products/309196185","image":"https://digitalcontent.api.tesco.com/v2/media/ghs/a8e3ff90-49d3-4936-8d93-2bd7b531cfd4/2455aafb-ca23-4dcf-b7a7-f08d64159f4d_1338806298.jpeg?h=540&w=540","rating":"5","category":"Fresh Food / Cooked Meats, Antipasti & Dips / Pate","number_of_reviews":"1","short_desc":"","nutrition":[{"Energy":"362kJ, 87kcal","nutr_percent":"4%"},{"Fat":"6.3g","nutr_percent":"9%"},{"Saturates":"2.2g","nutr_percent":"11%"},{"Sugars":"1.3g","nutr_percent":"1%"},{"Salt":"0.69g","nutr_percent":"12%"}],"ingredients":"Pork Liver (24%), Water, Pork Fat, Wiltshire Cured Ham (11%) [Pork, Salt, Preservatives (Sodium Nitrite, Potassium Nitrate)], Shallot, Tapioca Starch, Parsley, Sugar, White Wine Vinegar, Salt, Pork Gelatine, Gherkin, Onion, Maize Starch, Light Brown Soft Sugar, Tarragon, Spirit Vinegar, Gelling Agents (Agar, Locust Bean Gum), Mace, Antioxidant (Ascorbic Acid),. Flour, White Pepper, Rapeseed Oil, Garlic Purée, Sunflower Oil, Nutmeg, Sea Salt, Turmeric, Cider Vinegar, Ginger Powder, Brown. Seed, Coriander, Dextrose, Preservative (Sodium Nitrite), Concentrated Lemon Juice, Black Pepper.","description":"1/3 of a jar Energy 362kJ 87kcal 4% of the reference intake Fat 6.3g medium 9% of the reference intake Saturates 2.2g high 11% of the reference intake Sugars 1.3g low 1% of the reference intake Salt 0.69g high 12% of the reference intake of the reference intake * Typical values per 100g: Energy 861kJ / 207kcal Product Description A coarse pork liver, pork fat and Wiltshire cured ham pâté with a piccalilli jelly. Pack size: 125G Information Ingredients INGREDIENTS: Pork Liver (24%), Water, Pork Fat, Wiltshire Cured Ham (11%) [Pork, Salt, Preservatives (Sodium Nitrite, Potassium Nitrate)], Shallot, Tapioca Starch, Parsley, Sugar, White Wine Vinegar, Salt, Pork Gelatine, Gherkin, Onion, Maize Starch, Light Brown Soft Sugar, Tarragon, Spirit Vinegar, Gelling Agents (Agar, Locust Bean Gum), Mace, Antioxidant (Ascorbic Acid), Mustard Flour, White Pepper, Rapeseed Oil, Garlic Purée, Sunflower Oil, Nutmeg, Sea Salt, Turmeric, Cider Vinegar, Ginger Powder, Brown Mustard Seed, Coriander, Dextrose, Preservative (Sodium Nitrite), Concentrated Lemon Juice, Black Pepper. Allergy Information For allergens, see ingredients in bold. Storage Not suitable for freezing. Keep refrigerated. Once opened, consume within 2 days and by 'use by' date shown. Produce of Made using British pork. Number of uses 3 Servings Recycling info Jar. Recycle Return to Tesco Stores Ltd., Welwyn Garden City AL7 1GA, U.K Net Contents 125g e Nutrition Typical Values Per 100g 1/3 of a jar (42g) Energy 861kJ / 207kcal 362kJ / 87kcal Fat 15.1g 6.3g Saturates 5.2g 2.2g Carbohydrate 6.5g 2.7g Sugars 3.0g 1.3g Fibre 1.0g 0.4g Protein 10.8g 4.5g Salt 1.63g 0.69g * Reference intake of an average adult (8400 kJ / 2000 kcal) - - As sold - -","cooking_instructions":"","storage":"Not suitable for freezing. Keep refrigerated. Once opened, consume within 2 days and by 'use by' date shown.","allergy_info":"For allergens, see ingredients in bold.","produce_of":"Made using British pork.","number_of_uses":"3 Servings","recycling_info":"Jar. Recycle","return_to":"Tesco Stores Ltd.,. Welwyn Garden City AL7 1GA,. U.K","net_content":"125g e","nutrition_per_unit":[{"Typical Values":"Fat","Per 100g":"15.1g","1/3 of a jar (42g)":"6.3g"},{"Typical Values":"Saturates","Per 100g":"5.2g","1/3 of a jar (42g)":"2.2g"},{"Typical Values":"Carbohydrate","Per 100g":"6.5g","1/3 of a jar (42g)":"2.7g"},{"Typical Values":"Sugars","Per 100g":"3.0g","1/3 of a jar (42g)":"1.3g"},{"Typical Values":"Fibre","Per 100g":"1.0g","1/3 of a jar (42g)":"0.4g"},{"Typical Values":"Protein","Per 100g":"10.8g","1/3 of a jar (42g)":"4.5g"},{"Typical Values":"Salt","Per 100g":"1.63g","1/3 of a jar (42g)":"0.69g"},{"Typical Values":"* Reference intake of an average adult (8400 kJ / 2000 kcal)","Per 100g":"-","1/3 of a jar (42g)":"-"},{"Typical Values":"As sold","Per 100g":"-","1/3 of a jar (42g)":"-"}],"gtin13":"05059697391897","sku":"309196185","timestamp":"2023-01-31T12:09:11Z"},{"title":"Tesco Finest Duck & Truffle Pate 125G","unit_price":"4.00","currency":"£","price_per_quantity":"3.20","quantity":"1","url":"https://www.tesco.com/groceries/en-GB/products/309449273","image":"https://digitalcontent.api.tesco.com/v2/media/ghs/efb3ed02-e00e-4200-9344-a6752febae71/4b088803-04a7-4baf-a098-2fb3f8c308cc_1053891160.jpeg?h=540&w=540","rating":"1.5","category":"Fresh Food / Cooked Meats, Antipasti & Dips / Pate","number_of_reviews":"2","short_desc":"","nutrition":[{"Energy":"441kJ, 106kcal","nutr_percent":"5%"},{"Fat":"9.2g","nutr_percent":"13%"},{"Saturates":"4.4g","nutr_percent":"22%"},{"Sugars":"0.8g","nutr_percent":"1%"},{"Salt":"0.54g","nutr_percent":"9%"}],"ingredients":"Duck Liver (36%), Madeira Jelly (20%) [Water, Madeira Wine, Pork Gelatine, Sugar, Tapioca Starch, Gelling Agents (Agar, Locust Bean Gum), Olive Oil, Colour (Plain Caramel), Salt, Dextrose, Flavouring, Preservative (Potassium. )], Butter (. ), Pork Fat, Single Cream (. ), Tapioca Starch, Water, Olive Oil, Armagnac, Port, Salt, Double Cream (. ), Mushroom, Sugar, Antioxidant (Ascorbic Acid), Extra Virgin Olive Oil, Flavouring, White Pepper, Truffle, Black Olive, Carrot, Preservatives (Sodium Nitrite,. ), Parsley, Black Pepper, Chilli Pepper.","description":"1/3 of a jar Energy 441kJ 106kcal 5% of the reference intake Fat 9.2g high 13% of the reference intake Saturates 4.4g high 22% of the reference intake Sugars 0.8g low 1% of the reference intake Salt 0.54g medium 9% of the reference intake of the reference intake * Typical values per 100g: Energy 1049kJ / 253kcal Product Description A smooth duck liver and pork fat pâté with a madeira jelly. Pack size: 125G Information Ingredients INGREDIENTS: Duck Liver (36%), Madeira Jelly (20%) [Water, Madeira Wine, Pork Gelatine, Sugar, Tapioca Starch, Gelling Agents (Agar, Locust Bean Gum), Olive Oil, Colour (Plain Caramel), Salt, Dextrose, Flavouring, Preservative (Potassium Metabisulphite )], Butter ( Milk ), Pork Fat, Single Cream ( Milk ), Tapioca Starch, Water, Olive Oil, Armagnac, Port, Salt, Double Cream ( Milk ), Mushroom, Sugar, Antioxidant (Ascorbic Acid), Extra Virgin Olive Oil, Flavouring, White Pepper, Truffle, Black Olive, Carrot, Preservatives (Sodium Nitrite, Sulphur Dioxide ), Parsley, Black Pepper, Chilli Pepper. Allergy Information For allergens, see ingredients in bold. Storage Keep refrigerated. Once opened, consume within 2 days and by 'use by' date shown. Not suitable for freezing. Produce of Made using British duck and pork. Number of uses 3 Servings Recycling info Jar. Recycle Return to Tesco Stores Ltd., Welwyn Garden City AL7 1GA, U.K Net Contents 125g e Nutrition Typical Values Per 100g 1/3 of a jar (42g) Energy 1049kJ / 253kcal 441kJ / 106kcal Fat 22.0g 9.2g Saturates 10.5g 4.4g Carbohydrate 3.8g 1.6g Sugars 1.9g 0.8g Fibre 1.0g 0.4g Protein 9.5g 4.0g Salt 1.28g 0.54g * Reference intake of an average adult (8400 kJ / 2000 kcal) - - As sold - -","cooking_instructions":"","storage":"Keep refrigerated. Once opened, consume within 2 days and by 'use by' date shown. Not suitable for freezing.","allergy_info":"For allergens, see ingredients in bold.","produce_of":"Made using British duck and pork.","number_of_uses":"3 Servings","recycling_info":"Jar. Recycle","return_to":"Tesco Stores Ltd.,. Welwyn Garden City AL7 1GA,. U.K","net_content":"125g e","nutrition_per_unit":[{"Typical Values":"Fat","Per 100g":"22.0g","1/3 of a jar (42g)":"9.2g"},{"Typical Values":"Saturates","Per 100g":"10.5g","1/3 of a jar (42g)":"4.4g"},{"Typical Values":"Carbohydrate","Per 100g":"3.8g","1/3 of a jar (42g)":"1.6g"},{"Typical Values":"Sugars","Per 100g":"1.9g","1/3 of a jar (42g)":"0.8g"},{"Typical Values":"Fibre","Per 100g":"1.0g","1/3 of a jar (42g)":"0.4g"},{"Typical Values":"Protein","Per 100g":"9.5g","1/3 of a jar (42g)":"4.0g"},{"Typical Values":"Salt","Per 100g":"1.28g","1/3 of a jar (42g)":"0.54g"},{"Typical Values":"* Reference intake of an average adult (8400 kJ / 2000 kcal)","Per 100g":"-","1/3 of a jar (42g)":"-"},{"Typical Values":"As sold","Per 100g":"-","1/3 of a jar (42g)":"-"}],"gtin13":"05057753907174","sku":"309449273","timestamp":"2023-01-31T12:09:14Z"},{"title":"The Gym Kitchen Korean Beef Chilli 400G","unit_price":"3.75","currency":"£","price_per_quantity":"NaN","quantity":"1","url":"https://www.tesco.com/groceries/en-GB/products/313627431","image":"https://digitalcontent.api.tesco.com/v2/media/ghs/84e6ac7a-d9b3-4ad9-aafd-65c92d3c442b/1f2849ea-9021-409a-8286-9da24cd72b36.jpeg?h=540&w=540","rating":"No ratings yet","category":"Fresh Food / Ready Meals / Healthier & Low Calorie Ready Meals","number_of_reviews":"","short_desc":"","nutrition":[{"Energy":"1694kJ, 403kcal","nutr_percent":"21%"},{"Fat":"11.4g","nutr_percent":"17%"},{"Saturates":"3.7g","nutr_percent":"19%"},{"Sugars":"6.3g","nutr_percent":"7%"},{"Salt":"1.5g","nutr_percent":"25%"}],"ingredients":"Cooked Brown Rice (26%) [Water, Brown Rice], Beef (22%), Broccoli (13%), Water, Sweetcorn (7%), Red Peppers, Green Lentils (4%), Onions, Gochujang Paste [Glucose Syrup, Water, Fructose, Black. Beans, Concentrated Red Pepper Juice, Sugar, Rapeseed Oil, Onion Powder, Salt, Onion Juice Concentrate, Tomato Powder, White Wine Vinegar, Cayenne Powder, Maltodextrin, Acidity Regulator (Acetic Acid), Colour (Paprika Extract),. Beans, Rice Flour, Spirit Vinegar], Yellow Split Peas, Ginger Purée, Garlic Purée, Cornflour, Tomato Paste, Rapeseed Oil, Salt, Chilli Powder","description":"Per (microwaved) pack Energy 1694kJ 403kcal 21% of the reference intake Fat 11.4g low 17% of the reference intake Saturates 3.7g low 19% of the reference intake Sugars 6.3g low 7% of the reference intake Salt 1.5g medium 25% of the reference intake of the reference intake * Typical values per 100g: Energy (microwaved) Per pack Product Description Mildly spiced beef chilli with brown rice, broccoli, sweetcorn and green lentils. Macro Counted Macro is short for macronutrients, a term used to describe the three key food groups we all require for our bodies to function: carbohydrates (to fuel energy), fats (to keep you satiated) and proteins (to build and repair muscle). Here at The Gym Kitchen we don't think food should be boring or tasteless. So we've created a range of meals that contain no funny business, are macro-counted and most importantly taste awesome. We've banned bland to make your plate great, hope you enjoy! Food to Fuel High in Protein - 32g Protein 403 Kcal Per Pack 2 of Your 5 a Day Source of Fibre Chilli rating - Mild - 1 43g Carbs Per Pack Low in Fat - 11.4g Fat Pack size: 400G High in Protein Source of Fibre Low in Fat Information Ingredients Cooked Brown Rice (26%) [Water, Brown Rice], Beef (22%), Broccoli (13%), Water, Sweetcorn (7%), Red Peppers, Green Lentils (4%), Onions, Gochujang Paste [Glucose Syrup, Water, Fructose, Black Soya Beans, Concentrated Red Pepper Juice, Sugar, Rapeseed Oil, Onion Powder, Salt, Onion Juice Concentrate, Tomato Powder, White Wine Vinegar, Cayenne Powder, Maltodextrin, Acidity Regulator (Acetic Acid), Colour (Paprika Extract), Soya Beans, Rice Flour, Spirit Vinegar], Yellow Split Peas, Ginger Purée, Garlic Purée, Cornflour, Tomato Paste, Rapeseed Oil, Salt, Chilli Powder Allergy Information For allergens, see ingredients in bold. Storage For use by date: see top of pack.Keep refrigerated, once opened use immediately. Do not exceed the use by date. For best quality we suggest you do not freeze. Cooking Instructions Microwave Instructions: Remove sleeve and pierce film lid. Microwave on full power for 2 1/2 minutes (800W), or 2 minutes (900W). Stir thoroughly, re-cover and continue microwaving on full power for 2 minutes (800W or 900W). Stir thoroughly. Check food is piping hot. Allow to stand for 1 minute. Do not reheat once cooled. All cooking appliances vary. This is a guide only. Caution Take care when removing film lid as hot steam will escape. Number of uses This pack provides 1 serving Recycling info Film. Don't RecyclenLid. Don't RecyclenSleeve. Recycle Name and address TGK Brand Ltd, PO Box 564, Grays, RM17 9PY. Return to TGK Brand Ltd, PO Box 564, Grays, RM17 9PY. Connect with us www.thegymkitchen.com Net Contents 400g ℮ Nutrition Typical Values (microwaved) Per pack (microwaved) Per 100g RI (%)* Energy kJ 1694 442 Energy kcal 403 105 21% Fat, total 11.4g 3g 17% - saturates 3.7g 1g 19% Carbohydrate 42.8g 11.2g 17% - sugars 6.3g 1.6g 7% Fibre 10.4g 2.0g Protein 32g 7.8g 60% Salt 1.5g 0.40g 25% *Reference intake of an average adult (8400 kJ / 2000 kcal) - - - This pack provides 1 serving - - -","cooking_instructions":"Microwave. Instructions: Remove sleeve and pierce film lid. Microwave on full power for 2 1/2 minutes (800W), or 2 minutes (900W). Stir thoroughly, re-cover and continue microwaving on full power for 2 minutes (800W or 900W). Stir thoroughly. Check food is piping hot. Allow to stand for 1 minute. Do not reheat once cooled. All cooking appliances vary.. This is a guide only.. Caution. Take care when removing film lid as hot steam will escape.","storage":"For use by date: see top of pack.Keep refrigerated, once opened use immediately. Do not exceed the use by date. For best quality we suggest you do not freeze.","allergy_info":"For allergens, see ingredients in bold.","produce_of":"","number_of_uses":"This pack provides 1 serving","recycling_info":"Film. Don't RecyclenLid. Don't RecyclenSleeve. Recycle","return_to":"TGK Brand Ltd,. PO Box 564,. Grays,. RM17 9PY.. Connect with us. www.thegymkitchen.com","net_content":"400g ℮","nutrition_per_unit":[{"Typical Values":"Energy kcal","(microwaved) Per pack":"403","(microwaved) Per 100g":"105","RI (%)*":"21%"},{"Typical Values":"Fat, total","(microwaved) Per pack":"11.4g","(microwaved) Per 100g":"3g","RI (%)*":"17%"},{"Typical Values":"- saturates","(microwaved) Per pack":"3.7g","(microwaved) Per 100g":"1g","RI (%)*":"19%"},{"Typical Values":"Carbohydrate","(microwaved) Per pack":"42.8g","(microwaved) Per 100g":"11.2g","RI (%)*":"17%"},{"Typical Values":"- sugars","(microwaved) Per pack":"6.3g","(microwaved) Per 100g":"1.6g","RI (%)*":"7%"},{"Typical Values":"Fibre","(microwaved) Per pack":"10.4g","(microwaved) Per 100g":"2.0g","RI (%)*":""},{"Typical Values":"Protein","(microwaved) Per pack":"32g","(microwaved) Per 100g":"7.8g","RI (%)*":"60%"},{"Typical Values":"Salt","(microwaved) Per pack":"1.5g","(microwaved) Per 100g":"0.40g","RI (%)*":"25%"},{"Typical Values":"*Reference intake of an average adult (8400 kJ / 2000 kcal)","(microwaved) Per pack":"-","(microwaved) Per 100g":"-","RI (%)*":"-"},{"Typical Values":"This pack provides 1 serving","(microwaved) Per pack":"-","(microwaved) Per 100g":"-","RI (%)*":"-"}],"gtin13":"05060084345553","sku":"313627431","timestamp":"2023-01-31T12:09:19Z"},{"title":"Tesco Sweet & Sour Crispy Chicken Balls 310G","unit_price":"3.75","currency":"£","price_per_quantity":"NaN","quantity":"1","url":"https://www.tesco.com/groceries/en-GB/products/313177093","image":"https://digitalcontent.api.tesco.com/v2/media/ghs/8f2ca546-e815-42a8-9c76-5c763c0a9814/9ca626fa-0ead-40df-9be7-2ec71563dbe3.jpeg?h=540&w=540","rating":"No ratings yet","category":"Fresh Food / Ready Meals / Chinese, Thai & Asian Ready Meals","number_of_reviews":"","short_desc":"","nutrition":[{"Energy":"1104kJ, 262kcal","nutr_percent":"13%"},{"Fat":"8.0g","nutr_percent":"11%"},{"Saturates":"3.1g","nutr_percent":"16%"},{"Sugars":"7.0g","nutr_percent":"8%"},{"Salt":"1.03g","nutr_percent":"17%"}],"ingredients":"Cooked Battered Chicken (77%) [Chicken Breast,. Flour, Water, Palm Oil, Cornflour, Tapioca Starch,. Starch, Salt, Dextrose, Raising Agents (Disodium Diphosphate, Sodium Bicarbonate), Sugar, Corn Starch, Yeast], Water, Sugar, White Wine Vinegar, Concentrated Pineapple Juice, Cornflour, Tomato Paste, Ginger Purée, Colour (Paprika Extract), Salt,. Bean,. , Cinnamon, Alcohol.","description":"1/2 of a pack Energy 1104kJ 262kcal 13% of the reference intake Fat 8.0g medium 11% of the reference intake Saturates 3.1g medium 16% of the reference intake Sugars 7.0g low 8% of the reference intake Salt 1.03g medium 17% of the reference intake of the reference intake * Typical values per 100g: Energy 794kJ / 189kcal Product Description Cooked battered chicken breast pieces with a sweet and sour sauce pot. Working closely with our specialist chefs we use unique Chinese flavour combinations to create vibrant and aromatic dishes. A Taste of China Crispy battered chicken balls with a sweet & sour sauce Pack size: 310G Information Ingredients INGREDIENTS: Cooked Battered Chicken (77%) [Chicken Breast, Wheat Flour, Water, Palm Oil, Cornflour, Tapioca Starch, Wheat Starch, Salt, Dextrose, Raising Agents (Disodium Diphosphate, Sodium Bicarbonate), Sugar, Corn Starch, Yeast], Water, Sugar, White Wine Vinegar, Concentrated Pineapple Juice, Cornflour, Tomato Paste, Ginger Purée, Colour (Paprika Extract), Salt, Soya Bean, Wheat , Cinnamon, Alcohol. Allergy Information May contain sesame seeds.For allergens, including cereals containing gluten, see ingredients in bold. Storage Suitable for home freezing. Ideally freeze as soon as possible after purchase but always by 'use by' date shown. nKeep refrigerated. Cooking Instructions Oven Instructions: Remove outer sleeve and film lid. Remove pot and place to one side. Sauce pot is not suitable for oven heating. 190°C/Fan 170°C/Gas 5 25 mins Place foil tray on a baking tray in the centre of a pre-heated oven. Once chicken balls are heated, leave to stand for 2 minutes and follow the guidelines below. Serve chicken balls and sweet & sour sauce together. Oven from frozen Instructions: Remove outer sleeve and film lid. Remove pot and place to one side. Sauce pot is not suitable for oven heating. 190°C/Fan 170°C/Gas 5 30 mins Place foil tray on a baking tray in the centre of a pre-heated oven. Once chicken balls are heated, leave to stand for 2 minutes and follow the guidelines below. Serve chicken balls and sweet & sour sauce together. Microwave Instructions: Sweet & Sour Sauce: Peel film lid slightly, place sauce pot on microwaveable plate and heat. Chilled: 800W / 900W 15 secs Stir sauce thoroughly (from frozen). Serve chicken balls and sweet & sour sauce together. Microwave from frozen Instructions: Sweet & Sour Sauce: Peel film lid slightly, place sauce pot on microwaveable plate and heat. Chilled: 800W / 900W 30 secs Stir sauce thoroughly (from frozen). Serve chicken balls and sweet & sour sauce together. Produce of Made using Thai chicken. Number of uses 2 Servings Warnings Caution: Although every care has been taken to remove bones, some may remain. Recycling info Sleeve. RecyclenTray. RecyclenFilm. Recycle at large supermarketnPot. Recycle Return to Tesco Stores Ltd., Welwyn Garden City AL7 1GA, U.K Net Contents 310 g e Nutrition Typical Values Per 100g ½ of a pack (139g**) Energy 794kJ / 189kcal 1104kJ / 262kcal Fat 5.8g 8.0g Saturates 2.3g 3.1g Carbohydrate 21.8g 30.3g Sugars 5.0g 7.0g Fibre 0.8g 1.2g Protein 12.0g 16.6g Salt 0.74g 1.03g * Reference intake of an average adult (8400 kJ / 2000 kcal) - - When heated according to instructions. - - ** When heated according to instructions 310g typically weighs 278g. - - Safety information View more safety information Caution: Although every care has been taken to remove bones, some may remain.","cooking_instructions":"Oven. Instructions: Remove outer sleeve and film lid. Remove pot and place to one side. Sauce pot is not suitable for oven heating. 190°C/Fan 170°C/Gas 5 25 mins Place foil tray on a baking tray in the centre of a pre-heated oven. Once chicken balls are heated, leave to stand for 2 minutes and follow the guidelines below. Serve chicken balls and sweet & sour sauce together.. Oven from frozen. Instructions: Remove outer sleeve and film lid. Remove pot and place to one side. Sauce pot is not suitable for oven heating. 190°C/Fan 170°C/Gas 5 30 mins Place foil tray on a baking tray in the centre of a pre-heated oven. Once chicken balls are heated, leave to stand for 2 minutes and follow the guidelines below. Serve chicken balls and sweet & sour sauce together.. Microwave. Instructions: Sweet & Sour Sauce:. Peel film lid slightly, place sauce pot on microwaveable plate and heat.. Chilled: 800W / 900W 15 secs. Stir sauce thoroughly (from frozen).. Serve chicken balls and sweet & sour sauce together.. Microwave from frozen. Instructions: Sweet & Sour Sauce:. Peel film lid slightly, place sauce pot on microwaveable plate and heat.. Chilled: 800W / 900W 30 secs. Stir sauce thoroughly (from frozen).. Serve chicken balls and sweet & sour sauce together.","storage":"Suitable for home freezing. Ideally freeze as soon as possible after purchase but always by 'use by' date shown. nKeep refrigerated.","allergy_info":"May contain sesame seeds.For allergens, including cereals containing gluten, see ingredients in bold.","produce_of":"Made using Thai chicken.","number_of_uses":"2 Servings","recycling_info":"Sleeve. RecyclenTray. RecyclenFilm. Recycle at large supermarketnPot. Recycle","return_to":"Tesco Stores Ltd.,. Welwyn Garden City AL7 1GA,. U.K","net_content":"310 g e","nutrition_per_unit":[{"Typical Values":"Fat","Per 100g":"5.8g","½ of a pack (139g**)":"8.0g"},{"Typical Values":"Saturates","Per 100g":"2.3g","½ of a pack (139g**)":"3.1g"},{"Typical Values":"Carbohydrate","Per 100g":"21.8g","½ of a pack (139g**)":"30.3g"},{"Typical Values":"Sugars","Per 100g":"5.0g","½ of a pack (139g**)":"7.0g"},{"Typical Values":"Fibre","Per 100g":"0.8g","½ of a pack (139g**)":"1.2g"},{"Typical Values":"Protein","Per 100g":"12.0g","½ of a pack (139g**)":"16.6g"},{"Typical Values":"Salt","Per 100g":"0.74g","½ of a pack (139g**)":"1.03g"},{"Typical Values":"* Reference intake of an average adult (8400 kJ / 2000 kcal)","Per 100g":"-","½ of a pack (139g**)":"-"},{"Typical Values":"When heated according to instructions.","Per 100g":"-","½ of a pack (139g**)":"-"},{"Typical Values":"** When heated according to instructions 310g typically weighs 278g.","Per 100g":"-","½ of a pack (139g**)":"-"}],"gtin13":"05059512730979","sku":"313177093","timestamp":"2023-01-31T12:09:22Z"},{"title":"Tesco Tomato & Basil Flavoured Pulse Mix 25G","unit_price":"0.75","currency":"£","price_per_quantity":"3.00","quantity":"1","url":"https://www.tesco.com/groceries/en-GB/products/312573322","image":"https://digitalcontent.api.tesco.com/v2/media/ghs/fc69916c-bf00-48bc-879d-c3b3c04ba3fc/be47311b-8d6e-4b1e-9eff-d52aaefac561_691885092.jpeg?h=540&w=540","rating":"No ratings yet","category":"Fresh Food / Fresh Vegetables / Carrots & Root Vegetables","number_of_reviews":"","short_desc":"Any 3 for 2 Clubcard Price - Cheapest Product Free - Selected Tesco Dried Fruit Or Nuts Offer valid for delivery from 03/09/2022 until 31/12/2040","nutrition":[{"Energy":"520kJ, 125kcal","nutr_percent":"6%"},{"Fat":"7.2g","nutr_percent":"10%"},{"Saturates":"0.9g","nutr_percent":"5%"},{"Sugars":"0.6g","nutr_percent":"1%"},{"Salt":"0.11g","nutr_percent":"2%"}],"ingredients":"Broad Beans,. ,. ,. , Chicory Fibre, Rapeseed Oil, Black Pepper, Salt, Onion Powder, Maltodextrin, Red Pepper, Yeast Extract, Tomato Powder, Rice Flour, White Pepper, Sugar, Chilli Powder, Basil, Garlic Powder, Blueberry, Acidity Regulator (Citric Acid), Maize Starch, Pepper Extract, Parsley, Emulsifier (Sunflower Lecithins), Flavourings, Paprika Extract.","description":"Suitable for vegans Each pack Energy 520kJ 125kcal 6% of the reference intake Fat 7.2g high 10% of the reference intake Saturates 0.9g medium 5% of the reference intake Sugars 0.6g low 1% of the reference intake Salt 0.11g medium 2% of the reference intake of the reference intake * Typical values per 100g: Energy 2079kJ / 499kcal Product Description A mix of roasted broad beans with a tomato and basil seasoning with peppered peanuts, cashews and almonds. Tomato & Basil flavoured fava beans with peppered cashews, peanuts and almonds PULSE BITES Pack size: 25G Information Ingredients INGREDIENTS: Broad Beans, Peanut , Cashew Nut , Almond , Chicory Fibre, Rapeseed Oil, Black Pepper, Salt, Onion Powder, Maltodextrin, Red Pepper, Yeast Extract, Tomato Powder, Rice Flour, White Pepper, Sugar, Chilli Powder, Basil, Garlic Powder, Blueberry, Acidity Regulator (Citric Acid), Maize Starch, Pepper Extract, Parsley, Emulsifier (Sunflower Lecithins), Flavourings, Paprika Extract. Allergy Information May contain sesame seeds. Also, may contain other nuts., For allergens, see ingredients in bold. Legal information Packaged in a protective atmosphere Storage Store in a cool dry place. Number of uses 1 Servings Warnings Caution: This product may occasionally contain small fragments of shell..Warning: Not suitable for small children who can choke on nuts.. Recycling info Film. Recycle at large supermarket Return to Tesco Stores Ltd., Welwyn Garden City AL7 1GA, U.K Net Contents 25g e Nutrition Typical Values Per 100g Each pack (25g) Energy 2079kJ / 499kcal 520kJ / 125kcal Fat 28.9g 7.2g Saturates 3.7g 0.9g Carbohydrate 28.1g 7.0g Sugars 2.5g 0.6g Fibre 9.8g 2.5g Protein 26.7g 6.7g Salt 0.45g 0.11g * Reference intake of an average adult (8400 kJ / 2000 kcal) - - As sold - - Safety information View more safety information Caution: This product may occasionally contain small fragments of shell..Warning: Not suitable for small children who can choke on nuts..","cooking_instructions":"","storage":"Store in a cool dry place.","allergy_info":"May contain sesame seeds. Also, may contain other nuts., For allergens, see ingredients in bold.","produce_of":"","number_of_uses":"1 Servings","recycling_info":"Film. Recycle at large supermarket","return_to":"Tesco Stores Ltd.,. Welwyn Garden City AL7 1GA,. U.K","net_content":"25g e","nutrition_per_unit":[{"Typical Values":"Fat","Per 100g":"28.9g","Each pack (25g)":"7.2g"},{"Typical Values":"Saturates","Per 100g":"3.7g","Each pack (25g)":"0.9g"},{"Typical Values":"Carbohydrate","Per 100g":"28.1g","Each pack (25g)":"7.0g"},{"Typical Values":"Sugars","Per 100g":"2.5g","Each pack (25g)":"0.6g"},{"Typical Values":"Fibre","Per 100g":"9.8g","Each pack (25g)":"2.5g"},{"Typical Values":"Protein","Per 100g":"26.7g","Each pack (25g)":"6.7g"},{"Typical Values":"Salt","Per 100g":"0.45g","Each pack (25g)":"0.11g"},{"Typical Values":"* Reference intake of an average adult (8400 kJ / 2000 kcal)","Per 100g":"-","Each pack (25g)":"-"},{"Typical Values":"As sold","Per 100g":"-","Each pack (25g)":"-"}],"gtin13":"05059697724251","sku":"312573322","timestamp":"2023-01-31T12:09:25Z"},{"title":"Tesco Deli Peppered Beef 100G","unit_price":"2.50","currency":"£","price_per_quantity":"2.50","quantity":"1","url":"https://www.tesco.com/groceries/en-GB/products/312578334","image":"https://digitalcontent.api.tesco.com/v2/media/ghs/4b814fc1-6f19-45aa-a818-70f5ef328f0e/3d9dba72-67a9-4bff-8311-6eb04193ea40.jpeg?h=540&w=540","rating":"No ratings yet","category":"Fresh Food / Cooked Meats, Antipasti & Dips / Deli Counter","number_of_reviews":"","short_desc":"Any 3 for £6 Clubcard Price - Selected Cheese And Sliced Cooked Meats 30g - 220g Offer valid for delivery from 20/10/2022 until 30/04/2023","nutrition":[{"Energy":"130kJ, 31kcal","nutr_percent":"2%"},{"Fat":"0.5g","nutr_percent":"1%"},{"Saturates":"0.2g","nutr_percent":"1%"},{"Sugars":"<0.1g","nutr_percent":"<1%"},{"Salt":"0.17g","nutr_percent":"3%"}],"ingredients":"Beef, Stabilisers (Tetrapotassium Diphosphate, Pentasodium Triphosphate), Black Pepper, Salt, Mineral Sea Salt.","description":"One slice Energy 130kJ 31kcal 2% of the reference intake Fat 0.5g low 1% of the reference intake Saturates 0.2g low 1% of the reference intake Sugars <0.1g low <1% of the reference intake Salt 0.17g medium 3% of the reference intake of the reference intake * Typical values per 100g: Energy 520kJ / 123kcal Product Description Sliced, cooked and roasted topside of beef with black pepper. British topside of beef, slow cooked with cracked black peppercorns Pack size: 100G Information Ingredients INGREDIENTS: Beef, Stabilisers (Tetrapotassium Diphosphate, Pentasodium Triphosphate), Black Pepper, Salt, Mineral Sea Salt. Legal information Packaged in a protective atmosphere Storage Not suitable for freezing. Keep refrigerated. Once opened, consume within 2 days and by 'use by' date shown. Number of uses 4 Servings Recycling info Tray. RecyclenFilm. Recycle at large supermarket Return to Tesco Stores Ltd., Welwyn Garden City AL7 1GA, U.K Net Contents 100g e Nutrition Typical Values Per 100g One slice (25g) Energy 520kJ / 123kcal 130kJ / 31kcal Fat 2.1g 0.5g Saturates 0.9g 0.2g Carbohydrate 0.3g <0.1g Sugars 0.3g <0.1g Fibre 0.6g 0.2g Protein 25.5g 6.4g Salt 0.68g 0.17g * Reference intake of an average adult (8400 kJ / 2000 kcal) - - As sold - -","cooking_instructions":"","storage":"Not suitable for freezing. Keep refrigerated. Once opened, consume within 2 days and by 'use by' date shown.","allergy_info":"","produce_of":"","number_of_uses":"4 Servings","recycling_info":"Tray. RecyclenFilm. Recycle at large supermarket","return_to":"Tesco Stores Ltd.,. Welwyn Garden City AL7 1GA,. U.K","net_content":"100g e","nutrition_per_unit":[{"Typical Values":"Fat","Per 100g":"2.1g","One slice (25g)":"0.5g"},{"Typical Values":"Saturates","Per 100g":"0.9g","One slice (25g)":"0.2g"},{"Typical Values":"Carbohydrate","Per 100g":"0.3g","One slice (25g)":"<0.1g"},{"Typical Values":"Sugars","Per 100g":"0.3g","One slice (25g)":"<0.1g"},{"Typical Values":"Fibre","Per 100g":"0.6g","One slice (25g)":"0.2g"},{"Typical Values":"Protein","Per 100g":"25.5g","One slice (25g)":"6.4g"},{"Typical Values":"Salt","Per 100g":"0.68g","One slice (25g)":"0.17g"},{"Typical Values":"* Reference intake of an average adult (8400 kJ / 2000 kcal)","Per 100g":"-","One slice (25g)":"-"},{"Typical Values":"As sold","Per 100g":"-","One slice (25g)":"-"}],"gtin13":"05059697710148","sku":"312578334","timestamp":"2023-01-31T12:09:29Z"},{"title":"The Collective Dairy Free Banana Suckies 85G","unit_price":"1.00","currency":"£","price_per_quantity":"11.76","quantity":"1","url":"https://www.tesco.com/groceries/en-GB/products/312566982","image":"https://digitalcontent.api.tesco.com/v2/media/ghs/29f3a2bf-9286-4601-b1bb-aab6667e670b/ee675d87-0bd2-4cbb-938e-07afe3a9b71a.jpeg?h=540&w=540","rating":"5","category":"Fresh Food / Yoghurts / Dairy Free Yoghurt Alternatives","number_of_reviews":"2","short_desc":"","nutrition":[],"ingredients":"and Rice Base (Water,. (7.5%), Rice (2%)), Coconut Cream (11%), Water, Sugar, Cornflour, Banana Puree (3.5%), Coconut Oil, Natural Flavourings, Calcium (Tri-Calcium Phosphate), Gelling Agent (Pectin, Agar), Salt, Lemon Juice Concentrate, Vitamins (D2, B12), Live Cultures (L. Bulgaricus, S. Thermophilus)","description":"Suitable for vegans Product Description Live Oat, Coconut and Rice Yoghurt Alternative with Banana Hello friends, I'm Alfie and I love an adventure! Wanna hear a fun joke? What's is small, green and goes camping? A Brussel scout! Immune support+* Calcium for strong bones* *Calcium is needed for normal growth and development of bone in children, and vitamins D and B12 contribute to the normal function of the immune system, when consumed as part of a varied and healthy diet. No nasties* *No artificial flavours, colours and preservatives. Registered by the Vegan Society. Creamy blend of oat & coconut with real fruit No pips or bits Pack'd full of live cultures Dairy free Suitable for vegans Pack size: 85G Calcium is needed for normal growth and development of bone in children Vitamins D and B12 contribute to the normal function of the immune system Information Ingredients Oat and Rice Base (Water, Oats (7.5%), Rice (2%)), Coconut Cream (11%), Water, Sugar, Cornflour, Banana Puree (3.5%), Coconut Oil, Natural Flavourings, Calcium (Tri-Calcium Phosphate), Gelling Agent (Pectin, Agar), Salt, Lemon Juice Concentrate, Vitamins (D2, B12), Live Cultures (L. Bulgaricus, S. Thermophilus) Allergy Information For allergens, including Cereals containing Gluten, see ingredients in bold. Storage Keep refrigerated 0-5°C.One opened, keep refrigerated and eat within 1 day. Number of uses 1 serving per pouch Additives Free From Artificial Colours Free From Artificial Flavours Free From Artificial Preservatives Warnings WARNING: CAP = CHOKING HAZARD DO NOT LEAVE WITH CHILDREN UNDER 3 YRS UNSUPERVISED DUE TO SMALL PARTS Name and address The Collective, Westworks, 195 Wood Lane, London, W12 7FQ. EU & NI: Unit 186, Return to The Collective, Westworks, 195 Wood Lane, London, W12 7FQ. UK: 0800 169 7774 EU & NI: Unit 186, Moat House, 54 Bloomfield Av, Belfast, BT5 5AD. ROI: 1800 932 410 Lower age limit 3 Years Net Contents 85g ℮ Nutrition Typical Values Per 100g Per 85g Pouch Energy 499kJ/118kcal 424kJ/101kcal Fat 5.1g 4.3g - Of which Saturates 4.2g 3.6g Carbohydrate 17g 15g - Of which Sugars 6.7g 5.7g Protein 1.0g 0.8g Salt 0.16g 0.14g Calcium (RI%) 141mg (18%) 120mg (15%) Vitamin D (RI%) 0.88µg (18%) 0.75µg (15%) Vitamin B12 (RI%) 0.44µg (18%) 0.38µg (15%) RI = Reference intake of an average adult (8400kJ/2000kcal) - - 1 serving per pouch - - Safety information View more safety information WARNING: CAP = CHOKING HAZARD DO NOT LEAVE WITH CHILDREN UNDER 3 YRS UNSUPERVISED DUE TO SMALL PARTS","cooking_instructions":"","storage":"Keep refrigerated 0-5°C.One opened, keep refrigerated and eat within 1 day.","allergy_info":"For allergens, including Cereals containing Gluten, see ingredients in bold.","produce_of":"","number_of_uses":"1 serving per pouch","recycling_info":"","return_to":"The Collective,. Westworks,. 195 Wood Lane,. London,. W12 7FQ.. UK: 0800 169 7774. EU & NI: Unit 186,. Moat House,. 54 Bloomfield Av,. Belfast,. BT5 5AD.. ROI: 1800 932 410","net_content":"85g ℮","nutrition_per_unit":[{"Typical Values":"Fat","Per 100g":"5.1g","Per 85g Pouch":"4.3g"},{"Typical Values":"- Of which Saturates","Per 100g":"4.2g","Per 85g Pouch":"3.6g"},{"Typical Values":"Carbohydrate","Per 100g":"17g","Per 85g Pouch":"15g"},{"Typical Values":"- Of which Sugars","Per 100g":"6.7g","Per 85g Pouch":"5.7g"},{"Typical Values":"Protein","Per 100g":"1.0g","Per 85g Pouch":"0.8g"},{"Typical Values":"Salt","Per 100g":"0.16g","Per 85g Pouch":"0.14g"},{"Typical Values":"Calcium (RI%)","Per 100g":"141mg (18%)","Per 85g Pouch":"120mg (15%)"},{"Typical Values":"Vitamin D (RI%)","Per 100g":"0.88µg (18%)","Per 85g Pouch":"0.75µg (15%)"},{"Typical Values":"Vitamin B12 (RI%)","Per 100g":"0.44µg (18%)","Per 85g Pouch":"0.38µg (15%)"},{"Typical Values":"RI = Reference intake of an average adult (8400kJ/2000kcal)","Per 100g":"-","Per 85g Pouch":"-"},{"Typical Values":"1 serving per pouch","Per 100g":"-","Per 85g Pouch":"-"}],"gtin13":"05056138202026","sku":"312566982","timestamp":"2023-01-31T12:09:33Z"},{"title":"Tesco Organic Strawberries 227G","unit_price":"2.00","currency":"£","price_per_quantity":"8.81","quantity":"1","url":"https://www.tesco.com/groceries/en-GB/products/293104700","image":"https://digitalcontent.api.tesco.com/v2/media/ghs/6d1fbe29-9d2d-4f2e-8515-019f4c8bfa48/snapshotimagehandler_871012502.jpeg?h=540&w=540","rating":"5","category":"Fresh Food / Fresh Fruit / Berries & Cherries","number_of_reviews":"1","short_desc":"","nutrition":[],"ingredients":"","description":"Product Description Tesco Organic Strawberries 227G Pack size: 227G Information","cooking_instructions":"","storage":"","allergy_info":"","produce_of":"","number_of_uses":"","recycling_info":"","return_to":"","net_content":"","nutrition_per_unit":[],"gtin13":"00000003269763","sku":"293104700","timestamp":"2023-01-31T12:09:37Z"}]